Workbook
Name UPDATE: 'Data Sheet'!$E$1

Sheet Profit & Loss
A1: ='Data Sheet'!B1 -> TITAN COMPANY LTD | H1: =UPDATE | M1: SCREENER.IN
A3: Narration | B3: ='Data Sheet'!B16 -> 42460 | C3: ='Data Sheet'!C16 -> 42825 | D3: ='Data Sheet'!D16 -> 43190 | E3: ='Data Sheet'!E16 -> 43555 | F3: ='Data Sheet'!F16 -> 43921 | G3: ='Data Sheet'!G16 -> 44286 | H3: ='Data Sheet'!H16 -> 44651 | I3: ='Data Sheet'!I16 -> 45016 | ... K3: ='Data Sheet'!K16 -> 45747 | L3: Trailing | M3: Best Case | N3: Worst Case
A4: Sales | B4: ='Data Sheet'!B17 -> 11275.89 | C4: ='Data Sheet'!C17 -> 13260.83 | D4: ='Data Sheet'!D17 -> 16119.77 | E4: ='Data Sheet'!E17 -> 19778.52 | F4: ='Data Sheet'!F17 -> 21052 | G4: ='Data Sheet'!G17 -> 21644 | H4: ='Data Sheet'!H17 -> 28799 | I4: ='Data Sheet'!I17 -> 40575 | ... K4: ='Data Sheet'!K17 -> 60456 | L4: =SUM(Quarters!H4:K4) -> 75580 | M4: =$K4+M23*K4 -> 77409.348 | N4: =$K4+N23*L4 -> 75959.341
A5: Expenses | B5: =SUM('Data Sheet'!B18,'Data Sheet'!B20:B24, -1*'Data Sheet'!B19) -> 10336.56 | C5: =SUM('Data Sheet'!C18,'Data Sheet'!C20:C24, -1*'Data Sheet'!C19) -> 12096.93 | D5: =SUM('Data Sheet'!D18,'Data Sheet'!D20:D24, -1*'Data Sheet'!D19) -> 14475.57 | E5: =SUM('Data Sheet'!E18,'Data Sheet'!E20:E24, -1*'Data Sheet'!E19) -> 17784.73 | F5: =SUM('Data Sheet'!F18,'Data Sheet'!F20:F24, -1*'Data Sheet'!F19) -> 18589 | G5: =SUM('Data Sheet'!G18,'Data Sheet'!G20:G24, -1*'Data Sheet'!G19) -> 19919 | H5: =SUM('Data Sheet'!H18,'Data Sheet'!H20:H24, -1*'Data Sheet'!H19) -> 25455 | I5: =SUM('Data Sheet'!I18,'Data Sheet'!I20:I24, -1*'Data Sheet'!I19) -> 35693 | ... K5: =SUM('Data Sheet'!K18,'Data Sheet'!K20:K24, -1*'Data Sheet'!K19) -> 54762 | L5: =SUM(Quarters!H5:K5) -> 67625 | M5: =M4-M6 -> 69261.804 | N5: =N4-N6 -> 68166.393
A6: Operating Profit | B6: =B4-B5 -> 939.33 | C6: =C4-C5 -> 1163.9 | D6: =D4-D5 -> 1644.2 | E6: =E4-E5 -> 1993.79 | F6: =F4-F5 -> 2463 | G6: =G4-G5 -> 1725 | H6: =H4-H5 -> 3344 | I6: =I4-I5 -> 4882 | ... K6: =K4-K5 -> 5694 | L6: =SUM(Quarters!H6:K6) -> 7955 | M6: =M4*M24 -> 8147.5438 | N6: =N4*N24 -> 7792.9475
A7: Other Income | B7: ='Data Sheet'!B25 -> 69.33 | C7: ='Data Sheet'!C25 -> -42.38 | D7: ='Data Sheet'!D25 -> 69.93 | E7: ='Data Sheet'!E25 -> 178.48 | F7: ='Data Sheet'!F25 -> 153 | G7: ='Data Sheet'!G25 -> 180 | H7: ='Data Sheet'!H25 -> 177 | I7: ='Data Sheet'!I25 -> 306 | ... K7: ='Data Sheet'!K25 -> 487 | L7: =SUM(Quarters!H7:K7) -> 333 | M7: 0 | N7: 0
A8: Depreciation | B8: ='Data Sheet'!B26 -> 98.19 | C8: ='Data Sheet'!C26 -> 110.53 | D8: ='Data Sheet'!D26 -> 131.43 | E8: ='Data Sheet'!E26 -> 162.84 | F8: ='Data Sheet'!F26 -> 348 | G8: ='Data Sheet'!G26 -> 375 | H8: ='Data Sheet'!H26 -> 399 | I8: ='Data Sheet'!I26 -> 441 | ... K8: ='Data Sheet'!K26 -> 693 | L8: =SUM(Quarters!H8:K8) -> 763 | M8: =+$L8 -> 763 | N8: =+$L8 -> 763
A9: Interest | B9: ='Data Sheet'!B27 -> 42.36 | C9: ='Data Sheet'!C27 -> 37.74 | D9: ='Data Sheet'!D27 -> 52.92 | E9: ='Data Sheet'!E27 -> 52.54 | F9: ='Data Sheet'!F27 -> 166 | G9: ='Data Sheet'!G27 -> 203 | H9: ='Data Sheet'!H27 -> 218 | I9: ='Data Sheet'!I27 -> 300 | ... K9: ='Data Sheet'!K27 -> 953 | L9: =SUM(Quarters!H9:K9) -> 1082 | M9: =+$L9 -> 1082 | N9: =+$L9 -> 1082
A10: Profit before tax | B10: ='Data Sheet'!B28 -> 868.11 | C10: ='Data Sheet'!C28 -> 973.25 | D10: ='Data Sheet'!D28 -> 1529.78 | E10: ='Data Sheet'!E28 -> 1956.89 | F10: ='Data Sheet'!F28 -> 2102 | G10: ='Data Sheet'!G28 -> 1327 | H10: ='Data Sheet'!H28 -> 2904 | I10: ='Data Sheet'!I28 -> 4447 | ... K10: ='Data Sheet'!K28 -> 4535 | L10: =SUM(Quarters!H10:K10) -> 6443 | M10: =M6+M7-SUM(M8:M9) -> 6302.5438 | N10: =N6+N7-SUM(N8:N9) -> 5947.9475
A11: Tax | B11: ='Data Sheet'!B29 -> 191.59 | C11: ='Data Sheet'!C29 -> 275.97 | D11: ='Data Sheet'!D29 -> 427.87 | E11: ='Data Sheet'!E29 -> 568.24 | F11: ='Data Sheet'!F29 -> 609 | G11: ='Data Sheet'!G29 -> 353 | H11: ='Data Sheet'!H29 -> 706 | I11: ='Data Sheet'!I29 -> 1173 | ... K11: ='Data Sheet'!K29 -> 1198 | L11: =SUM(Quarters!H11:K11) -> 1677 | M11: =IF($L10>0,$L11/$L10,0) -> 0.26028248 | N11: =IF($L10>0,$L11/$L10,0) -> 0.26028248
A12: Net profit | B12: ='Data Sheet'!B30 -> 674.52 | C12: ='Data Sheet'!C30 -> 711.47 | D12: ='Data Sheet'!D30 -> 1130.09 | E12: ='Data Sheet'!E30 -> 1404.15 | F12: ='Data Sheet'!F30 -> 1501 | G12: ='Data Sheet'!G30 -> 973 | H12: ='Data Sheet'!H30 -> 2173 | I12: ='Data Sheet'!I30 -> 3250 | ... K12: ='Data Sheet'!K30 -> 3337 | L12: =SUM(Quarters!H12:K12) -> 4766 | M12: =M10-M11*M10 -> 4662.1021 | N12: =N10-N11*N10 -> 4399.801
A13: EPS | B13: =IF('Data Sheet'!B93>0,B12/'Data Sheet'!B93,0) -> 7.5976571 | C13: =IF('Data Sheet'!C93>0,C12/'Data Sheet'!C93,0) -> 8.0138545 | D13: =IF('Data Sheet'!D93>0,D12/'Data Sheet'!D93,0) -> 12.729106 | E13: =IF('Data Sheet'!E93>0,E12/'Data Sheet'!E93,0) -> 15.816062 | F13: =IF('Data Sheet'!F93>0,F12/'Data Sheet'!F93,0) -> 16.906961 | G13: =IF('Data Sheet'!G93>0,G12/'Data Sheet'!G93,0) -> 10.959676 | H13: =IF('Data Sheet'!H93>0,H12/'Data Sheet'!H93,0) -> 24.476233 | I13: =IF('Data Sheet'!I93>0,I12/'Data Sheet'!I93,0) -> 36.607344 | ... K13: =IF('Data Sheet'!K93>0,K12/'Data Sheet'!K93,0) -> 37.587294 | L13: =IF('Data Sheet'!$B6>0,'Profit & Loss'!L12/'Data Sheet'!$B6,0) -> 53.691305 | M13: =IF('Data Sheet'!$B6>0,'Profit & Loss'!M12/'Data Sheet'!$B6,0) -> 52.520845 | N13: =IF('Data Sheet'!$B6>0,'Profit & Loss'!N12/'Data Sheet'!$B6,0) -> 49.565895
A14: Price to earning | B14: =IF(B15>0,B15/B13,"") -> 44.592694 | C14: =IF(C15>0,C15/C13,"") -> 57.743749 | D14: =IF(D15>0,D15/D13,"") -> 74.027196 | E14: =IF(E15>0,E15/E13,"") -> 72.195594 | F14: =IF(F15>0,F15/F13,"") -> 55.225773 | G14: =IF(G15>0,G15/G13,"") -> 142.16205 | H14: =IF(H15>0,H15/H13,"") -> 103.61684 | I14: =IF(I15>0,I15/I13,"") -> 68.69933 | ... K14: =IF(K15>0,K15/K13,"") -> 81.499614 | L14: =IF(L13>0,L15/L13,0) -> 79.083569 | M14: =M25 -> 81.457056 | N14: =N25 -> 79.083569
A15: Price | B15: ='Data Sheet'!B90 -> 338.8 | C15: ='Data Sheet'!C90 -> 462.75 | D15: ='Data Sheet'!D90 -> 942.3 | E15: ='Data Sheet'!E90 -> 1141.85 | F15: ='Data Sheet'!F90 -> 933.7 | G15: ='Data Sheet'!G90 -> 1558.05 | H15: ='Data Sheet'!H90 -> 2536.15 | I15: ='Data Sheet'!I90 -> 2514.9 | ... K15: ='Data Sheet'!K90 -> 3063.35 | L15: ='Data Sheet'!B8 -> 4246.1 | M15: =M13*M14 -> 4278.1934 | N15: =N13*N14 -> 3919.8479
A17: RATIOS:
A18: Dividend Payout | B18: =IF('Data Sheet'!B30>0, 'Data Sheet'!B31/'Data Sheet'!B30, 0) -> 0.28956888 | C18: =IF('Data Sheet'!C30>0, 'Data Sheet'!C31/'Data Sheet'!C30, 0) -> 0.32444095 | D18: =IF('Data Sheet'!D30>0, 'Data Sheet'!D31/'Data Sheet'!D30, 0) -> 0.29459601 | E18: =IF('Data Sheet'!E30>0, 'Data Sheet'!E31/'Data Sheet'!E30, 0) -> 0.31613432 | F18: =IF('Data Sheet'!F30>0, 'Data Sheet'!F31/'Data Sheet'!F30, 0) -> 0.23717522 | G18: =IF('Data Sheet'!G30>0, 'Data Sheet'!G31/'Data Sheet'!G30, 0) -> 0.36587873 | H18: =IF('Data Sheet'!H30>0, 'Data Sheet'!H31/'Data Sheet'!H30, 0) -> 0.30717902 | I18: =IF('Data Sheet'!I30>0, 'Data Sheet'!I31/'Data Sheet'!I30, 0) -> 0.27384615 | ... K18: =IF('Data Sheet'!K30>0, 'Data Sheet'!K31/'Data Sheet'!K30, 0) -> 0.29337728
A19: OPM | B19: =IF(B6>0,B6/B4,0) -> 0.083304289 | C19: =IF(C6>0,C6/C4,0) -> 0.08776977 | D19: =IF(D6>0,D6/D4,0) -> 0.10199897 | E19: =IF(E6>0,E6/E4,0) -> 0.10080582 | F19: =IF(F6>0,F6/F4,0) -> 0.11699601 | G19: =IF(G6>0,G6/G4,0) -> 0.079698762 | H19: =IF(H6>0,H6/H4,0) -> 0.11611514 | I19: =IF(I6>0,I6/I4,0) -> 0.12032039 | ... L19: =IF(L6>0,L6/L4,0) -> 0.10525271
G22: TRENDS: | H22: 10 YEARS | I22: 7 YEARS | J22: 5 YEARS | K22: 3 YEARS | L22: RECENT | M22: BEST | N22: WORST
G23: Sales Growth | H23: =IF(B4=0,"",POWER($K4/B4,1/9)-1) -> 0.20512491 | I23: =IF(D4=0,"",POWER($K4/D4,1/7)-1) -> 0.20784585 | J23: =IF(F4=0,"",POWER($K4/F4,1/5)-1) -> 0.23489266 | K23: =IF(H4=0,"",POWER($K4/H4, 1/3)-1) -> 0.28042457 | L23: =IF(ISERROR(MAX(IF(J4=0,"",(K4-J4)/J4),IF(K4=0,"",(L4-K4)/K4))),"",MAX(IF(J4=0,"",(K4-J4)/J4),IF(K4=0,"",(L4-K4)/K4))) -> 0.25016541 | M23: =MAX(K23:L23) -> 0.28042457 | N23: =MIN(H23:L23) -> 0.20512491
G24: OPM | H24: =IF(SUM(B4:$K$4)=0,"",SUMPRODUCT(B19:$K$19,B4:$K$4)/SUM(B4:$K$4)) -> 0.10259367 | I24: =IF(SUM(E4:$K$4)=0,"",SUMPRODUCT(E19:$K$19,E4:$K$4)/SUM(E4:$K$4)) -> 0.10433438 | J24: =IF(SUM(G4:$K$4)=0,"",SUMPRODUCT(G19:$K$19,G4:$K$4)/SUM(G4:$K$4)) -> 0.10336299 | K24: =IF(SUM(I4:$K$4)=0, "", SUMPRODUCT(I19:$K$19,I4:$K$4)/SUM(I4:$K$4)) -> 0.10431581 | L24: =L19 -> 0.10525271 | M24: =MAX(K24:L24) -> 0.10525271 | N24: =MIN(H24:L24) -> 0.10259367
G25: Price to Earning | H25: =IF(ISERROR(AVERAGEIF(B14:$L14,">0")),"",AVERAGEIF(B14:$L14,">0")) -> 79.581102 | I25: =IF(ISERROR(AVERAGEIF(E14:$L14,">0")),"",AVERAGEIF(E14:$L14,">0")) -> 87.378561 | J25: =IF(ISERROR(AVERAGEIF(G14:$L14,">0")),"",AVERAGEIF(G14:$L14,">0")) -> 95.267853 | K25: =IF(ISERROR(AVERAGEIF(I14:$L14,">0")),"",AVERAGEIF(I14:$L14,">0")) -> 81.457056 | L25: =L14 -> 79.083569 | M25: =MAX(K25:L25) -> 81.457056 | N25: =MIN(H25:L25) -> 79.083569

Sheet Quarters
A1: ='Profit & Loss'!A1 -> TITAN COMPANY LTD | E1: =UPDATE | J1: SCREENER.IN
A3: Narration | B3: ='Data Sheet'!B41 -> 45199 | C3: ='Data Sheet'!C41 -> 45291 | D3: ='Data Sheet'!D41 -> 45382 | E3: ='Data Sheet'!E41 -> 45473 | F3: ='Data Sheet'!F41 -> 45565 | G3: ='Data Sheet'!G41 -> 45657 | H3: ='Data Sheet'!H41 -> 45747 | I3: ='Data Sheet'!I41 -> 45838 | ... K3: ='Data Sheet'!K41 -> 46022
A4: Sales | B4: ='Data Sheet'!B42 -> 12529 | C4: ='Data Sheet'!C42 -> 14164 | D4: ='Data Sheet'!D42 -> 12494 | E4: ='Data Sheet'!E42 -> 13266 | F4: ='Data Sheet'!F42 -> 14534 | G4: ='Data Sheet'!G42 -> 17740 | H4: ='Data Sheet'!H42 -> 14916 | I4: ='Data Sheet'!I42 -> 16523 | ... K4: ='Data Sheet'!K42 -> 25416
A5: Expenses | B5: ='Data Sheet'!B43 -> 11118 | C5: ='Data Sheet'!C43 -> 12599 | D5: ='Data Sheet'!D43 -> 11303 | E5: ='Data Sheet'!E43 -> 12019 | F5: ='Data Sheet'!F43 -> 13298 | G5: ='Data Sheet'!G43 -> 16066 | H5: ='Data Sheet'!H43 -> 13379 | I5: ='Data Sheet'!I43 -> 14693 | ... K5: ='Data Sheet'!K43 -> 22703
A6: Operating Profit | B6: ='Data Sheet'!B50 -> 1411 | C6: ='Data Sheet'!C50 -> 1565 | D6: ='Data Sheet'!D50 -> 1191 | E6: ='Data Sheet'!E50 -> 1247 | F6: ='Data Sheet'!F50 -> 1236 | G6: ='Data Sheet'!G50 -> 1674 | H6: ='Data Sheet'!H50 -> 1537 | I6: ='Data Sheet'!I50 -> 1830 | ... K6: ='Data Sheet'!K50 -> 2713
A7: Other Income | B7: ='Data Sheet'!B44 -> 125 | C7: ='Data Sheet'!C44 -> 136 | D7: ='Data Sheet'!D44 -> 159 | E7: ='Data Sheet'!E44 -> 120 | F7: ='Data Sheet'!F44 -> 123 | G7: ='Data Sheet'!G44 -> 128 | H7: ='Data Sheet'!H44 -> 116 | I7: ='Data Sheet'!I44 -> 105 | ... K7: ='Data Sheet'!K44 -> -1
A8: Depreciation | B8: ='Data Sheet'!B45 -> 144 | C8: ='Data Sheet'!C45 -> 154 | D8: ='Data Sheet'!D45 -> 158 | E8: ='Data Sheet'!E45 -> 164 | F8: ='Data Sheet'!F45 -> 171 | G8: ='Data Sheet'!G45 -> 175 | H8: ='Data Sheet'!H45 -> 183 | I8: ='Data Sheet'!I45 -> 184 | ... K8: ='Data Sheet'!K45 -> 207
A9: Interest | B9: ='Data Sheet'!B46 -> 140 | C9: ='Data Sheet'!C46 -> 169 | D9: ='Data Sheet'!D46 -> 201 | E9: ='Data Sheet'!E46 -> 230 | F9: ='Data Sheet'!F46 -> 240 | G9: ='Data Sheet'!G46 -> 231 | H9: ='Data Sheet'!H46 -> 252 | I9: ='Data Sheet'!I46 -> 271 | ... K9: ='Data Sheet'!K46 -> 282
A10: Profit before tax | B10: ='Data Sheet'!B47 -> 1252 | C10: ='Data Sheet'!C47 -> 1378 | D10: ='Data Sheet'!D47 -> 991 | E10: ='Data Sheet'!E47 -> 973 | F10: ='Data Sheet'!F47 -> 948 | G10: ='Data Sheet'!G47 -> 1396 | H10: ='Data Sheet'!H47 -> 1218 | I10: ='Data Sheet'!I47 -> 1480 | ... K10: ='Data Sheet'!K47 -> 2223
A11: Tax | B11: ='Data Sheet'!B48 -> 336 | C11: ='Data Sheet'!C48 -> 325 | D11: ='Data Sheet'!D48 -> 220 | E11: ='Data Sheet'!E48 -> 258 | F11: ='Data Sheet'!F48 -> 244 | G11: ='Data Sheet'!G48 -> 349 | H11: ='Data Sheet'!H48 -> 347 | I11: ='Data Sheet'!I48 -> 389 | ... K11: ='Data Sheet'!K48 -> 539
A12: Net profit | B12: ='Data Sheet'!B49 -> 915 | C12: ='Data Sheet'!C49 -> 1053 | D12: ='Data Sheet'!D49 -> 771 | E12: ='Data Sheet'!E49 -> 715 | F12: ='Data Sheet'!F49 -> 704 | G12: ='Data Sheet'!G49 -> 1047 | H12: ='Data Sheet'!H49 -> 871 | I12: ='Data Sheet'!I49 -> 1091 | ... K12: ='Data Sheet'!K49 -> 1684
A14: OPM | B14: =IF(B4>0,B6/B4,"") -> 0.11261872 | C14: =IF(C4>0,C6/C4,"") -> 0.11049139 | D14: =IF(D4>0,D6/D4,"") -> 0.095325756 | E14: =IF(E4>0,E6/E4,"") -> 0.093999698 | F14: =IF(F4>0,F6/F4,"") -> 0.085041971 | G14: =IF(G4>0,G6/G4,"") -> 0.094363021 | H14: =IF(H4>0,H6/H4,"") -> 0.10304371 | I14: =IF(I4>0,I6/I4,"") -> 0.11075471 | ... K14: =IF(K4>0,K6/K4,"") -> 0.10674378

Sheet Titan Beta Regression
B2: Regression Beta - 5 Years Monthly
B4: Titan Company Monthly Returns | F4: NIFTY Returns | I4: Beta Drifting
L5: Beta 1 | M5: =SLOPE(D8:D67,G8:G67) -> 1.1953036
B6: Date | C6: Closing Price | D6: Return | F6: Closing Price | G6: Return | I6: Levered Raw Beta | J6: =M7 -> 1.1953036 | L6: Beta 2 | M6: =_xlfn.COVARIANCE.S(D7:D67,G7:G67)/_xlfn.VAR.S(G7:G67) -> 1.1953036
B7: 44317 | C7: 1571.8 | F7: 15582.8 | I7: Raw Beta Weight | J7: 0.75 | L7: Beta 3 | M7: =M30 -> 1.1953036
B8: 44348 | C8: 1705.97 | D8: =C8/C7-1 -> 0.085360733 | F8: 15721.5 | G8: =F8/F7-1 -> 0.0089008394
B9: 44378 | C9: 1688.29 | D9: =C9/C8-1 -> -0.010363605 | F9: 15763.05 | G9: =F9/F8-1 -> 0.0026428776 | I9: Market Beta | J9: 1
B10: 44409 | C10: 1896.71 | D10: =C10/C9-1 -> 0.12345036 | F10: 17132.2 | G10: =F10/F9-1 -> 0.086858191 | I10: Market Beta Weight | J10: 0.25
B11: 44440 | C11: 2133.85 | D11: =C11/C10-1 -> 0.12502702 | F11: 17618.15 | G11: =F11/F10-1 -> 0.028364717
B12: 44470 | C12: 2352.68 | D12: =C12/C11-1 -> 0.10255173 | F12: 17671.65 | G12: =F12/F11-1 -> 0.0030366412 | I12: Adjusted Beta | J12: =(J6*J7)+(J9*J10) -> 1.1464777
B13: 44501 | C13: 2344.73 | D13: =C13/C12-1 -> -0.0033791251 | F13: 16983.2 | G13: =F13/F12-1 -> -0.038957879 | L13: SUMMARY OUTPUT
B14: 44531 | C14: 2489.73 | D14: =C14/C13-1 -> 0.061840809 | F14: 17354.05 | G14: =F14/F13-1 -> 0.021836285
B15: 44562 | C15: 2329.73 | D15: =C15/C14-1 -> -0.064263996 | F15: 17339.85 | G15: =F15/F14-1 -> -0.0008182528 | L15: Regression Statistics
B16: 44593 | C16: 2513.56 | D16: =C16/C15-1 -> 0.078906139 | F16: 16793.9 | G16: =F16/F15-1 -> -0.031485278 | L16: Multiple R | M16: 0.63417475
B17: 44621 | C17: 2503.3 | D17: =C17/C16-1 -> -0.00408186 | F17: 17464.75 | G17: =F17/F16-1 -> 0.039946052 | L17: R Square | M17: 0.40217762
B18: 44652 | C18: 2426.36 | D18: =C18/C17-1 -> -0.030735429 | F18: 17102.55 | G18: =F18/F17-1 -> -0.020738917 | L18: Adjusted R Square | M18: 0.39187034
B19: 44682 | C19: 2187.3 | D19: =C19/C18-1 -> -0.098526187 | F19: 16584.55 | G19: =F19/F18-1 -> -0.030287881 | L19: Standard Error | M19: 0.055886874
B20: 44713 | C20: 1916.1 | D20: =C20/C19-1 -> -0.12398848 | F20: 15780.25 | G20: =F20/F19-1 -> -0.048496944 | L20: Observations | M20: 60
B21: 44743 | C21: 2321.58 | D21: =C21/C20-1 -> 0.21161735 | F21: 17158.25 | G21: =F21/F20-1 -> 0.087324345
B22: 44774 | C22: 2580.01 | D22: =C22/C21-1 -> 0.11131643 | F22: 17759.3 | G22: =F22/F21-1 -> 0.035029796 | L22: ANOVA
B23: 44805 | C23: 2582.28 | D23: =C23/C22-1 -> 0.00087984155 | F23: 17094.35 | G23: =F23/F22-1 -> -0.037442354 | M23: df | N23: SS | O23: MS | P23: F | Q23: Significance F
B24: 44835 | C24: 2735.37 | D24: =C24/C23-1 -> 0.059284818 | F24: 18012.2 | G24: =F24/F23-1 -> 0.053693179 | L24: Regression | M24: 1 | N24: 0.12186903 | O24: 0.12186903 | P24: 39.018783 | Q24: 5.3279023e-08
B25: 44866 | C25: 2627.9 | D25: =C25/C24-1 -> -0.039289018 | F25: 18758.35 | G25: =F25/F24-1 -> 0.041424701 | L25: Residual | M25: 58 | N25: 0.18115388 | O25: 0.0031233427
B26: 44896 | C26: 2572.92 | D26: =C26/C25-1 -> -0.020921648 | F26: 18105.3 | G26: =F26/F25-1 -> -0.03481383 | L26: Total | M26: 59 | N26: 0.30302291
B27: 44927 | C27: 2354.66 | D27: =C27/C26-1 -> -0.084829688 | F27: 17662.15 | G27: =F27/F26-1 -> -0.024476258
B28: 44958 | C28: 2350.35 | D28: =C28/C27-1 -> -0.0018304129 | F28: 17303.95 | G28: =F28/F27-1 -> -0.020280657 | M28: Coefficients | N28: Standard Error | O28: t Stat | P28: P-value | Q28: Lower 95% | R28: Upper 95% | S28: Lower 95.0% | T28: Upper 95.0%
B29: 44986 | C29: 2491.11 | D29: =C29/C28-1 -> 0.059888953 | F29: 17359.75 | G29: =F29/F28-1 -> 0.0032246973 | L29: Intercept | M29: 0.01061252 | N29: 0.007345298 | O29: 1.4448046 | P29: 0.15389393 | Q29: -0.0040906912 | R29: 0.025315732 | S29: -0.0040906912 | T29: 0.025315732
B30: 45017 | C30: 2616.85 | D30: =C30/C29-1 -> 0.050475491 | F30: 18065 | G30: =F30/F29-1 -> 0.040625585 | L30: X Variable 1 | M30: 1.1953036 | N30: 0.19135568 | O30: 6.2465017 | P30: 5.3279023e-08 | Q30: 0.81226356 | R30: 1.5783436 | S30: 0.81226356 | T30: 1.5783436
B31: 45047 | C31: 2796.54 | D31: =C31/C30-1 -> 0.068666527 | F31: 18534.4 | G31: =F31/F30-1 -> 0.025983947
B32: 45078 | C32: 3018.81 | D32: =C32/C31-1 -> 0.079480358 | F32: 19189.05 | G32: =F32/F31-1 -> 0.035320809
B33: 45108 | C33: 2975.63 | D33: =C33/C32-1 -> -0.014303649 | F33: 19753.8 | G33: =F33/F32-1 -> 0.029430847
B34: 45139 | C34: 3085.04 | D34: =C34/C33-1 -> 0.036768684 | F34: 19253.8 | G34: =F34/F33-1 -> -0.025311586
B35: 45170 | C35: 3129.11 | D35: =C35/C34-1 -> 0.014285066 | F35: 19638.3 | G35: =F35/F34-1 -> 0.019970084
B36: 45200 | C36: 3169.71 | D36: =C36/C35-1 -> 0.012974935 | F36: 19079.6 | G36: =F36/F35-1 -> -0.028449509
B37: 45231 | C37: 3468.78 | D37: =C37/C36-1 -> 0.09435248 | F37: 20133.15 | G37: =F37/F36-1 -> 0.055218663
B38: 45261 | C38: 3652.47 | D38: =C38/C37-1 -> 0.052955218 | F38: 21731.4 | G38: =F38/F37-1 -> 0.079384001
B39: 45292 | C39: 3674.43 | D39: =C39/C38-1 -> 0.0060123697 | F39: 21725.7 | G39: =F39/F38-1 -> -0.00026229327
B40: 45323 | C40: 3601.74 | D40: =C40/C39-1 -> -0.01978266 | F40: 21982.8 | G40: =F40/F39-1 -> 0.011833911
B41: 45352 | C41: 3778.03 | D41: =C41/C40-1 -> 0.048945787 | F41: 22326.9 | G41: =F41/F40-1 -> 0.015653147
B42: 45383 | C42: 3566.81 | D42: =C42/C41-1 -> -0.055907444 | F42: 22604.85 | G42: =F42/F41-1 -> 0.012449108
... B67: 46118 | C67: 4246.1 | D67: =C67/C66-1 -> 0.036341892 | F67: 22968.25 | G67: =F67/F66-1 -> 0.011233605

Sheet Bluestone Jewel Regression
B2: Regression Beta - 5 Monthly
B4: Bluestone Jewel Monthly Returns | F4: NIFTY Returns | I4: Beta Drifting
L5: Beta 1 | M5: =SLOPE(D8:D67,G8:G67) -> -1.7078554
B6: Date | C6: Closing Price | D6: Return | F6: Closing Price | G6: Return | I6: Levered Raw Beta | J6: =M7 -> -1.7078554 | L6: Beta 2 | M6: =_xlfn.COVARIANCE.S(D7:D67,G7:G67)/_xlfn.VAR.S(G7:G67) -> -1.7078554 | R6: Date | S6: Adj Close
B7: 45870 | C7: 534.8 | F7: 15582.8 | I7: Raw Beta Weight | J7: 0.75 | L7: Beta 3 | M7: =M29 -> -1.7078554
B8: 45901 | C8: 599.65 | D8: =C8/C7-1 -> 0.12126028 | F8: 15721.5 | G8: =F8/F7-1 -> 0.0089008394
B9: 45931 | C9: 708 | D9: =C9/C8-1 -> 0.18068874 | F9: 15763.05 | G9: =F9/F8-1 -> 0.0026428776 | I9: Market Beta | J9: 1
B10: 45962 | C10: 558.1 | D10: =C10/C9-1 -> -0.21172316 | F10: 17132.2 | G10: =F10/F9-1 -> 0.086858191 | I10: Market Beta Weight | J10: 0.25
B11: 45992 | C11: 470.75 | D11: =C11/C10-1 -> -0.15651317 | F11: 17618.15 | G11: =F11/F10-1 -> 0.028364717
B12: 46023 | C12: 440.1 | D12: =C12/C11-1 -> -0.065108869 | F12: 17671.65 | G12: =F12/F11-1 -> 0.0030366412 | I12: Adjusted Beta | J12: =(J6*J7)+(J9*J10) -> -1.0308916 | L12: SUMMARY OUTPUT
B13: 46054 | C13: 437.45 | D13: =C13/C12-1 -> -0.0060213588 | F13: 16983.2 | G13: =F13/F12-1 -> -0.038957879
B14: 46082 | C14: 467.15 | D14: =C14/C13-1 -> 0.067893474 | F14: 17354.05 | G14: =F14/F13-1 -> 0.021836285 | L14: Regression Statistics
B15: 46113 | C15: 427.55 | D15: =C15/C14-1 -> -0.084769346 | F15: 17339.85 | G15: =F15/F14-1 -> -0.0008182528 | L15: Multiple R | M15: 0.49009433
B16: 46118 | C16: 427.45 | D16: =C16/C15-1 -> -0.00023389077 | F16: 16793.9 | G16: =F16/F15-1 -> -0.031485278 | L16: R Square | M16: 0.24019245
L17: Adjusted R Square | M17: 0.13164852
L18: Standard Error | M18: 0.11883109
L19: Observations | M19: 9
L21: ANOVA
M22: df | N22: SS | O22: MS | P22: F | Q22: Significance F
L23: Regression | M23: 1 | N23: 0.031247405 | O23: 0.031247405 | P23: 2.2128593 | Q23: 0.18046324
L24: Residual | M24: 7 | N24: 0.098845795 | O24: 0.014120828
L25: Total | M25: 8 | N25: 0.1300932
M27: Coefficients | N27: Standard Error | O27: t Stat | P27: P-value | Q27: Lower 95% | R27: Upper 95% | S27: Lower 95.0% | T27: Upper 95.0%
L28: Intercept | M28: -0.0019170067 | N28: 0.040915937 | O28: -0.046852322 | P28: 0.96393959 | Q28: -0.098667825 | R28: 0.094833811 | S28: -0.098667825 | T28: 0.094833811
L29: X Variable 1 | M29: -1.7078554 | N29: 1.1480854 | O29: -1.4875682 | P29: 0.18046324 | Q29: -4.4226461 | R29: 1.0069352 | S29: -4.4226461 | T29: 1.0069352

Sheet Kalyan J Regression
B2: Regression Beta - 5 Years Monthly
B4: Kalyan Jewellery Monthly Returns | F4: NIFTY Returns | I4: Beta Drifting
L5: Beta 1 | M5: =SLOPE(D8:D64,G8:G64) -> 0.057413536
B6: Date | C6: Closing Price | D6: Returns | F6: Closing Price | G6: Return | I6: Levered Raw Beta | J6: =M7 -> 0.057413536 | L6: Beta 2 | M6: =_xlfn.COVARIANCE.S(D7:D64,G7:G64)/_xlfn.VAR.S(G7:G64) -> 0.057413536
B7: 44317 | C7: 66.26 | F7: 15582.8 | I7: Raw Beta Weight | J7: 0.75 | L7: Beta 3 | M7: =M27 -> 0.057413536
B8: 44348 | C8: 77.62 | D8: =C8/C7-1 -> 0.17144582 | F8: 15721.5 | G8: =F8/F7-1 -> 0.0089008394
B9: 44378 | C9: 70.38 | D9: =C9/C8-1 -> -0.093274929 | F9: 15763.05 | G9: =F9/F8-1 -> 0.0026428776 | I9: Market Beta | J9: 1
B10: 44409 | C10: 66.56 | D10: =C10/C9-1 -> -0.054276783 | F10: 17132.2 | G10: =F10/F9-1 -> 0.086858191 | I10: Market Beta Weight | J10: 0.25 | L10: SUMMARY OUTPUT
B11: 44440 | C11: 72.31 | D11: =C11/C10-1 -> 0.086388221 | F11: 17618.15 | G11: =F11/F10-1 -> 0.028364717
B12: 44470 | C12: 75.63 | D12: =C12/C11-1 -> 0.045913428 | F12: 17671.65 | G12: =F12/F11-1 -> 0.0030366412 | I12: Adjusted Beta | J12: =(J6*J7)+(J9*J10) -> 0.29306015 | L12: Regression Statistics
B13: 44501 | C13: 66.51 | D13: =C13/C12-1 -> -0.12058707 | F13: 16983.2 | G13: =F13/F12-1 -> -0.038957879 | L13: Multiple R | M13: 0.014804427
B14: 44531 | C14: 67.9 | D14: =C14/C13-1 -> 0.020899113 | F14: 17354.05 | G14: =F14/F13-1 -> 0.021836285 | L14: R Square | M14: 0.00021917105
B15: 44562 | C15: 66.01 | D15: =C15/C14-1 -> -0.027835052 | F15: 17339.85 | G15: =F15/F14-1 -> -0.0008182528 | L15: Adjusted R Square | M15: -0.017958662
B16: 44593 | C16: 58.47 | D16: =C16/C15-1 -> -0.11422512 | F16: 16793.9 | G16: =F16/F15-1 -> -0.031485278 | L16: Standard Error | M16: 0.13884886
B17: 44621 | C17: 58.28 | D17: =C17/C16-1 -> -0.0032495297 | F17: 17464.75 | G17: =F17/F16-1 -> 0.039946052 | L17: Observations | M17: 57
B18: 44652 | C18: 60.41 | D18: =C18/C17-1 -> 0.036547701 | F18: 17102.55 | G18: =F18/F17-1 -> -0.020738917
B19: 44682 | C19: 59.66 | D19: =C19/C18-1 -> -0.012415163 | F19: 16584.55 | G19: =F19/F18-1 -> -0.030287881 | L19: ANOVA
B20: 44713 | C20: 59.42 | D20: =C20/C19-1 -> -0.0040227958 | F20: 15780.25 | G20: =F20/F19-1 -> -0.048496944 | M20: df | N20: SS | O20: MS | P20: F | Q20: Significance F
B21: 44743 | C21: 64.53 | D21: =C21/C20-1 -> 0.08599798 | F21: 17158.25 | G21: =F21/F20-1 -> 0.087324345 | L21: Regression | M21: 1 | N21: 0.00023244794 | O21: 0.00023244794 | P21: 0.01205705 | Q21: 0.91296402
B22: 44774 | C22: 80.99 | D22: =C22/C21-1 -> 0.25507516 | F22: 17759.3 | G22: =F22/F21-1 -> 0.035029796 | L22: Residual | M22: 55 | N22: 1.0603453 | O22: 0.019279005
B23: 44805 | C23: 95.52 | D23: =C23/C22-1 -> 0.17940486 | F23: 17094.35 | G23: =F23/F22-1 -> -0.037442354 | L23: Total | M23: 56 | N23: 1.0605777
B24: 44835 | C24: 101.67 | D24: =C24/C23-1 -> 0.064384422 | F24: 18012.2 | G24: =F24/F23-1 -> 0.053693179
B25: 44866 | C25: 105.05 | D25: =C25/C24-1 -> 0.033244812 | F25: 18758.35 | G25: =F25/F24-1 -> 0.041424701 | M25: Coefficients | N25: Standard Error | O25: t Stat | P25: P-value | Q25: Lower 95% | R25: Upper 95% | S25: Lower 95.0% | T25: Upper 95.0%
B26: 44896 | C26: 125.53 | D26: =C26/C25-1 -> 0.19495478 | F26: 18105.3 | G26: =F26/F25-1 -> -0.03481383 | L26: Intercept | M26: 0.041510436 | N26: 0.018991924 | O26: 2.1856889 | P26: 0.033113925 | Q26: 0.0034497709 | R26: 0.079571102 | S26: 0.0034497709 | T26: 0.079571102
B27: 44927 | C27: 117 | D27: =C27/C26-1 -> -0.067951884 | F27: 17662.15 | G27: =F27/F26-1 -> -0.024476258 | L27: X Variable 1 | M27: 0.057413536 | N27: 0.52287005 | O27: 0.1098046 | P27: 0.91296402 | Q27: -0.99044146 | R27: 1.1052685 | S27: -0.99044146 | T27: 1.1052685
B28: 44958 | C28: 112.73 | D28: =C28/C27-1 -> -0.036495726 | F28: 17303.95 | G28: =F28/F27-1 -> -0.020280657
B29: 44986 | C29: 104.5 | D29: =C29/C28-1 -> -0.073006298 | F29: 17359.75 | G29: =F29/F28-1 -> 0.0032246973
B30: 45017 | C30: 101.87 | D30: =C30/C29-1 -> -0.025167464 | F30: 18065 | G30: =F30/F29-1 -> 0.040625585
B31: 45047 | C31: 104.8 | D31: =C31/C30-1 -> 0.028762148 | F31: 18534.4 | G31: =F31/F30-1 -> 0.025983947
B32: 45078 | C32: 145.86 | D32: =C32/C31-1 -> 0.39179389 | F32: 19189.05 | G32: =F32/F31-1 -> 0.035320809
B33: 45108 | C33: 173.29 | D33: =C33/C32-1 -> 0.18805704 | F33: 19753.8 | G33: =F33/F32-1 -> 0.029430847
B34: 45139 | C34: 249.77 | D34: =C34/C33-1 -> 0.4413411 | F34: 19253.8 | G34: =F34/F33-1 -> -0.025311586
B35: 45200 | C35: 287.21 | D35: =C35/C34-1 -> 0.14989791 | F35: 19638.3 | G35: =F35/F34-1 -> 0.019970084
B36: 45231 | C36: 323.43 | D36: =C36/C35-1 -> 0.12610982 | F36: 19079.6 | G36: =F36/F35-1 -> -0.028449509
B37: 45261 | C37: 352.28 | D37: =C37/C36-1 -> 0.089200136 | F37: 20133.15 | G37: =F37/F36-1 -> 0.055218663
B38: 45292 | C38: 348.4 | D38: =C38/C37-1 -> -0.011013966 | F38: 21731.4 | G38: =F38/F37-1 -> 0.079384001
B39: 45323 | C39: 394.81 | D39: =C39/C38-1 -> 0.13320896 | F39: 21725.7 | G39: =F39/F38-1 -> -0.00026229327
... B64: 46118 | C64: 420.35 | D64: =C64/C63-1 -> 0.065931279 | F64: 25178.65 | G64: =F64/F63-1 -> -0.0056080709
F65: 22331.4
F66: 22713.1
F67: 22968.25

Sheet Thangamayil J Regression
B2: Regression Beta - 5 Years Monthly
B4: Thangamayil Monthly Returns | F4: NIFTY Returns | I4: Beta Drifting
L5: Beta 1 | M5: =SLOPE(D8:D67,G8:G67) -> 1.0684007
B6: Date | C6: Closing Price | D6: Returns | F6: Closing Price | G6: Return | I6: Levered Raw Beta | J6: =M7 -> 1.0684007 | L6: Beta 2 | M6: =_xlfn.COVARIANCE.S(D7:D67,G7:G67)/_xlfn.VAR.S(G7:G67) -> 1.0684007
B7: 44317 | C7: 382.07 | F7: 15582.8 | I7: Raw Beta Weight | J7: 0.75 | L7: Beta 3 | M7: =M29 -> 1.0684007
B8: 44348 | C8: 394.4 | D8: =C8/C7-1 -> 0.032271573 | F8: 15721.5 | G8: =F8/F7-1 -> 0.0089008394
B9: 44378 | C9: 422.93 | D9: =C9/C8-1 -> 0.072337728 | F9: 15763.05 | G9: =F9/F8-1 -> 0.0026428776 | I9: Market Beta | J9: 1
B10: 44409 | C10: 492.43 | D10: =C10/C9-1 -> 0.16432979 | F10: 17132.2 | G10: =F10/F9-1 -> 0.086858191 | I10: Market Beta Weight | J10: 0.25
B11: 44440 | C11: 539.13 | D11: =C11/C10-1 -> 0.094835814 | F11: 17618.15 | G11: =F11/F10-1 -> 0.028364717
B12: 44470 | C12: 628.59 | D12: =C12/C11-1 -> 0.165934 | F12: 17671.65 | G12: =F12/F11-1 -> 0.0030366412 | I12: Adjusted Beta | J12: =(J6*J7)+(J9*J10) -> 1.0513005 | L12: SUMMARY OUTPUT
B13: 44501 | C13: 672.47 | D13: =C13/C12-1 -> 0.069807028 | F13: 16983.2 | G13: =F13/F12-1 -> -0.038957879
B14: 44531 | C14: 666.99 | D14: =C14/C13-1 -> -0.0081490624 | F14: 17354.05 | G14: =F14/F13-1 -> 0.021836285 | L14: Regression Statistics
B15: 44562 | C15: 572.58 | D15: =C15/C14-1 -> -0.14154635 | F15: 17339.85 | G15: =F15/F14-1 -> -0.0008182528 | L15: Multiple R | M15: 0.27386735
B16: 44593 | C16: 554.04 | D16: =C16/C15-1 -> -0.032379755 | F16: 16793.9 | G16: =F16/F15-1 -> -0.031485278 | L16: R Square | M16: 0.075003325
B17: 44621 | C17: 530.74 | D17: =C17/C16-1 -> -0.042054725 | F17: 17464.75 | G17: =F17/F16-1 -> 0.039946052 | L17: Adjusted R Square | M17: 0.059055106
B18: 44652 | C18: 551.65 | D18: =C18/C17-1 -> 0.039397822 | F18: 17102.55 | G18: =F18/F17-1 -> -0.020738917 | L18: Standard Error | M18: 0.14388598
B19: 44682 | C19: 495.66 | D19: =C19/C18-1 -> -0.10149551 | F19: 16584.55 | G19: =F19/F18-1 -> -0.030287881 | L19: Observations | M19: 60
B20: 44713 | C20: 474.58 | D20: =C20/C19-1 -> -0.042529153 | F20: 15780.25 | G20: =F20/F19-1 -> -0.048496944
B21: 44743 | C21: 512.31 | D21: =C21/C20-1 -> 0.079501875 | F21: 17158.25 | G21: =F21/F20-1 -> 0.087324345 | L21: ANOVA
B22: 44774 | C22: 552.28 | D22: =C22/C21-1 -> 0.078019168 | F22: 17759.3 | G22: =F22/F21-1 -> 0.035029796 | M22: df | N22: SS | O22: MS | P22: F | Q22: Significance F
B23: 44805 | C23: 607.42 | D23: =C23/C22-1 -> 0.099840661 | F23: 17094.35 | G23: =F23/F22-1 -> -0.037442354 | L23: Regression | M23: 1 | N23: 0.097365541 | O23: 0.097365541 | P23: 4.7029281 | Q23: 0.034225209
B24: 44835 | C24: 477.05 | D24: =C24/C23-1 -> -0.21462909 | F24: 18012.2 | G24: =F24/F23-1 -> 0.053693179 | L24: Residual | M24: 58 | N24: 1.2007841 | O24: 0.020703175
B25: 44866 | C25: 499.08 | D25: =C25/C24-1 -> 0.046179646 | F25: 18758.35 | G25: =F25/F24-1 -> 0.041424701 | L25: Total | M25: 59 | N25: 1.2981497
B26: 44896 | C26: 535.19 | D26: =C26/C25-1 -> 0.07235313 | F26: 18105.3 | G26: =F26/F25-1 -> -0.03481383
B27: 44927 | C27: 519.1 | D27: =C27/C26-1 -> -0.030064089 | F27: 17662.15 | G27: =F27/F26-1 -> -0.024476258 | M27: Coefficients | N27: Standard Error | O27: t Stat | P27: P-value | Q27: Lower 95% | R27: Upper 95% | S27: Lower 95.0% | T27: Upper 95.0%
B28: 44958 | C28: 488.95 | D28: =C28/C27-1 -> -0.058081295 | F28: 17303.95 | G28: =F28/F27-1 -> -0.020280657 | L28: Intercept | M28: 0.040211089 | N28: 0.018911156 | O28: 2.1263158 | P28: 0.037744043 | Q28: 0.0023562977 | R28: 0.07806588 | S28: 0.0023562977 | T28: 0.07806588
B29: 44986 | C29: 494.2 | D29: =C29/C28-1 -> 0.010737294 | F29: 17359.75 | G29: =F29/F28-1 -> 0.0032246973 | L29: X Variable 1 | M29: 1.0684007 | N29: 0.49266307 | O29: 2.1686235 | P29: 0.034225209 | Q29: 0.082228451 | R29: 2.054573 | S29: 0.082228451 | T29: 2.054573
B30: 45017 | C30: 509.91 | D30: =C30/C29-1 -> 0.031788749 | F30: 18065 | G30: =F30/F29-1 -> 0.040625585
B31: 45047 | C31: 666.2 | D31: =C31/C30-1 -> 0.30650507 | F31: 18534.4 | G31: =F31/F30-1 -> 0.025983947
B32: 45078 | C32: 746.91 | D32: =C32/C31-1 -> 0.1211498 | F32: 19189.05 | G32: =F32/F31-1 -> 0.035320809
B33: 45108 | C33: 1253.91 | D33: =C33/C32-1 -> 0.67879664 | F33: 19753.8 | G33: =F33/F32-1 -> 0.029430847
B34: 45139 | C34: 1221.83 | D34: =C34/C33-1 -> -0.025583973 | F34: 19253.8 | G34: =F34/F33-1 -> -0.025311586
B35: 45170 | C35: 1221.38 | D35: =C35/C34-1 -> -0.00036830001 | F35: 19638.3 | G35: =F35/F34-1 -> 0.019970084
B36: 45200 | C36: 1412.32 | D36: =C36/C35-1 -> 0.15633136 | F36: 19079.6 | G36: =F36/F35-1 -> -0.028449509
B37: 45231 | C37: 1359.99 | D37: =C37/C36-1 -> -0.037052509 | F37: 20133.15 | G37: =F37/F36-1 -> 0.055218663
B38: 45261 | C38: 1472.34 | D38: =C38/C37-1 -> 0.082610902 | F38: 21731.4 | G38: =F38/F37-1 -> 0.079384001
B39: 45292 | C39: 1337.88 | D39: =C39/C38-1 -> -0.091324015 | F39: 21725.7 | G39: =F39/F38-1 -> -0.00026229327
B40: 45323 | C40: 1352.15 | D40: =C40/C39-1 -> 0.010666129 | F40: 21982.8 | G40: =F40/F39-1 -> 0.011833911
B41: 45352 | C41: 1275.05 | D41: =C41/C40-1 -> -0.057020301 | F41: 22326.9 | G41: =F41/F40-1 -> 0.015653147
... B67: 46118 | C67: 3752.9 | D67: =C67/C66-1 -> 0.059004458 | F67: 22968.25 | G67: =F67/F66-1 -> 0.011233605
P68: 45931 | Q68: 2169.6
P69: 45962 | Q69: 3254
P70: 45992 | Q70: 3222.1
P71: 46023 | Q71: 3320.6
P72: 46054 | Q72: 3959.2
P73: 46082 | Q73: 3425.9
P74: 46113 | Q74: 3543.8
P75: 46118 | Q75: 3752.9

Sheet P N Gadgil J Regression
B2: Regression Beta - 5 Years Monthly
B4: P N Gadgil Jewel Monthly Returns | F4: NIFTY Returns | I4: Beta Drifting | V4: Date | W4: Adj Close
L5: Beta 1 | M5: =SLOPE(D8:D113,G8:G113) -> -0.42304575
B6: Date | C6: Closing Price | D6: Returns | F6: Closing Price | G6: Return | I6: Levered Raw Beta | J6: =M7 -> -0.42304575 | L6: Beta 2 | M6: =_xlfn.COVARIANCE.S(D7:D113,G7:G113)/_xlfn.VAR.S(G7:G113) -> -0.42304575
B7: 45536 | C7: 749.15 | F7: 15582.8 | I7: Raw Beta Weight | J7: 0.75 | L7: Beta 3 | M7: =M29 -> -0.42304575
B8: 45566 | C8: 715.6 | D8: =C8/C7-1 -> -0.044784089 | F8: 15721.5 | G8: =F8/F7-1 -> 0.0089008394
B9: 45597 | C9: 681.2 | D9: =C9/C8-1 -> -0.048071548 | F9: 15763.05 | G9: =F9/F8-1 -> 0.0026428776 | I9: Market Beta | J9: 1
B10: 45627 | C10: 665.35 | D10: =C10/C9-1 -> -0.023267763 | F10: 17132.2 | G10: =F10/F9-1 -> 0.086858191 | I10: Market Beta Weight | J10: 0.25
B11: 45658 | C11: 564.8 | D11: =C11/C10-1 -> -0.15112347 | F11: 17618.15 | G11: =F11/F10-1 -> 0.028364717
B12: 45689 | C12: 537.95 | D12: =C12/C11-1 -> -0.047538952 | F12: 17671.65 | G12: =F12/F11-1 -> 0.0030366412 | I12: Adjusted Beta | J12: =(J6*J7)+(J9*J10) -> -0.067284316 | L12: SUMMARY OUTPUT
B13: 45717 | C13: 505.65 | D13: =C13/C12-1 -> -0.060042755 | F13: 16983.2 | G13: =F13/F12-1 -> -0.038957879
B14: 45748 | C14: 511 | D14: =C14/C13-1 -> 0.010580441 | F14: 17354.05 | G14: =F14/F13-1 -> 0.021836285 | L14: Regression Statistics
B15: 45778 | C15: 548.5 | D15: =C15/C14-1 -> 0.073385519 | F15: 17339.85 | G15: =F15/F14-1 -> -0.0008182528 | L15: Multiple R | M15: 0.29463052
B16: 45809 | C16: 580.7 | D16: =C16/C15-1 -> 0.058705561 | F16: 16793.9 | G16: =F16/F15-1 -> -0.031485278 | L16: R Square | M16: 0.086807143
B17: 45839 | C17: 584 | D17: =C17/C16-1 -> 0.0056827966 | F17: 17464.75 | G17: =F17/F16-1 -> 0.039946052 | L17: Adjusted R Square | M17: 0.036074206
B18: 45870 | C18: 572.15 | D18: =C18/C17-1 -> -0.020291096 | F18: 17102.55 | G18: =F18/F17-1 -> -0.020738917 | L18: Standard Error | M18: 0.058203981
B19: 45901 | C19: 603.5 | D19: =C19/C18-1 -> 0.054793323 | F19: 16584.55 | G19: =F19/F18-1 -> -0.030287881 | L19: Observations | M19: 20
B20: 45931 | C20: 647.7 | D20: =C20/C19-1 -> 0.073239437 | F20: 15780.25 | G20: =F20/F19-1 -> -0.048496944
B21: 45962 | C21: 629.65 | D21: =C21/C20-1 -> -0.02786784 | F21: 17158.25 | G21: =F21/F20-1 -> 0.087324345 | L21: ANOVA
B22: 45992 | C22: 607.45 | D22: =C22/C21-1 -> -0.035257683 | F22: 17759.3 | G22: =F22/F21-1 -> 0.035029796 | M22: df | N22: SS | O22: MS | P22: F | Q22: Significance F
B23: 46023 | C23: 549.8 | D23: =C23/C22-1 -> -0.09490493 | F23: 17094.35 | G23: =F23/F22-1 -> -0.037442354 | L23: Regression | M23: 1 | N23: 0.0057965667 | O23: 0.0057965667 | P23: 1.7110609 | Q23: 0.20730704
B24: 46054 | C24: 552 | D24: =C24/C23-1 -> 0.0040014551 | F24: 18012.2 | G24: =F24/F23-1 -> 0.053693179 | L24: Residual | M24: 18 | N24: 0.06097866 | O24: 0.0033877034
B25: 46082 | C25: 530.95 | D25: =C25/C24-1 -> -0.038134058 | F25: 18758.35 | G25: =F25/F24-1 -> 0.041424701 | L25: Total | M25: 19 | N25: 0.066775227
B26: 46113 | C26: 569 | D26: =C26/C25-1 -> 0.071663998 | F26: 18105.3 | G26: =F26/F25-1 -> -0.03481383
B27: 46118 | C27: 578.75 | D27: =C27/C26-1 -> 0.017135325 | F27: 17662.15 | G27: =F27/F26-1 -> -0.024476258 | M27: Coefficients | N27: Standard Error | O27: t Stat | P27: P-value | Q27: Lower 95% | R27: Upper 95% | S27: Lower 95.0% | T27: Upper 95.0%
L28: Intercept | M28: -0.0081109209 | N28: 0.013214525 | O28: -0.61378829 | P28: 0.54703464 | Q28: -0.035873608 | R28: 0.019651766 | S28: -0.035873608 | T28: 0.019651766
L29: X Variable 1 | M29: -0.42304575 | N29: 0.32341087 | O29: -1.3080753 | P29: 0.20730704 | Q29: -1.1025068 | R29: 0.25641527 | S29: -1.1025068 | T29: 0.25641527

Sheet PC Jeweller Regression
B2: Regression Beta - 5 Years Monthly
B4: PC Jeweller Monthly Returns | F4: NIFTY Returns | I4: Beta Drifting
L5: Beta 1 | M5: =SLOPE(D8:D113,G8:G113) -> 2.5407188
B6: Date | C6: Closing Price | D6: Returns | F6: Closing Price | G6: Return | I6: Levered Raw Beta | J6: =M7 -> 2.5407188 | L6: Beta 2 | M6: =_xlfn.COVARIANCE.S(D7:D113,G7:G113)/_xlfn.VAR.S(G7:G113) -> 2.5407188
B7: 44317 | C7: 2.7 | F7: 15582.8 | I7: Raw Beta Weight | J7: 0.75 | L7: Beta 3 | M7: =M29 -> 2.5407188
B8: 44348 | C8: 2.68 | D8: =C8/C7-1 -> -0.0074074074 | F8: 15721.5 | G8: =F8/F7-1 -> 0.0089008394
B9: 44378 | C9: 2.45 | D9: =C9/C8-1 -> -0.085820896 | F9: 15763.05 | G9: =F9/F8-1 -> 0.0026428776 | I9: Market Beta | J9: 1
B10: 44409 | C10: 2.28 | D10: =C10/C9-1 -> -0.069387755 | F10: 17132.2 | G10: =F10/F9-1 -> 0.086858191 | I10: Market Beta Weight | J10: 0.25
B11: 44440 | C11: 2.66 | D11: =C11/C10-1 -> 0.16666667 | F11: 17618.15 | G11: =F11/F10-1 -> 0.028364717
B12: 44470 | C12: 2.76 | D12: =C12/C11-1 -> 0.037593985 | F12: 17671.65 | G12: =F12/F11-1 -> 0.0030366412 | I12: Adjusted Beta | J12: =(J6*J7)+(J9*J10) -> 2.1555391 | L12: SUMMARY OUTPUT
B13: 44501 | C13: 2.35 | D13: =C13/C12-1 -> -0.14855072 | F13: 16983.2 | G13: =F13/F12-1 -> -0.038957879
B14: 44531 | C14: 2.69 | D14: =C14/C13-1 -> 0.14468085 | F14: 17354.05 | G14: =F14/F13-1 -> 0.021836285 | L14: Regression Statistics
B15: 44562 | C15: 2.63 | D15: =C15/C14-1 -> -0.022304833 | F15: 17339.85 | G15: =F15/F14-1 -> -0.0008182528 | L15: Multiple R | M15: 0.37595635
B16: 44593 | C16: 2.02 | D16: =C16/C15-1 -> -0.23193916 | F16: 16793.9 | G16: =F16/F15-1 -> -0.031485278 | L16: R Square | M16: 0.14134318
B17: 44621 | C17: 2.09 | D17: =C17/C16-1 -> 0.034653465 | F17: 17464.75 | G17: =F17/F16-1 -> 0.039946052 | L17: Adjusted R Square | M17: 0.12627902
B18: 44652 | C18: 2.2 | D18: =C18/C17-1 -> 0.052631579 | F18: 17102.55 | G18: =F18/F17-1 -> -0.020738917 | L18: Standard Error | M18: 0.24222439
B19: 44682 | C19: 2.02 | D19: =C19/C18-1 -> -0.081818182 | F19: 16584.55 | G19: =F19/F18-1 -> -0.030287881 | L19: Observations | M19: 59
B20: 44713 | C20: 2.31 | D20: =C20/C19-1 -> 0.14356436 | F20: 15780.25 | G20: =F20/F19-1 -> -0.048496944
B21: 44743 | C21: 4.68 | D21: =C21/C20-1 -> 1.025974 | F21: 17158.25 | G21: =F21/F20-1 -> 0.087324345 | L21: ANOVA
B22: 44774 | C22: 7.14 | D22: =C22/C21-1 -> 0.52564103 | F22: 17759.3 | G22: =F22/F21-1 -> 0.035029796 | M22: df | N22: SS | O22: MS | P22: F | Q22: Significance F
B23: 44805 | C23: 8.39 | D23: =C23/C22-1 -> 0.17507003 | F23: 17094.35 | G23: =F23/F22-1 -> -0.037442354 | L23: Regression | M23: 1 | N23: 0.55051078 | O23: 0.55051078 | P23: 9.3827485 | Q23: 0.0033411863
B24: 44835 | C24: 10.39 | D24: =C24/C23-1 -> 0.23837902 | F24: 18012.2 | G24: =F24/F23-1 -> 0.053693179 | L24: Residual | M24: 57 | N24: 3.3443414 | O24: 0.058672656
B25: 44866 | C25: 7.89 | D25: =C25/C24-1 -> -0.24061598 | F25: 18758.35 | G25: =F25/F24-1 -> 0.041424701 | L25: Total | M25: 58 | N25: 3.8948522
B26: 44896 | C26: 8.34 | D26: =C26/C25-1 -> 0.057034221 | F26: 18105.3 | G26: =F26/F25-1 -> -0.03481383
B27: 44927 | C27: 5.05 | D27: =C27/C26-1 -> -0.39448441 | F27: 17662.15 | G27: =F27/F26-1 -> -0.024476258 | M27: Coefficients | N27: Standard Error | O27: t Stat | P27: P-value | Q27: Lower 95% | R27: Upper 95% | S27: Lower 95.0% | T27: Upper 95.0%
B28: 44958 | C28: 2.71 | D28: =C28/C27-1 -> -0.46336634 | F28: 17303.95 | G28: =F28/F27-1 -> -0.020280657 | L28: Intercept | M28: 0.028790518 | N28: 0.03208478 | O28: 0.89732635 | P28: 0.37331934 | Q28: -0.035458145 | R28: 0.093039182 | S28: -0.035458145 | T28: 0.093039182
B29: 44986 | C29: 2.67 | D29: =C29/C28-1 -> -0.014760148 | F29: 17359.75 | G29: =F29/F28-1 -> 0.0032246973 | L29: X Variable 1 | M29: 2.5407188 | N29: 0.82945257 | O29: 3.0631272 | P29: 0.0033411863 | Q29: 0.87976863 | R29: 4.2016689 | S29: 0.87976863 | T29: 4.2016689
B30: 45017 | C30: 2.55 | D30: =C30/C29-1 -> -0.04494382 | F30: 18065 | G30: =F30/F29-1 -> 0.040625585
B31: 45047 | C31: 2.35 | D31: =C31/C30-1 -> -0.078431373 | F31: 18534.4 | G31: =F31/F30-1 -> 0.025983947
B32: 45078 | C32: 2.63 | D32: =C32/C31-1 -> 0.11914894 | F32: 19189.05 | G32: =F32/F31-1 -> 0.035320809
B33: 45108 | C33: 2.93 | D33: =C33/C32-1 -> 0.11406844 | F33: 19753.8 | G33: =F33/F32-1 -> 0.029430847
B34: 45139 | C34: 2.66 | D34: =C34/C33-1 -> -0.092150171 | F34: 19253.8 | G34: =F34/F33-1 -> -0.025311586
B35: 45170 | C35: 2.62 | D35: =C35/C34-1 -> -0.015037594 | F35: 19638.3 | G35: =F35/F34-1 -> 0.019970084
B36: 45200 | C36: 2.94 | D36: =C36/C35-1 -> 0.1221374 | F36: 19079.6 | G36: =F36/F35-1 -> -0.028449509
B37: 45231 | C37: 2.81 | D37: =C37/C36-1 -> -0.044217687 | F37: 20133.15 | G37: =F37/F36-1 -> 0.055218663
B38: 45261 | C38: 4.67 | D38: =C38/C37-1 -> 0.66192171 | F38: 21731.4 | G38: =F38/F37-1 -> 0.079384001
B39: 45292 | C39: 5.52 | D39: =C39/C38-1 -> 0.18201285 | F39: 21725.7 | G39: =F39/F38-1 -> -0.00026229327
B40: 45323 | C40: 5.78 | D40: =C40/C39-1 -> 0.047101449 | F40: 21982.8 | G40: =F40/F39-1 -> 0.011833911
B41: 45352 | C41: 5.38 | D41: =C41/C40-1 -> -0.069204152 | F41: 22326.9 | G41: =F41/F40-1 -> 0.015653147
... B66: 46118 | C66: 8.46 | D66: =C66/C65-1 -> 0.03045067 | F66: 22713.1 | G66: =F66/F65-1 -> 0.017092524

Sheet Rm
B2: Return on Markets
B4: Year | C4: Annual
B5: 2000 | C5: -0.1465 | E5: Average Return | G5: =AVERAGE(C5:C30) -> 0.15149231
B6: 2001 | C6: -0.1618 | E6: Dividend Yield | G6: 1.16% 1
B7: 2002 | C7: 0.0325 | E7: Total Market Return | G7: =SUM(G5:G6) -> 0.15149231
B8: 2003 | C8: 0.719
B9: 2004 | C9: 0.1068
B10: 2005 | C10: 0.3634
B11: 2006 | C11: 0.3983
B12: 2007 | C12: 0.5477
B13: 2008 | C13: -0.5179
B14: 2009 | C14: 0.7576
B15: 2010 | C15: 0.1795
B16: 2011 | C16: -0.2462
B17: 2012 | C17: 0.277
B18: 2013 | C18: 0.0676
B19: 2014 | C19: 0.3139
... B30: 2025 | C30: 0.1051

Sheet Beta - Comps
B2: S.No. | C2: Name | D2: CMP Rs. | E2: Mar Cap Rs.Cr. | F2: Debt Rs.Cr. | G2: Debt / Eq
B3: 1 | C3: Titan Company | D3: 4246.1 | E3: 376912.29 | F3: 12465 | G3: 0.97
B4: 2 | C4: Kalyan Jewellers | D4: 420.35 | E4: 43400.23 | F4: 5334.96 | G4: 1
B5: 3 | C5: Thangamayil Jew. | D5: 3752.9 | E5: 11659.68 | F5: 1124.35 | G5: 0.96
B6: 4 | C6: P N Gadgil Jewe. | D6: 578.75 | E6: 7904.82 | F6: 1291.13 | G6: 0.76
B7: 5 | C7: PC Jeweller | D7: 8.46 | E7: 7054.05 | F7: 1594.49 | G7: 0.22
B8: 6 | C8: Bluestone Jewel | D8: 427.45 | E8: 6494.97 | F8: 1889.28 | G8: 1.12

Sheet Financials>

Sheet HistoricalFS
B2: ="Historical Financial Statement - "&'Data Sheet'!B1 -> Historical Financial Statement - TITAN COMPANY LTD
B3: Years | C3: ='Data Sheet'!B16 -> 42460 | D3: ='Data Sheet'!C16 -> 42825 | E3: ='Data Sheet'!D16 -> 43190 | F3: ='Data Sheet'!E16 -> 43555 | G3: ='Data Sheet'!F16 -> 43921 | H3: ='Data Sheet'!G16 -> 44286 | I3: ='Data Sheet'!H16 -> 44651 | J3: ='Data Sheet'!I16 -> 45016 | ... L3: ='Data Sheet'!K16 -> 45747 | M3: LTM
A5: # | B5: Income Statement
B6: Sales | C6: =IFERROR('Data Sheet'!B17,0) -> 11275.89 | D6: =IFERROR('Data Sheet'!C17,0) -> 13260.83 | E6: =IFERROR('Data Sheet'!D17,0) -> 16119.77 | F6: =IFERROR('Data Sheet'!E17,0) -> 19778.52 | G6: =IFERROR('Data Sheet'!F17,0) -> 21052 | H6: =IFERROR('Data Sheet'!G17,0) -> 21644 | I6: =IFERROR('Data Sheet'!H17,0) -> 28799 | J6: =IFERROR('Data Sheet'!I17,0) -> 40575 | ... L6: =IFERROR('Data Sheet'!K17,0) -> 60456 | M6: =IFERROR(SUM('Data Sheet'!H42:K42),0) -> 75580
B7: Sales Growth | C7: - | D7: =D6/C6-1 -> 0.176034 | E7: =E6/D6-1 -> 0.21559284 | F7: =F6/E6-1 -> 0.22697284 | G7: =G6/F6-1 -> 0.064387022 | H7: =H6/G6-1 -> 0.028120844 | I7: =I6/H6-1 -> 0.3305766 | J7: =J6/I6-1 -> 0.40890309 | K7: =K6/J6-1 -> 0.25900185 | ... M7: =M6/L6-1 -> 0.25016541
B9: COGS | C9: =IFERROR(SUM('Data Sheet'!B18,'Data Sheet'!B20:B22)-1*'Data Sheet'!B19,0) -> 9183.33 | D9: =IFERROR(SUM('Data Sheet'!C18,'Data Sheet'!C20:C22)-1*'Data Sheet'!C19,0) -> 10606.01 | E9: =IFERROR(SUM('Data Sheet'!D18,'Data Sheet'!D20:D22)-1*'Data Sheet'!D19,0) -> 12762.63 | F9: =IFERROR(SUM('Data Sheet'!E18,'Data Sheet'!E20:E22)-1*'Data Sheet'!E19,0) -> 15660.48 | G9: =IFERROR(SUM('Data Sheet'!F18,'Data Sheet'!F20:F22)-1*'Data Sheet'!F19,0) -> 16626 | H9: =IFERROR(SUM('Data Sheet'!G18,'Data Sheet'!G20:G22)-1*'Data Sheet'!G19,0) -> 17661 | I9: =IFERROR(SUM('Data Sheet'!H18,'Data Sheet'!H20:H22)-1*'Data Sheet'!H19,0) -> 23225 | J9: =IFERROR(SUM('Data Sheet'!I18,'Data Sheet'!I20:I22)-1*'Data Sheet'!I19,0) -> 32295 | ... L9: =IFERROR(SUM('Data Sheet'!K18,'Data Sheet'!K20:K22)-1*'Data Sheet'!K19,0) -> 50024 | M9: =IFERROR(SUM('Data Sheet'!H43:K43),0) -> 67625
B10: COGS % Sales | C10: =C9/C6 -> 0.81442174 | D10: =D9/D6 -> 0.79979986 | E10: =E9/E6 -> 0.79173772 | F10: =F9/F6 -> 0.79179231 | G10: =G9/G6 -> 0.78975869 | H10: =H9/H6 -> 0.81597671 | I10: =I9/I6 -> 0.80645161 | J10: =J9/J6 -> 0.79593346 | ... M10: =M9/M6 -> 0.89474729
B12: Gross Profit | C12: =C6-C9 -> 2092.56 | D12: =D6-D9 -> 2654.82 | E12: =E6-E9 -> 3357.14 | F12: =F6-F9 -> 4118.04 | G12: =G6-G9 -> 4426 | H12: =H6-H9 -> 3983 | I12: =I6-I9 -> 5574 | J12: =J6-J9 -> 8280 | ... M12: =M6-M9 -> 7955
B13: Gross Margins | C13: =C12/C6 -> 0.18557826 | D13: =D12/D6 -> 0.20020014 | E13: =E12/E6 -> 0.20826228 | F13: =F12/F6 -> 0.20820769 | G13: =G12/G6 -> 0.21024131 | H13: =H12/H6 -> 0.18402329 | I13: =I12/I6 -> 0.19354839 | J13: =J12/J6 -> 0.20406654 | ... M13: =M12/M6 -> 0.10525271
B15: Selling & General Expenses | C15: =IFERROR(SUM('Data Sheet'!B23:B24),0) -> 1153.23 | D15: =IFERROR(SUM('Data Sheet'!C23:C24),0) -> 1490.92 | E15: =IFERROR(SUM('Data Sheet'!D23:D24),0) -> 1712.94 | F15: =IFERROR(SUM('Data Sheet'!E23:E24),0) -> 2124.25 | G15: =IFERROR(SUM('Data Sheet'!F23:F24),0) -> 1963 | H15: =IFERROR(SUM('Data Sheet'!G23:G24),0) -> 2258 | I15: =IFERROR(SUM('Data Sheet'!H23:H24),0) -> 2230 | J15: =IFERROR(SUM('Data Sheet'!I23:I24),0) -> 3398 | ... L15: =IFERROR(SUM('Data Sheet'!K23:K24),0) -> 4738
B16: S&G Exp % Sales | C16: =C15/C6 -> 0.10227397 | D16: =D15/D6 -> 0.11243037 | E16: =E15/E6 -> 0.1062633 | F16: =F15/F6 -> 0.10740187 | G16: =G15/G6 -> 0.093245297 | H16: =H15/H6 -> 0.10432452 | I16: =I15/I6 -> 0.077433244 | J16: =J15/J6 -> 0.083746149 | ... M16: =M15/M6 -> 0
B18: EBITDA | C18: =C12-C15 -> 939.33 | D18: =D12-D15 -> 1163.9 | E18: =E12-E15 -> 1644.2 | F18: =F12-F15 -> 1993.79 | G18: =G12-G15 -> 2463 | H18: =H12-H15 -> 1725 | I18: =I12-I15 -> 3344 | J18: =J12-J15 -> 4882 | ... M18: =M12-M15 -> 7955
B19: EBITDA Margins | C19: =C18/C6 -> 0.083304289 | D19: =D18/D6 -> 0.08776977 | E19: =E18/E6 -> 0.10199897 | F19: =F18/F6 -> 0.10080582 | G19: =G18/G6 -> 0.11699601 | H19: =H18/H6 -> 0.079698762 | I19: =I18/I6 -> 0.11611514 | J19: =J18/J6 -> 0.12032039 | ... M19: =M18/M6 -> 0.10525271
B21: Interest | C21: =IFERROR('Data Sheet'!B27,0) -> 42.36 | D21: =IFERROR('Data Sheet'!C27,0) -> 37.74 | E21: =IFERROR('Data Sheet'!D27,0) -> 52.92 | F21: =IFERROR('Data Sheet'!E27,0) -> 52.54 | G21: =IFERROR('Data Sheet'!F27,0) -> 166 | H21: =IFERROR('Data Sheet'!G27,0) -> 203 | I21: =IFERROR('Data Sheet'!H27,0) -> 218 | J21: =IFERROR('Data Sheet'!I27,0) -> 300 | ... L21: =IFERROR('Data Sheet'!K27,0) -> 953 | M21: =IFERROR(SUM('Data Sheet'!H46:K46),0) -> 1082
B22: Interest % Sales | C22: =C21/C6 -> 0.0037566879 | D22: =D21/D6 -> 0.0028459757 | E22: =E21/E6 -> 0.0032829253 | F22: =F21/F6 -> 0.0026564172 | G22: =G21/G6 -> 0.0078852366 | H22: =H21/H6 -> 0.0093790427 | I22: =I21/I6 -> 0.0075697073 | J22: =J21/J6 -> 0.0073937153 | ... M22: =M21/M6 -> 0.014315957
B24: Depreciation | C24: =IFERROR('Data Sheet'!B26,0) -> 98.19 | D24: =IFERROR('Data Sheet'!C26,0) -> 110.53 | E24: =IFERROR('Data Sheet'!D26,0) -> 131.43 | F24: =IFERROR('Data Sheet'!E26,0) -> 162.84 | G24: =IFERROR('Data Sheet'!F26,0) -> 348 | H24: =IFERROR('Data Sheet'!G26,0) -> 375 | I24: =IFERROR('Data Sheet'!H26,0) -> 399 | J24: =IFERROR('Data Sheet'!I26,0) -> 441 | ... L24: =IFERROR('Data Sheet'!K26,0) -> 693 | M24: =IFERROR(SUM('Data Sheet'!H45:K45),0) -> 763
B25: Depreciation % Sales | C25: =C24/C6 -> 0.0087079601 | D25: =D24/D6 -> 0.008335074 | E25: =E24/E6 -> 0.0081533421 | F25: =F24/F6 -> 0.0082331742 | G25: =G24/G6 -> 0.016530496 | H25: =H24/H6 -> 0.017325818 | I25: =I24/I6 -> 0.013854648 | J25: =J24/J6 -> 0.010868762 | ... M25: =M24/M6 -> 0.010095263
B27: Earnings Before Tax | C27: =IFERROR(C18-SUM(C24,C21),0) -> 798.78 | D27: =IFERROR(D18-SUM(D24,D21),0) -> 1015.63 | E27: =IFERROR(E18-SUM(E24,E21),0) -> 1459.85 | F27: =IFERROR(F18-SUM(F24,F21),0) -> 1778.41 | G27: =IFERROR(G18-SUM(G24,G21),0) -> 1949 | H27: =IFERROR(H18-SUM(H24,H21),0) -> 1147 | I27: =IFERROR(I18-SUM(I24,I21),0) -> 2727 | J27: =IFERROR(J18-SUM(J24,J21),0) -> 4141 | ... M27: =IFERROR(M18-SUM(M24,M21),0) -> 6110
B28: EBT % Sales | C28: =C27/C9 -> 0.08698152 | D28: =D27/D9 -> 0.095759857 | E28: =E27/E9 -> 0.11438473 | F28: =F27/F9 -> 0.11356038 | G28: =G27/G9 -> 0.11722603 | H28: =H27/H9 -> 0.06494536 | I28: =I27/I9 -> 0.11741658 | J28: =J27/J9 -> 0.12822418 | ... M28: =M27/M9 -> 0.090351201
B30: Tax | C30: =IFERROR('Data Sheet'!B29,0) -> 191.59 | D30: =IFERROR('Data Sheet'!C29,0) -> 275.97 | E30: =IFERROR('Data Sheet'!D29,0) -> 427.87 | F30: =IFERROR('Data Sheet'!E29,0) -> 568.24 | G30: =IFERROR('Data Sheet'!F29,0) -> 609 | H30: =IFERROR('Data Sheet'!G29,0) -> 353 | I30: =IFERROR('Data Sheet'!H29,0) -> 706 | J30: =IFERROR('Data Sheet'!I29,0) -> 1173 | ... L30: =IFERROR('Data Sheet'!K29,0) -> 1198 | M30: =IFERROR(SUM('Data Sheet'!H48:K48),0) -> 1677
B31: Effective Tax Rate | C31: =C30/C27 -> 0.23985328 | D31: =D30/D27 -> 0.27172297 | E31: =E30/E27 -> 0.29309176 | F31: =F30/F27 -> 0.31952137 | G31: =G30/G27 -> 0.31246793 | H31: =H30/H27 -> 0.30775937 | I31: =I30/I27 -> 0.25889256 | J31: =J30/J27 -> 0.28326491 | ... M31: =M30/M27 -> 0.27446809
B33: Net Profit | C33: =IFERROR(C27-C30,0) -> 607.19 | D33: =D27-D30 -> 739.66 | E33: =E27-E30 -> 1031.98 | F33: =F27-F30 -> 1210.17 | G33: =G27-G30 -> 1340 | H33: =H27-H30 -> 794 | I33: =I27-I30 -> 2021 | J33: =J27-J30 -> 2968 | K33: =K27-K30 -> 2962 | ... M33: =M27-M30 -> 4433
B34: Net Margins | C34: =C33/C6 -> 0.053848521 | D34: =D33/D6 -> 0.055777806 | E34: =E33/E6 -> 0.064019524 | F34: =F33/F6 -> 0.061186075 | G34: =G33/G6 -> 0.06365191 | H34: =H33/H6 -> 0.036684532 | I34: =I33/I6 -> 0.070176048 | J34: =J33/J6 -> 0.07314849 | ... M34: =M33/M6 -> 0.058653083
B36: No of Equity Shares | C36: =IFERROR('Data Sheet'!B93,0) -> 88.78 | D36: =IFERROR('Data Sheet'!C93,0) -> 88.78 | E36: =IFERROR('Data Sheet'!D93,0) -> 88.78 | F36: =IFERROR('Data Sheet'!E93,0) -> 88.78 | G36: =IFERROR('Data Sheet'!F93,0) -> 88.78 | H36: =IFERROR('Data Sheet'!G93,0) -> 88.78 | I36: =IFERROR('Data Sheet'!H93,0) -> 88.78 | J36: =IFERROR('Data Sheet'!I93,0) -> 88.78 | ... L36: =IFERROR('Data Sheet'!K93,0) -> 88.78 | M36: =L36 -> 88.78
B38: Earning Per Share | C38: =IFERROR(C33/C36,0) -> 6.8392656 | D38: =IFERROR(D33/D36,0) -> 8.3313809 | E38: =IFERROR(E33/E36,0) -> 11.624014 | F38: =IFERROR(F33/F36,0) -> 13.631111 | G38: =IFERROR(G33/G36,0) -> 15.09349 | H38: =IFERROR(H33/H36,0) -> 8.9434557 | I38: =IFERROR(I33/I36,0) -> 22.764136 | J38: =IFERROR(J33/J36,0) -> 33.430953 | ... M38: =IFERROR(M33/M36,0) -> 49.932417
B39: EPS Growth% | D39: =IFERROR(D38/C38-1,0) -> 0.21816894 | E39: =IFERROR(E38/D38-1,0) -> 0.39520861 | F39: =IFERROR(F38/E38-1,0) -> 0.17266807 | G39: =IFERROR(G38/F38-1,0) -> 0.10728245 | H39: =IFERROR(H38/G38-1,0) -> -0.40746269 | I39: =IFERROR(I38/H38-1,0) -> 1.5453401 | J39: =IFERROR(J38/I38-1,0) -> 0.46857991 | K39: =IFERROR(K38/J38-1,0) -> -0.0020215633 | ... M39: =IFERROR(M38/L38-1,0) -> 0.5554386
B41: Dividend Per Share | C41: =IFERROR('Data Sheet'!B31/HistoricalFS!C36,0) -> 2.2000451 | D41: =IFERROR('Data Sheet'!C31/HistoricalFS!D36,0) -> 2.6000225 | E41: =IFERROR('Data Sheet'!D31/HistoricalFS!E36,0) -> 3.7499437 | F41: =IFERROR('Data Sheet'!E31/HistoricalFS!F36,0) -> 5 | G41: =IFERROR('Data Sheet'!F31/HistoricalFS!G36,0) -> 4.0099121 | H41: =IFERROR('Data Sheet'!G31/HistoricalFS!H36,0) -> 4.0099121 | I41: =IFERROR('Data Sheet'!H31/HistoricalFS!I36,0) -> 7.5185853 | J41: =IFERROR('Data Sheet'!I31/HistoricalFS!J36,0) -> 10.02478 | ... L41: =IFERROR('Data Sheet'!K31/HistoricalFS!L36,0) -> 11.027258
B42: Dividend Payout ratio | C42: =IFERROR(C41/C38,0) -> 0.32167855 | D42: =IFERROR(D41/D38,0) -> 0.31207582 | E42: =IFERROR(E41/E38,0) -> 0.32260315 | F42: =IFERROR(F41/F38,0) -> 0.36680797 | G42: =IFERROR(G41/G38,0) -> 0.26567164 | H42: =IFERROR(H41/H38,0) -> 0.44836272 | I42: =IFERROR(I41/I38,0) -> 0.33028204 | J42: =IFERROR(J41/J38,0) -> 0.29986523 | ... L42: =IFERROR(L41/L38,0) -> 0.34350877
B44: Retained Earnings | C44: =IFERROR(IF(C38>C41,1-C42,0),0) -> 0.67832145 | D44: =IFERROR(IF(D38>D41,1-D42,0),0) -> 0.68792418 | E44: =IFERROR(IF(E38>E41,1-E42,0),0) -> 0.67739685 | F44: =IFERROR(IF(F38>F41,1-F42,0),0) -> 0.63319203 | G44: =IFERROR(IF(G38>G41,1-G42,0),0) -> 0.73432836 | H44: =IFERROR(IF(H38>H41,1-H42,0),0) -> 0.55163728 | I44: =IFERROR(IF(I38>I41,1-I42,0),0) -> 0.66971796 | J44: =IFERROR(IF(J38>J41,1-J42,0),0) -> 0.70013477 | ... L44: =IFERROR(IF(L38>L41,1-L42,0),0) -> 0.65649123
A46: # | B46: Balance Sheet
B47: Equity Share Capital | C47: =IFERROR('Data Sheet'!B57,0) -> 88.78 | D47: =IFERROR('Data Sheet'!C57,0) -> 88.78 | E47: =IFERROR('Data Sheet'!D57,0) -> 88.78 | F47: =IFERROR('Data Sheet'!E57,0) -> 88.78 | G47: =IFERROR('Data Sheet'!F57,0) -> 89 | H47: =IFERROR('Data Sheet'!G57,0) -> 89 | I47: =IFERROR('Data Sheet'!H57,0) -> 89 | J47: =IFERROR('Data Sheet'!I57,0) -> 89 | ... L47: =IFERROR('Data Sheet'!K57,0) -> 89
B48: Reserves | C48: =IFERROR('Data Sheet'!B58,0) -> 3417.5 | D48: =IFERROR('Data Sheet'!C58,0) -> 4143.6 | E48: =IFERROR('Data Sheet'!D58,0) -> 5001.1 | F48: =IFERROR('Data Sheet'!E58,0) -> 5981.37 | G48: =IFERROR('Data Sheet'!F58,0) -> 6580 | H48: =IFERROR('Data Sheet'!G58,0) -> 7408 | I48: =IFERROR('Data Sheet'!H58,0) -> 9214 | J48: =IFERROR('Data Sheet'!I58,0) -> 11762 | ... L48: =IFERROR('Data Sheet'!K58,0) -> 11535
B49: Borrowings | C49: =IFERROR('Data Sheet'!B59,0) -> 113.05 | D49: =IFERROR('Data Sheet'!C59,0) -> 1882.43 | E49: =IFERROR('Data Sheet'!D59,0) -> 1691.01 | F49: =IFERROR('Data Sheet'!E59,0) -> 2392.98 | G49: =IFERROR('Data Sheet'!F59,0) -> 3562 | H49: =IFERROR('Data Sheet'!G59,0) -> 5638 | I49: =IFERROR('Data Sheet'!H59,0) -> 7275 | J49: =IFERROR('Data Sheet'!I59,0) -> 9367 | ... L49: =IFERROR('Data Sheet'!K59,0) -> 20777
B50: Other Liabilities | C50: =IFERROR('Data Sheet'!B60,0) -> 2722.58 | D50: =IFERROR('Data Sheet'!C60,0) -> 2292.76 | E50: =IFERROR('Data Sheet'!D60,0) -> 2740.15 | F50: =IFERROR('Data Sheet'!E60,0) -> 3246.71 | G50: =IFERROR('Data Sheet'!F60,0) -> 3313 | H50: =IFERROR('Data Sheet'!G60,0) -> 3309 | I50: =IFERROR('Data Sheet'!H60,0) -> 4610 | J50: =IFERROR('Data Sheet'!I60,0) -> 5802 | ... L50: =IFERROR('Data Sheet'!K60,0) -> 8244
B51: Total Liabilities | C51: =IFERROR('Data Sheet'!B61,0) -> 6341.91 | D51: =IFERROR('Data Sheet'!C61,0) -> 8407.57 | E51: =IFERROR('Data Sheet'!D61,0) -> 9521.04 | F51: =IFERROR('Data Sheet'!E61,0) -> 11709.84 | G51: =IFERROR('Data Sheet'!F61,0) -> 13544 | H51: =IFERROR('Data Sheet'!G61,0) -> 16444 | I51: =IFERROR('Data Sheet'!H61,0) -> 21188 | J51: =IFERROR('Data Sheet'!I61,0) -> 27020 | ... L51: =IFERROR('Data Sheet'!K61,0) -> 40645
B53: Fixed Assets Net Block | C53: =IFERROR('Data Sheet'!B62,0) -> 770.54 | D53: =IFERROR('Data Sheet'!C62,0) -> 1188.72 | E53: =IFERROR('Data Sheet'!D62,0) -> 1473.81 | F53: =IFERROR('Data Sheet'!E62,0) -> 1566.63 | G53: =IFERROR('Data Sheet'!F62,0) -> 2633 | H53: =IFERROR('Data Sheet'!G62,0) -> 2523 | I53: =IFERROR('Data Sheet'!H62,0) -> 2544 | J53: =IFERROR('Data Sheet'!I62,0) -> 2998 | ... L53: =IFERROR('Data Sheet'!K62,0) -> 4062
B54: Capital Work in Progress | C54: =IFERROR('Data Sheet'!B63,0) -> 106.71 | D54: =IFERROR('Data Sheet'!C63,0) -> 152.07 | E54: =IFERROR('Data Sheet'!D63,0) -> 43.37 | F54: =IFERROR('Data Sheet'!E63,0) -> 31.77 | G54: =IFERROR('Data Sheet'!F63,0) -> 18 | H54: =IFERROR('Data Sheet'!G63,0) -> 32 | I54: =IFERROR('Data Sheet'!H63,0) -> 85 | J54: =IFERROR('Data Sheet'!I63,0) -> 144 | ... L54: =IFERROR('Data Sheet'!K63,0) -> 105
B55: Investments | C55: =IFERROR('Data Sheet'!B64,0) -> 30.41 | D55: =IFERROR('Data Sheet'!C64,0) -> 430.73 | E55: =IFERROR('Data Sheet'!D64,0) -> 35.99 | F55: =IFERROR('Data Sheet'!E64,0) -> 108.42 | G55: =IFERROR('Data Sheet'!F64,0) -> 158 | H55: =IFERROR('Data Sheet'!G64,0) -> 2824 | I55: =IFERROR('Data Sheet'!H64,0) -> 294 | J55: =IFERROR('Data Sheet'!I64,0) -> 2515 | ... L55: =IFERROR('Data Sheet'!K64,0) -> 1988
B56: Other Assets | C56: =IFERROR('Data Sheet'!B65-SUM('Data Sheet'!B67:B69),0) -> 678.25 | D56: =IFERROR('Data Sheet'!C65-SUM('Data Sheet'!C67:C69),0) -> 723.78 | E56: =IFERROR('Data Sheet'!D65-SUM('Data Sheet'!D67:D69),0) -> 1129.43 | F56: =IFERROR('Data Sheet'!E65-SUM('Data Sheet'!E67:E69),0) -> 1477.27 | G56: =IFERROR('Data Sheet'!F65-SUM('Data Sheet'!F67:F69),0) -> 1939 | H56: =IFERROR('Data Sheet'!G65-SUM('Data Sheet'!G67:G69),0) -> 1731 | I56: =IFERROR('Data Sheet'!H65-SUM('Data Sheet'!H67:H69),0) -> 2518 | J56: =IFERROR('Data Sheet'!I65-SUM('Data Sheet'!I67:I69),0) -> 2762 | ... L56: =IFERROR('Data Sheet'!K65-SUM('Data Sheet'!K67:K69),0) -> 3654
B57: Total Non Current Assets | C57: =IFERROR(SUM(C53:C56),0) -> 1585.91 | D57: =IFERROR(SUM(D53:D56),0) -> 2495.3 | E57: =IFERROR(SUM(E53:E56),0) -> 2682.6 | F57: =IFERROR(SUM(F53:F56),0) -> 3184.09 | G57: =IFERROR(SUM(G53:G56),0) -> 4748 | H57: =IFERROR(SUM(H53:H56),0) -> 7110 | I57: =IFERROR(SUM(I53:I56),0) -> 5441 | J57: =IFERROR(SUM(J53:J56),0) -> 8419 | ... L57: =IFERROR(SUM(L53:L56),0) -> 9809
B59: Receivables | C59: =IFERROR('Data Sheet'!B67,0) -> 192.5 | D59: =IFERROR('Data Sheet'!C67,0) -> 207.6 | E59: =IFERROR('Data Sheet'!D67,0) -> 295.69 | F59: =IFERROR('Data Sheet'!E67,0) -> 420.45 | G59: =IFERROR('Data Sheet'!F67,0) -> 312 | H59: =IFERROR('Data Sheet'!G67,0) -> 366 | I59: =IFERROR('Data Sheet'!H67,0) -> 565 | J59: =IFERROR('Data Sheet'!I67,0) -> 674 | ... L59: =IFERROR('Data Sheet'!K67,0) -> 1068
B60: Inventory | C60: =IFERROR('Data Sheet'!B68,0) -> 4447.15 | D60: =IFERROR('Data Sheet'!C68,0) -> 4925.74 | E60: =IFERROR('Data Sheet'!D68,0) -> 5924.84 | F60: =IFERROR('Data Sheet'!E68,0) -> 7038.82 | G60: =IFERROR('Data Sheet'!F68,0) -> 8103 | H60: =IFERROR('Data Sheet'!G68,0) -> 8408 | I60: =IFERROR('Data Sheet'!H68,0) -> 13609 | J60: =IFERROR('Data Sheet'!I68,0) -> 16584 | ... L60: =IFERROR('Data Sheet'!K68,0) -> 28184
B61: Cash & Bank | C61: =IFERROR('Data Sheet'!B69,0) -> 116.35 | D61: =IFERROR('Data Sheet'!C69,0) -> 778.93 | E61: =IFERROR('Data Sheet'!D69,0) -> 617.91 | F61: =IFERROR('Data Sheet'!E69,0) -> 1066.48 | G61: =IFERROR('Data Sheet'!F69,0) -> 381 | H61: =IFERROR('Data Sheet'!G69,0) -> 560 | I61: =IFERROR('Data Sheet'!H69,0) -> 1573 | J61: =IFERROR('Data Sheet'!I69,0) -> 1343 | ... L61: =IFERROR('Data Sheet'!K69,0) -> 1584
B62: Total Current Assets | C62: =IFERROR(SUM(C59:C61),0) -> 4756 | D62: =IFERROR(SUM(D59:D61),0) -> 5912.27 | E62: =IFERROR(SUM(E59:E61),0) -> 6838.44 | F62: =IFERROR(SUM(F59:F61),0) -> 8525.75 | G62: =IFERROR(SUM(G59:G61),0) -> 8796 | H62: =IFERROR(SUM(H59:H61),0) -> 9334 | I62: =IFERROR(SUM(I59:I61),0) -> 15747 | J62: =IFERROR(SUM(J59:J61),0) -> 18601 | ... L62: =IFERROR(SUM(L59:L61),0) -> 30836
B64: Total Assets | C64: =IFERROR(SUM(C62,C57),0) -> 6341.91 | D64: =IFERROR(SUM(D62,D57),0) -> 8407.57 | E64: =IFERROR(SUM(E62,E57),0) -> 9521.04 | F64: =IFERROR(SUM(F62,F57),0) -> 11709.84 | G64: =IFERROR(SUM(G62,G57),0) -> 13544 | H64: =IFERROR(SUM(H62,H57),0) -> 16444 | I64: =IFERROR(SUM(I62,I57),0) -> 21188 | J64: =IFERROR(SUM(J62,J57),0) -> 27020 | ... L64: =IFERROR(SUM(L62,L57),0) -> 40645
B66: Check | C66: =C64=C51 -> TRUE | D66: =D64=D51 -> TRUE | E66: =E64=E51 -> TRUE | F66: =F64=F51 -> TRUE | G66: =G64=G51 -> TRUE | H66: =H64=H51 -> TRUE | I66: =I64=I51 -> TRUE | J66: =J64=J51 -> TRUE | ... L66: =L64=L51 -> TRUE
A68: # | B68: Cash Flow Statements
B70: Cash from Operating Activity | C70: =IFERROR('Data Sheet'!B82,0) -> 576.09 | D70: =IFERROR('Data Sheet'!C82,0) -> 1712.3 | E70: =IFERROR('Data Sheet'!D82,0) -> -51.12 | F70: =IFERROR('Data Sheet'!E82,0) -> 1242.92 | G70: =IFERROR('Data Sheet'!F82,0) -> -348 | H70: =IFERROR('Data Sheet'!G82,0) -> 4139 | I70: =IFERROR('Data Sheet'!H82,0) -> -724 | J70: =IFERROR('Data Sheet'!I82,0) -> 1370 | ... L70: =IFERROR('Data Sheet'!K82,0) -> -541
B72: Cash from Investing Activity | C72: =IFERROR('Data Sheet'!B83,0) -> -158.79 | D72: =IFERROR('Data Sheet'!C83,0) -> -953.15 | E72: =IFERROR('Data Sheet'!D83,0) -> 97.62 | F72: =IFERROR('Data Sheet'!E83,0) -> -796.61 | G72: =IFERROR('Data Sheet'!F83,0) -> 235 | H72: =IFERROR('Data Sheet'!G83,0) -> -2799 | I72: =IFERROR('Data Sheet'!H83,0) -> 1165 | J72: =IFERROR('Data Sheet'!I83,0) -> -1814 | ... L72: =IFERROR('Data Sheet'!K83,0) -> 546
B74: Cash from Financing Activity | C74: =IFERROR('Data Sheet'!B84,0) -> -504.84 | D74: =IFERROR('Data Sheet'!C84,0) -> -165.6 | E74: =IFERROR('Data Sheet'!D84,0) -> -252.45 | F74: =IFERROR('Data Sheet'!E84,0) -> -488.83 | G74: =IFERROR('Data Sheet'!F84,0) -> -242 | H74: =IFERROR('Data Sheet'!G84,0) -> -1234 | I74: =IFERROR('Data Sheet'!H84,0) -> -403 | J74: =IFERROR('Data Sheet'!I84,0) -> 457 | ... L74: =IFERROR('Data Sheet'!K84,0) -> -7
B76: Net Cash Flow | C76: =IFERROR('Data Sheet'!B85,0) -> -87.54 | D76: =IFERROR('Data Sheet'!C85,0) -> 593.55 | E76: =IFERROR('Data Sheet'!D85,0) -> -205.95 | F76: =IFERROR('Data Sheet'!E85,0) -> -42.52 | G76: =IFERROR('Data Sheet'!F85,0) -> -355 | H76: =IFERROR('Data Sheet'!G85,0) -> 106 | I76: =IFERROR('Data Sheet'!H85,0) -> 38 | J76: =IFERROR('Data Sheet'!I85,0) -> 13 | ... L76: =IFERROR('Data Sheet'!K85,0) -> -2

Sheet Ratio Analysis
B2: ="Ratio Analysis of - "&'Data Sheet'!B1 -> Ratio Analysis of - TITAN COMPANY LTD
B3: Years | C3: ='Data Sheet'!B16 -> 42460 | D3: ='Data Sheet'!C16 -> 42825 | E3: ='Data Sheet'!D16 -> 43190 | F3: ='Data Sheet'!E16 -> 43555 | G3: ='Data Sheet'!F16 -> 43921 | H3: ='Data Sheet'!G16 -> 44286 | I3: ='Data Sheet'!H16 -> 44651 | J3: ='Data Sheet'!I16 -> 45016 | ... L3: ='Data Sheet'!K16 -> 45747 | M3: Trend | N3: Mean | O3: Median
B5: SalesGrowth | D5: =IFERROR(HistoricalFS!D7,0) -> 0.176034 | E5: =IFERROR(HistoricalFS!E7,0) -> 0.21559284 | F5: =IFERROR(HistoricalFS!F7,0) -> 0.22697284 | G5: =IFERROR(HistoricalFS!G7,0) -> 0.064387022 | H5: =IFERROR(HistoricalFS!H7,0) -> 0.028120844 | I5: =IFERROR(HistoricalFS!I7,0) -> 0.3305766 | J5: =IFERROR(HistoricalFS!J7,0) -> 0.40890309 | K5: =IFERROR(HistoricalFS!K7,0) -> 0.25900185 | L5: =IFERROR(HistoricalFS!L7,0) -> 0.18346253 | N5: =IFERROR(AVERAGE(D5:L5),0) -> 0.21033907 | O5: =IFERROR(MEDIAN(C5:L5),0) -> 0.21559284
B6: EBITDA Growth | D6: =IFERROR(HistoricalFS!D18/HistoricalFS!C18-1,0) -> 0.23907466 | E6: =IFERROR(HistoricalFS!E18/HistoricalFS!D18-1,0) -> 0.41266432 | F6: =IFERROR(HistoricalFS!F18/HistoricalFS!E18-1,0) -> 0.21262012 | G6: =IFERROR(HistoricalFS!G18/HistoricalFS!F18-1,0) -> 0.23533572 | H6: =IFERROR(HistoricalFS!H18/HistoricalFS!G18-1,0) -> -0.29963459 | I6: =IFERROR(HistoricalFS!I18/HistoricalFS!H18-1,0) -> 0.93855072 | J6: =IFERROR(HistoricalFS!J18/HistoricalFS!I18-1,0) -> 0.45992823 | K6: =IFERROR(HistoricalFS!K18/HistoricalFS!J18-1,0) -> 0.083981975 | L6: =IFERROR(HistoricalFS!L18/HistoricalFS!K18-1,0) -> 0.075963719 | N6: =IFERROR(AVERAGE(D6:L6),0) -> 0.26205387 | O6: =IFERROR(MEDIAN(C6:L6),0) -> 0.23533572
B7: EBIT Growth | D7: =IFERROR(HistoricalFS!D27/HistoricalFS!C27-1,0) -> 0.2714765 | E7: =IFERROR(HistoricalFS!E27/HistoricalFS!D27-1,0) -> 0.43738369 | F7: =IFERROR(HistoricalFS!F27/HistoricalFS!E27-1,0) -> 0.2182142 | G7: =IFERROR(HistoricalFS!G27/HistoricalFS!F27-1,0) -> 0.095922762 | H7: =IFERROR(HistoricalFS!H27/HistoricalFS!G27-1,0) -> -0.41149307 | I7: =IFERROR(HistoricalFS!I27/HistoricalFS!H27-1,0) -> 1.3775065 | J7: =IFERROR(HistoricalFS!J27/HistoricalFS!I27-1,0) -> 0.51851852 | K7: =IFERROR(HistoricalFS!K27/HistoricalFS!J27-1,0) -> -0.012557353 | L7: =IFERROR(HistoricalFS!L27/HistoricalFS!K27-1,0) -> -0.010026901 | N7: =IFERROR(AVERAGE(D7:L7),0) -> 0.27610499 | O7: =IFERROR(MEDIAN(C7:L7),0) -> 0.2182142
B8: Net Profit Growth | D8: =IFERROR(HistoricalFS!D33/HistoricalFS!C33-1,0) -> 0.21816894 | E8: =IFERROR(HistoricalFS!E33/HistoricalFS!D33-1,0) -> 0.39520861 | F8: =IFERROR(HistoricalFS!F33/HistoricalFS!E33-1,0) -> 0.17266807 | G8: =IFERROR(HistoricalFS!G33/HistoricalFS!F33-1,0) -> 0.10728245 | H8: =IFERROR(HistoricalFS!H33/HistoricalFS!G33-1,0) -> -0.40746269 | I8: =IFERROR(HistoricalFS!I33/HistoricalFS!H33-1,0) -> 1.5453401 | J8: =IFERROR(HistoricalFS!J33/HistoricalFS!I33-1,0) -> 0.46857991 | K8: =IFERROR(HistoricalFS!K33/HistoricalFS!J33-1,0) -> -0.0020215633 | L8: =IFERROR(HistoricalFS!L33/HistoricalFS!K33-1,0) -> -0.037812289 | N8: =IFERROR(AVERAGE(D8:L8),0) -> 0.27332794 | O8: =IFERROR(MEDIAN(C8:L8),0) -> 0.17266807
B9: Dividend Growth | D9: =IFERROR(HistoricalFS!D41/HistoricalFS!C41-1,0) -> 0.18180422 | E9: =IFERROR(HistoricalFS!E41/HistoricalFS!D41-1,0) -> 0.44227353 | F9: =IFERROR(HistoricalFS!F41/HistoricalFS!E41-1,0) -> 0.33335336 | G9: =IFERROR(HistoricalFS!G41/HistoricalFS!F41-1,0) -> -0.19801757 | H9: =IFERROR(HistoricalFS!H41/HistoricalFS!G41-1,0) -> 0 | I9: =IFERROR(HistoricalFS!I41/HistoricalFS!H41-1,0) -> 0.875 | J9: =IFERROR(HistoricalFS!J41/HistoricalFS!I41-1,0) -> 0.33333333 | K9: =IFERROR(HistoricalFS!K41/HistoricalFS!J41-1,0) -> 0.1 | L9: =IFERROR(HistoricalFS!L41/HistoricalFS!K41-1,0) -> 0 | N9: =IFERROR(AVERAGE(D9:L9),0) -> 0.22974965 | O9: =IFERROR(MEDIAN(C9:L9),0) -> 0.18180422
B11: Gross Margin | C11: =IFERROR(HistoricalFS!C13,0) -> 0.18557826 | D11: =IFERROR(HistoricalFS!D13,0) -> 0.20020014 | E11: =IFERROR(HistoricalFS!E13,0) -> 0.20826228 | F11: =IFERROR(HistoricalFS!F13,0) -> 0.20820769 | G11: =IFERROR(HistoricalFS!G13,0) -> 0.21024131 | H11: =IFERROR(HistoricalFS!H13,0) -> 0.18402329 | I11: =IFERROR(HistoricalFS!I13,0) -> 0.19354839 | J11: =IFERROR(HistoricalFS!J13,0) -> 0.20406654 | ... L11: =IFERROR(HistoricalFS!L13,0) -> 0.17255525 | N11: =IFERROR(AVERAGE(C11:L11),0) -> 0.19510853 | O11: =IFERROR(MEDIAN(C11:L11),0) -> 0.19687426
B12: EBITDA Margin | C12: =IFERROR(HistoricalFS!C19,0) -> 0.083304289 | D12: =IFERROR(HistoricalFS!D19,0) -> 0.08776977 | E12: =IFERROR(HistoricalFS!E19,0) -> 0.10199897 | F12: =IFERROR(HistoricalFS!F19,0) -> 0.10080582 | G12: =IFERROR(HistoricalFS!G19,0) -> 0.11699601 | H12: =IFERROR(HistoricalFS!H19,0) -> 0.079698762 | I12: =IFERROR(HistoricalFS!I19,0) -> 0.11611514 | J12: =IFERROR(HistoricalFS!J19,0) -> 0.12032039 | ... L12: =IFERROR(HistoricalFS!L19,0) -> 0.0941842 | N12: =IFERROR(AVERAGE(C12:L12),0) -> 0.10047874 | O12: =IFERROR(MEDIAN(C12:L12),0) -> 0.1014024
B13: EBIT Margin | C13: =IFERROR((HistoricalFS!C18-HistoricalFS!C24)/HistoricalFS!C6,0) -> 0.074596329 | D13: =IFERROR((HistoricalFS!D18-HistoricalFS!D24)/HistoricalFS!D6,0) -> 0.079434696 | E13: =IFERROR((HistoricalFS!E18-HistoricalFS!E24)/HistoricalFS!E6,0) -> 0.093845632 | F13: =IFERROR((HistoricalFS!F18-HistoricalFS!F24)/HistoricalFS!F6,0) -> 0.09257265 | G13: =IFERROR((HistoricalFS!G18-HistoricalFS!G24)/HistoricalFS!G6,0) -> 0.10046551 | H13: =IFERROR((HistoricalFS!H18-HistoricalFS!H24)/HistoricalFS!H6,0) -> 0.062372944 | I13: =IFERROR((HistoricalFS!I18-HistoricalFS!I24)/HistoricalFS!I6,0) -> 0.1022605 | J13: =IFERROR((HistoricalFS!J18-HistoricalFS!J24)/HistoricalFS!J6,0) -> 0.10945163 | ... L13: =IFERROR((HistoricalFS!L18-HistoricalFS!L24)/HistoricalFS!L6,0) -> 0.082721318 | N13: =IFERROR(AVERAGE(C13:L13),0) -> 0.088988314 | O13: =IFERROR(MEDIAN(C13:L13),0) -> 0.092367289
B14: EBT Margin | C14: =IFERROR(HistoricalFS!C28,0) -> 0.08698152 | D14: =IFERROR(HistoricalFS!D28,0) -> 0.095759857 | E14: =IFERROR(HistoricalFS!E28,0) -> 0.11438473 | F14: =IFERROR(HistoricalFS!F28,0) -> 0.11356038 | G14: =IFERROR(HistoricalFS!G28,0) -> 0.11722603 | H14: =IFERROR(HistoricalFS!H28,0) -> 0.06494536 | I14: =IFERROR(HistoricalFS!I28,0) -> 0.11741658 | J14: =IFERROR(HistoricalFS!J28,0) -> 0.12822418 | ... L14: =IFERROR(HistoricalFS!L28,0) -> 0.080921158 | N14: =IFERROR(AVERAGE(C14:L14),0) -> 0.10175621 | O14: =IFERROR(MEDIAN(C14:L14),0) -> 0.10585133
B15: Net Profit Margin | C15: =IFERROR(HistoricalFS!C34,0) -> 0.053848521 | D15: =IFERROR(HistoricalFS!D34,0) -> 0.055777806 | E15: =IFERROR(HistoricalFS!E34,0) -> 0.064019524 | F15: =IFERROR(HistoricalFS!F34,0) -> 0.061186075 | G15: =IFERROR(HistoricalFS!G34,0) -> 0.06365191 | H15: =IFERROR(HistoricalFS!H34,0) -> 0.036684532 | I15: =IFERROR(HistoricalFS!I34,0) -> 0.070176048 | J15: =IFERROR(HistoricalFS!J34,0) -> 0.07314849 | ... L15: =IFERROR(HistoricalFS!L34,0) -> 0.047141723 | N15: =IFERROR(AVERAGE(C15:L15),0) -> 0.058361756 | O15: =IFERROR(MEDIAN(C15:L15),0) -> 0.059584502
B17: SalesExpenses%Sales | C17: =IFERROR(HistoricalFS!C16,0) -> 0.10227397 | D17: =IFERROR(HistoricalFS!D16,0) -> 0.11243037 | E17: =IFERROR(HistoricalFS!E16,0) -> 0.1062633 | F17: =IFERROR(HistoricalFS!F16,0) -> 0.10740187 | G17: =IFERROR(HistoricalFS!G16,0) -> 0.093245297 | H17: =IFERROR(HistoricalFS!H16,0) -> 0.10432452 | I17: =IFERROR(HistoricalFS!I16,0) -> 0.077433244 | J17: =IFERROR(HistoricalFS!J16,0) -> 0.083746149 | ... L17: =IFERROR(HistoricalFS!L16,0) -> 0.078371047 | N17: =IFERROR(AVERAGE(C17:L17),0) -> 0.094629785 | O17: =IFERROR(MEDIAN(C17:L17),0) -> 0.097759632
B18: Depreciation%Sales | C18: =IFERROR(HistoricalFS!C25,0) -> 0.0087079601 | D18: =IFERROR(HistoricalFS!D25,0) -> 0.008335074 | E18: =IFERROR(HistoricalFS!E25,0) -> 0.0081533421 | F18: =IFERROR(HistoricalFS!F25,0) -> 0.0082331742 | G18: =IFERROR(HistoricalFS!G25,0) -> 0.016530496 | H18: =IFERROR(HistoricalFS!H25,0) -> 0.017325818 | I18: =IFERROR(HistoricalFS!I25,0) -> 0.013854648 | J18: =IFERROR(HistoricalFS!J25,0) -> 0.010868762 | ... L18: =IFERROR(HistoricalFS!L25,0) -> 0.011462882 | N18: =IFERROR(AVERAGE(C18:L18),0) -> 0.011490431 | O18: =IFERROR(MEDIAN(C18:L18),0) -> 0.011150456
B19: OperatingIncome%Sales | C19: =C13 -> 0.074596329 | D19: =D13 -> 0.079434696 | E19: =E13 -> 0.093845632 | F19: =F13 -> 0.09257265 | G19: =G13 -> 0.10046551 | H19: =H13 -> 0.062372944 | I19: =I13 -> 0.1022605 | J19: =J13 -> 0.10945163 | ... L19: =L13 -> 0.082721318 | N19: =IFERROR(AVERAGE(C19:L19),0) -> 0.088988314 | O19: =IFERROR(MEDIAN(C19:L19),0) -> 0.092367289
B21: Return on Capital Employed | C21: =IFERROR((HistoricalFS!C18-HistoricalFS!C24)/(SUM(HistoricalFS!C47:C49)),0) -> 0.23240213 | D21: =IFERROR((HistoricalFS!D18-HistoricalFS!D24)/(SUM(HistoricalFS!D47:D49)),0) -> 0.17226537 | E21: =IFERROR((HistoricalFS!E18-HistoricalFS!E24)/(SUM(HistoricalFS!E47:E49)),0) -> 0.22309313 | F21: =IFERROR((HistoricalFS!F18-HistoricalFS!F24)/(SUM(HistoricalFS!F47:F49)),0) -> 0.21634431 | G21: =IFERROR((HistoricalFS!G18-HistoricalFS!G24)/(SUM(HistoricalFS!G47:G49)),0) -> 0.20672466 | H21: =IFERROR((HistoricalFS!H18-HistoricalFS!H24)/(SUM(HistoricalFS!H47:H49)),0) -> 0.10277884 | I21: =IFERROR((HistoricalFS!I18-HistoricalFS!I24)/(SUM(HistoricalFS!I47:I49)),0) -> 0.17764507 | J21: =IFERROR((HistoricalFS!J18-HistoricalFS!J24)/(SUM(HistoricalFS!J47:J49)),0) -> 0.20930342 | ... L21: =IFERROR((HistoricalFS!L18-HistoricalFS!L24)/(SUM(HistoricalFS!L47:L49)),0) -> 0.15434709 | N21: =IFERROR(AVERAGE(C21:L21),0) -> 0.1883821 | O21: =IFERROR(MEDIAN(C21:L21),0) -> 0.19782082
B22: Retained Earnings% | C22: =IFERROR(HistoricalFS!C44,0) -> 0.67832145 | D22: =IFERROR(HistoricalFS!D44,0) -> 0.68792418 | E22: =IFERROR(HistoricalFS!E44,0) -> 0.67739685 | F22: =IFERROR(HistoricalFS!F44,0) -> 0.63319203 | G22: =IFERROR(HistoricalFS!G44,0) -> 0.73432836 | H22: =IFERROR(HistoricalFS!H44,0) -> 0.55163728 | I22: =IFERROR(HistoricalFS!I44,0) -> 0.66971796 | J22: =IFERROR(HistoricalFS!J44,0) -> 0.70013477 | ... L22: =IFERROR(HistoricalFS!L44,0) -> 0.65649123 | N22: =IFERROR(AVERAGE(C22:L22),0) -> 0.66586242 | O22: =IFERROR(MEDIAN(C22:L22),0) -> 0.67355741
B23: Return on Equity% | C23: =IFERROR(HistoricalFS!C33/SUM(HistoricalFS!C47:C48),0) -> 0.17317214 | D23: =IFERROR(HistoricalFS!D33/SUM(HistoricalFS!D47:D48),0) -> 0.17476219 | E23: =IFERROR(HistoricalFS!E33/SUM(HistoricalFS!E47:E48),0) -> 0.20275134 | F23: =IFERROR(HistoricalFS!F33/SUM(HistoricalFS!F47:F48),0) -> 0.1993641 | G23: =IFERROR(HistoricalFS!G33/SUM(HistoricalFS!G47:G48),0) -> 0.20092967 | H23: =IFERROR(HistoricalFS!H33/SUM(HistoricalFS!H47:H48),0) -> 0.10590903 | I23: =IFERROR(HistoricalFS!I33/SUM(HistoricalFS!I47:I48),0) -> 0.21724175 | J23: =IFERROR(HistoricalFS!J33/SUM(HistoricalFS!J47:J48),0) -> 0.250443 | ... L23: =IFERROR(HistoricalFS!L33/SUM(HistoricalFS!L47:L48),0) -> 0.24518238 | N23: =IFERROR(AVERAGE(C23:L23),0) -> 0.20850968 | O23: =IFERROR(MEDIAN(C23:L23),0) -> 0.20184051
B24: Self Sustained Growth Rate | C24: =IFERROR(C22*C23,0) -> 0.11746637 | D24: =IFERROR(D22*D23,0) -> 0.12022314 | E24: =IFERROR(E22*E23,0) -> 0.13734312 | F24: =IFERROR(F22*F23,0) -> 0.12623576 | G24: =IFERROR(G22*G23,0) -> 0.14754836 | H24: =IFERROR(H22*H23,0) -> 0.058423369 | I24: =IFERROR(I22*I23,0) -> 0.1454907 | J24: =IFERROR(J22*J23,0) -> 0.17534385 | ... L24: =IFERROR(L22*L23,0) -> 0.16096008 | N24: =IFERROR(AVERAGE(C24:L24),0) -> 0.14001494 | O24: =IFERROR(MEDIAN(C24:L24),0) -> 0.14141691
B25: Interest Coverage Ratio | C25: =IFERROR((HistoricalFS!C18-HistoricalFS!C24)/HistoricalFS!C21,0) -> 19.856941 | D25: =IFERROR((HistoricalFS!D18-HistoricalFS!D24)/HistoricalFS!D21,0) -> 27.911235 | E25: =IFERROR((HistoricalFS!E18-HistoricalFS!E24)/HistoricalFS!E21,0) -> 28.585979 | F25: =IFERROR((HistoricalFS!F18-HistoricalFS!F24)/HistoricalFS!F21,0) -> 34.848687 | G25: =IFERROR((HistoricalFS!G18-HistoricalFS!G24)/HistoricalFS!G21,0) -> 12.740964 | H25: =IFERROR((HistoricalFS!H18-HistoricalFS!H24)/HistoricalFS!H21,0) -> 6.6502463 | I25: =IFERROR((HistoricalFS!I18-HistoricalFS!I24)/HistoricalFS!I21,0) -> 13.509174 | J25: =IFERROR((HistoricalFS!J18-HistoricalFS!J24)/HistoricalFS!J21,0) -> 14.803333 | ... L25: =IFERROR((HistoricalFS!L18-HistoricalFS!L24)/HistoricalFS!L21,0) -> 5.247639 | N25: =IFERROR(AVERAGE(C25:L25),0) -> 17.176001 | O25: =IFERROR(MEDIAN(C25:L25),0) -> 14.156254
B27: Debtor Turnover Ratio | C27: =IFERROR(HistoricalFS!C6/HistoricalFS!C59,0) -> 58.576052 | D27: =IFERROR(HistoricalFS!D6/HistoricalFS!D59,0) -> 63.87683 | E27: =IFERROR(HistoricalFS!E6/HistoricalFS!E59,0) -> 54.515777 | F27: =IFERROR(HistoricalFS!F6/HistoricalFS!F59,0) -> 47.041313 | G27: =IFERROR(HistoricalFS!G6/HistoricalFS!G59,0) -> 67.474359 | H27: =IFERROR(HistoricalFS!H6/HistoricalFS!H59,0) -> 59.136612 | I27: =IFERROR(HistoricalFS!I6/HistoricalFS!I59,0) -> 50.971681 | J27: =IFERROR(HistoricalFS!J6/HistoricalFS!J59,0) -> 60.200297 | ... L27: =IFERROR(HistoricalFS!L6/HistoricalFS!L59,0) -> 56.606742 | N27: =IFERROR(AVERAGE(C27:L27),0) -> 56.858041 | O27: =IFERROR(MEDIAN(C27:L27),0) -> 57.591397
B28: Creditor Turnover Ratio | C28: =IFERROR(HistoricalFS!C6/HistoricalFS!C50,0) -> 4.1416193 | D28: =IFERROR(HistoricalFS!D6/HistoricalFS!D50,0) -> 5.7837846 | E28: =IFERROR(HistoricalFS!E6/HistoricalFS!E50,0) -> 5.8828057 | F28: =IFERROR(HistoricalFS!F6/HistoricalFS!F50,0) -> 6.0918653 | G28: =IFERROR(HistoricalFS!G6/HistoricalFS!G50,0) -> 6.3543616 | H28: =IFERROR(HistoricalFS!H6/HistoricalFS!H50,0) -> 6.5409489 | I28: =IFERROR(HistoricalFS!I6/HistoricalFS!I50,0) -> 6.2470716 | J28: =IFERROR(HistoricalFS!J6/HistoricalFS!J50,0) -> 6.9932782 | ... L28: =IFERROR(HistoricalFS!L6/HistoricalFS!L50,0) -> 7.3333333 | N28: =IFERROR(AVERAGE(C28:L28),0) -> 6.3078697 | O28: =IFERROR(MEDIAN(C28:L28),0) -> 6.3007166
B29: Inventory Turnover | C29: =IFERROR(HistoricalFS!C6/HistoricalFS!C60,0) -> 2.5355317 | D29: =IFERROR(HistoricalFS!D6/HistoricalFS!D60,0) -> 2.6921498 | E29: =IFERROR(HistoricalFS!E6/HistoricalFS!E60,0) -> 2.7207098 | F29: =IFERROR(HistoricalFS!F6/HistoricalFS!F60,0) -> 2.8099198 | G29: =IFERROR(HistoricalFS!G6/HistoricalFS!G60,0) -> 2.5980501 | H29: =IFERROR(HistoricalFS!H6/HistoricalFS!H60,0) -> 2.574215 | I29: =IFERROR(HistoricalFS!I6/HistoricalFS!I60,0) -> 2.1161731 | J29: =IFERROR(HistoricalFS!J6/HistoricalFS!J60,0) -> 2.4466353 | ... L29: =IFERROR(HistoricalFS!L6/HistoricalFS!L60,0) -> 2.1450468 | N29: =IFERROR(AVERAGE(C29:L29),0) -> 2.5319866 | O29: =IFERROR(MEDIAN(C29:L29),0) -> 2.5861326
B30: Fixed Asset Turnover | C30: =IFERROR(HistoricalFS!C6/HistoricalFS!C53,0) -> 14.63375 | D30: =IFERROR(HistoricalFS!D6/HistoricalFS!D53,0) -> 11.155554 | E30: =IFERROR(HistoricalFS!E6/HistoricalFS!E53,0) -> 10.937482 | F30: =IFERROR(HistoricalFS!F6/HistoricalFS!F53,0) -> 12.624883 | G30: =IFERROR(HistoricalFS!G6/HistoricalFS!G53,0) -> 7.9954425 | H30: =IFERROR(HistoricalFS!H6/HistoricalFS!H53,0) -> 8.5786762 | I30: =IFERROR(HistoricalFS!I6/HistoricalFS!I53,0) -> 11.320362 | J30: =IFERROR(HistoricalFS!J6/HistoricalFS!J53,0) -> 13.534023 | ... L30: =IFERROR(HistoricalFS!L6/HistoricalFS!L53,0) -> 14.883309 | N30: =IFERROR(AVERAGE(C30:L30),0) -> 11.943647 | O30: =IFERROR(MEDIAN(C30:L30),0) -> 11.972622
B31: Capital Turnover Ratio | C31: =IFERROR(HistoricalFS!C6/SUM(HistoricalFS!C47:C48),0) -> 3.2159126 | D31: =IFERROR(HistoricalFS!D6/SUM(HistoricalFS!D47:D48),0) -> 3.1331851 | E31: =IFERROR(HistoricalFS!E6/SUM(HistoricalFS!E47:E48),0) -> 3.1670236 | F31: =IFERROR(HistoricalFS!F6/SUM(HistoricalFS!F47:F48),0) -> 3.2583248 | G31: =IFERROR(HistoricalFS!G6/SUM(HistoricalFS!G47:G48),0) -> 3.1566952 | H31: =IFERROR(HistoricalFS!H6/SUM(HistoricalFS!H47:H48),0) -> 2.8870215 | I31: =IFERROR(HistoricalFS!I6/SUM(HistoricalFS!I47:I48),0) -> 3.0956681 | J31: =IFERROR(HistoricalFS!J6/SUM(HistoricalFS!J47:J48),0) -> 3.4237617 | ... L31: =IFERROR(HistoricalFS!L6/SUM(HistoricalFS!L47:L48),0) -> 5.2009635 | N31: =IFERROR(AVERAGE(C31:L31),0) -> 3.5977074 | O31: =IFERROR(MEDIAN(C31:L31),0) -> 3.1914681
B33: Debtor Days | C33: =IFERROR(365/C27,0) -> 6.2312155 | D33: =IFERROR(365/D27,0) -> 5.714122 | E33: =IFERROR(365/E27,0) -> 6.6953095 | F33: =IFERROR(365/F27,0) -> 7.7591372 | G33: =IFERROR(365/G27,0) -> 5.4094623 | H33: =IFERROR(365/H27,0) -> 6.1721493 | I33: =IFERROR(365/I27,0) -> 7.1608389 | J33: =IFERROR(365/J27,0) -> 6.063093 | ... L33: =IFERROR(365/L27,0) -> 6.4479952 | N33: =IFERROR(AVERAGE(C33:L33),0) -> 6.4927029 | O33: =IFERROR(MEDIAN(C33:L33),0) -> 6.3396053
B34: Payable Days | C34: =IFERROR(365/C28,0) -> 88.12978 | D34: =IFERROR(365/D28,0) -> 63.107468 | E34: =IFERROR(365/E28,0) -> 62.045225 | F34: =IFERROR(365/F28,0) -> 59.915967 | G34: =IFERROR(365/G28,0) -> 57.440861 | H34: =IFERROR(365/H28,0) -> 55.802301 | I34: =IFERROR(365/I28,0) -> 58.427376 | J34: =IFERROR(365/J28,0) -> 52.192976 | ... L34: =IFERROR(365/L28,0) -> 49.772727 | N34: =IFERROR(AVERAGE(C34:L34),0) -> 59.417807 | O34: =IFERROR(MEDIAN(C34:L34),0) -> 57.934118
B35: Inventory Days | C35: =IFERROR(365/C29,0) -> 143.95402 | D35: =IFERROR(365/D29,0) -> 135.57938 | E35: =IFERROR(365/E29,0) -> 134.15617 | F35: =IFERROR(365/F29,0) -> 129.89694 | G35: =IFERROR(365/G29,0) -> 140.48998 | H35: =IFERROR(365/H29,0) -> 141.7908 | I35: =IFERROR(365/I29,0) -> 172.48116 | J35: =IFERROR(365/J29,0) -> 149.18447 | ... L35: =IFERROR(365/L29,0) -> 170.15945 | N35: =IFERROR(AVERAGE(C35:L35),0) -> 145.38136 | O35: =IFERROR(MEDIAN(C35:L35),0) -> 141.14039
B36: Cash Conversion Cycle | C36: =IFERROR(SUM(C33,C35)-C34,0) -> 62.055461 | D36: =IFERROR(SUM(D33,D35)-D34,0) -> 78.186034 | E36: =IFERROR(SUM(E33,E35)-E34,0) -> 78.806255 | F36: =IFERROR(SUM(F33,F35)-F34,0) -> 77.740114 | G36: =IFERROR(SUM(G33,G35)-G34,0) -> 88.458579 | H36: =IFERROR(SUM(H33,H35)-H34,0) -> 92.160645 | I36: =IFERROR(SUM(I33,I35)-I34,0) -> 121.21463 | J36: =IFERROR(SUM(J33,J35)-J34,0) -> 103.05459 | ... L36: =IFERROR(SUM(L33,L35)-L34,0) -> 126.83472 | N36: =IFERROR(AVERAGE(C36:L36),0) -> 92.456253 | O36: =IFERROR(MEDIAN(C36:L36),0) -> 90.309612
B38: CFO/Sales | C38: =IFERROR(HistoricalFS!C70/HistoricalFS!C6,0) -> 0.051090424 | D38: =IFERROR(HistoricalFS!D70/HistoricalFS!D6,0) -> 0.12912465 | E38: =IFERROR(HistoricalFS!E70/HistoricalFS!E6,0) -> -0.0031712611 | F38: =IFERROR(HistoricalFS!F70/HistoricalFS!F6,0) -> 0.062841911 | G38: =IFERROR(HistoricalFS!G70/HistoricalFS!G6,0) -> -0.016530496 | H38: =IFERROR(HistoricalFS!H70/HistoricalFS!H6,0) -> 0.19123083 | I38: =IFERROR(HistoricalFS!I70/HistoricalFS!I6,0) -> -0.025139762 | J38: =IFERROR(HistoricalFS!J70/HistoricalFS!J6,0) -> 0.033764633 | ... L38: =IFERROR(HistoricalFS!L70/HistoricalFS!L6,0) -> -0.0089486569 | N38: =IFERROR(AVERAGE(C38:L38),0) -> 0.044744291 | O38: =IFERROR(MEDIAN(C38:L38),0) -> 0.033472639
B39: CFO/Total Assets | C39: =IFERROR(HistoricalFS!C70/HistoricalFS!C64,0) -> 0.090838564 | D39: =IFERROR(HistoricalFS!D70/HistoricalFS!D64,0) -> 0.2036617 | E39: =IFERROR(HistoricalFS!E70/HistoricalFS!E64,0) -> -0.0053691614 | F39: =IFERROR(HistoricalFS!F70/HistoricalFS!F64,0) -> 0.10614321 | G39: =IFERROR(HistoricalFS!G70/HistoricalFS!G64,0) -> -0.025694034 | H39: =IFERROR(HistoricalFS!H70/HistoricalFS!H64,0) -> 0.25170275 | I39: =IFERROR(HistoricalFS!I70/HistoricalFS!I64,0) -> -0.034170285 | J39: =IFERROR(HistoricalFS!J70/HistoricalFS!J64,0) -> 0.050703183 | ... L39: =IFERROR(HistoricalFS!L70/HistoricalFS!L64,0) -> -0.01331037 | N39: =IFERROR(AVERAGE(C39:L39),0) -> 0.067823491 | O39: =IFERROR(MEDIAN(C39:L39),0) -> 0.05221627
B40: CFO/Total Debt | C40: =IFERROR(HistoricalFS!C70/HistoricalFS!C49,0) -> 5.0958868 | D40: =IFERROR(HistoricalFS!D70/HistoricalFS!D49,0) -> 0.90962214 | E40: =IFERROR(HistoricalFS!E70/HistoricalFS!E49,0) -> -0.030230454 | F40: =IFERROR(HistoricalFS!F70/HistoricalFS!F49,0) -> 0.51940259 | G40: =IFERROR(HistoricalFS!G70/HistoricalFS!G49,0) -> -0.097697923 | H40: =IFERROR(HistoricalFS!H70/HistoricalFS!H49,0) -> 0.73412558 | I40: =IFERROR(HistoricalFS!I70/HistoricalFS!I49,0) -> -0.0995189 | J40: =IFERROR(HistoricalFS!J70/HistoricalFS!J49,0) -> 0.14625814 | ... L40: =IFERROR(HistoricalFS!L70/HistoricalFS!L49,0) -> -0.026038408 | N40: =IFERROR(AVERAGE(C40:L40),0) -> 0.72609672 | O40: =IFERROR(MEDIAN(C40:L40),0) -> 0.1277079

Sheet Peer Analysis

Sheet Forecasting
B2: ='Data Sheet'!$B$1&" - "&'Data Sheet'!A17&" Forecasting" -> TITAN COMPANY LTD - Sales Forecasting | G2: ='Data Sheet'!$B$1&" - "&HistoricalFS!B18&" Forecasting" -> TITAN COMPANY LTD - EBITDA Forecasting | L2: ='Data Sheet'!$B$1&" - "&HistoricalFS!B38&" Forecasting" -> TITAN COMPANY LTD - Earning Per Share Forecasting
B3: Year Weight | C3: Year | D3: Sales | E3: Sales Growth | G3: Year Weight | H3: Year | I3: Sales | J3: EBITDA Growth | L3: Year Weight | M3: Year | N3: Sales | O3: EPS Growth
B4: 1 | C4: ='Data Sheet'!$B$16 -> 42460 | D4: {=TRANSPOSE('Data Sheet'!B17:K17)} -> 11275.89 | G4: 1 | H4: ='Data Sheet'!$B$16 -> 42460 | I4: {=TRANSPOSE(HistoricalFS!C18:M18)} -> 939.33 | L4: 1 | M4: ='Data Sheet'!$B$16 -> 42460 | N4: {=TRANSPOSE(HistoricalFS!C38:M38)} -> 6.8392656
B5: =B4+1 -> 2 | C5: =C4+365 -> 42825 | D5: 13260.83 | E5: =D5/D4-1 -> 0.176034 | G5: =G4+1 -> 2 | H5: =H4+365 -> 42825 | I5: 1163.9 | J5: =I5/I4-1 -> 0.23907466 | L5: =L4+1 -> 2 | M5: =M4+365 -> 42825 | N5: 8.3313809 | O5: =N5/N4-1 -> 0.21816894
B6: =B5+1 -> 3 | C6: =C5+365 -> 43190 | D6: 16119.77 | E6: =D6/D5-1 -> 0.21559284 | G6: =G5+1 -> 3 | H6: =H5+365 -> 43190 | I6: 1644.2 | J6: =I6/I5-1 -> 0.41266432 | L6: =L5+1 -> 3 | M6: =M5+365 -> 43190 | N6: 11.624014 | O6: =N6/N5-1 -> 0.39520861
B7: =B6+1 -> 4 | C7: =C6+365 -> 43555 | D7: 19778.52 | E7: =D7/D6-1 -> 0.22697284 | G7: =G6+1 -> 4 | H7: =H6+365 -> 43555 | I7: 1993.79 | J7: =I7/I6-1 -> 0.21262012 | L7: =L6+1 -> 4 | M7: =M6+365 -> 43555 | N7: 13.631111 | O7: =N7/N6-1 -> 0.17266807
B8: =B7+1 -> 5 | C8: =C7+365 -> 43920 | D8: 21052 | E8: =D8/D7-1 -> 0.064387022 | G8: =G7+1 -> 5 | H8: =H7+365 -> 43920 | I8: 2463 | J8: =I8/I7-1 -> 0.23533572 | L8: =L7+1 -> 5 | M8: =M7+365 -> 43920 | N8: 15.09349 | O8: =N8/N7-1 -> 0.10728245
B9: =B8+1 -> 6 | C9: =C8+365 -> 44285 | D9: 21644 | E9: =D9/D8-1 -> 0.028120844 | G9: =G8+1 -> 6 | H9: =H8+365 -> 44285 | I9: 1725 | J9: =I9/I8-1 -> -0.29963459 | L9: =L8+1 -> 6 | M9: =M8+365 -> 44285 | N9: 8.9434557 | O9: =N9/N8-1 -> -0.40746269
B10: =B9+1 -> 7 | C10: =C9+365 -> 44650 | D10: 28799 | E10: =D10/D9-1 -> 0.3305766 | G10: =G9+1 -> 7 | H10: =H9+365 -> 44650 | I10: 3344 | J10: =I10/I9-1 -> 0.93855072 | L10: =L9+1 -> 7 | M10: =M9+365 -> 44650 | N10: 22.764136 | O10: =N10/N9-1 -> 1.5453401
B11: =B10+1 -> 8 | C11: =C10+365 -> 45015 | D11: 40575 | E11: =D11/D10-1 -> 0.40890309 | G11: =G10+1 -> 8 | H11: =H10+365 -> 45015 | I11: 4882 | J11: =I11/I10-1 -> 0.45992823 | L11: =L10+1 -> 8 | M11: =M10+365 -> 45015 | N11: 33.430953 | O11: =N11/N10-1 -> 0.46857991
B12: =B11+1 -> 9 | C12: =C11+365 -> 45380 | D12: 51084 | E12: =D12/D11-1 -> 0.25900185 | G12: =G11+1 -> 9 | H12: =H11+365 -> 45380 | I12: 5292 | J12: =I12/I11-1 -> 0.083981975 | L12: =L11+1 -> 9 | M12: =M11+365 -> 45380 | N12: 33.36337 | O12: =N12/N11-1 -> -0.0020215633
B13: =B12+1 -> 10 | C13: =C12+365 -> 45745 | D13: 60456 | E13: =D13/D12-1 -> 0.18346253 | G13: =G12+1 -> 10 | H13: =H12+365 -> 45745 | I13: 5694 | J13: =I13/I12-1 -> 0.075963719 | L13: =L12+1 -> 10 | M13: =M12+365 -> 45745 | N13: 32.101825 | O13: =N13/N12-1 -> -0.037812289
B14: =B13+1 -> 11 | C14: =C13+365 -> 46110 | D14: =FORECAST(B14,$D$4:$D$13,$B$4:$B$13) -> 56981.593 | E14: =D14/D13-1 -> -0.057470006 | G14: =G13+1 -> 11 | H14: =H13+365 -> 46110 | I14: =FORECAST(G14,$I$4:$I$13,$G$4:$G$13) -> 5953.8007 | J14: =I14/I13-1 -> 0.045627093 | L14: =L13+1 -> 11 | M14: =M13+365 -> 46110 | N14: =FORECAST(L14,$N$4:$N$13,$L$4:$L$13) -> 36.374656 | O14: =N14/N13-1 -> 0.13310246
B15: =B14+1 -> 12 | C15: =C14+365 -> 46475 | D15: =FORECAST(B15,$D$4:$D$13,$B$4:$B$13) -> 62177.428 | E15: =D15/D14-1 -> 0.091184445 | G15: =G14+1 -> 12 | H15: =H14+365 -> 46475 | I15: =FORECAST(G15,$I$4:$I$13,$G$4:$G$13) -> 6506.4695 | J15: =I15/I14-1 -> 0.092826226 | L15: =L14+1 -> 12 | M15: =M14+365 -> 46475 | N15: =FORECAST(L15,$N$4:$N$13,$L$4:$L$13) -> 39.604176 | O15: =N15/N14-1 -> 0.088784875
B16: =B15+1 -> 13 | C16: =C15+365 -> 46840 | D16: =FORECAST(B16,$D$4:$D$13,$B$4:$B$13) -> 67373.263 | E16: =D16/D15-1 -> 0.083564649 | G16: =G15+1 -> 13 | H16: =H15+365 -> 46840 | I16: =FORECAST(G16,$I$4:$I$13,$G$4:$G$13) -> 7059.1384 | J16: =I16/I15-1 -> 0.084941434 | L16: =L15+1 -> 13 | M16: =M15+365 -> 46840 | N16: =FORECAST(L16,$N$4:$N$13,$L$4:$L$13) -> 42.833695 | O16: =N16/N15-1 -> 0.08154492
B17: =B16+1 -> 14 | C17: =C16+365 -> 47205 | D17: =FORECAST(B17,$D$4:$D$13,$B$4:$B$13) -> 72569.098 | E17: =D17/D16-1 -> 0.077120132 | G17: =G16+1 -> 14 | H17: =H16+365 -> 47205 | I17: =FORECAST(G17,$I$4:$I$13,$G$4:$G$13) -> 7611.8072 | J17: =I17/I16-1 -> 0.078291262 | L17: =L16+1 -> 14 | M17: =M16+365 -> 47205 | N17: =FORECAST(L17,$N$4:$N$13,$L$4:$L$13) -> 46.063214 | O17: =N17/N16-1 -> 0.075396702
B18: =B17+1 -> 15 | C18: =C17+365 -> 47570 | D18: =FORECAST(B18,$D$4:$D$13,$B$4:$B$13) -> 77764.933 | E18: =D18/D17-1 -> 0.07159845 | G18: =G17+1 -> 15 | H18: =H17+365 -> 47570 | I18: =FORECAST(G18,$I$4:$I$13,$G$4:$G$13) -> 8164.4761 | J18: =I18/I17-1 -> 0.072606785 | L18: =L17+1 -> 15 | M18: =M17+365 -> 47570 | N18: =FORECAST(L18,$N$4:$N$13,$L$4:$L$13) -> 49.292734 | O18: =N18/N17-1 -> 0.070110594

Sheet Comps_Val
B1: Amount in crores
B2: Comparable Company valuation
D4: Market Data | K4: Financials | O4: Valuation
B5: Company | C5: Ticker | D5: Share Price | E5: Shares Outstanding | F5: Equity Value | G5: Net Debt | H5: Enterprise Value | K5: Revenue | L5: EBITDA | M5: Net Income | O5: EV/Revenue | P5: EV/EBITDA | Q5: P/E
B8: =Comps_Data!C4 -> Titan Company | D8: =Comps_Data!D4 -> 4230.6 | E8: =Comps_Data!E4 -> 88.78 | F8: =E8*D8 -> 375592.67 | G8: =Comps_Data!I4 -> 10881 | H8: =F8+G8 -> 386473.67 | K8: =Comps_Data!K4 -> 75580 | L8: =Comps_Data!L4 -> 8313.8 | M8: =Comps_Data!M4 -> 4766 | O8: =$H8/K8 -> 5.1134383 | P8: =$H8/L8 -> 46.485803 | Q8: =F8/M8 -> 78.806687
B9: =Comps_Data!C5 -> Kalyan Jewellers | D9: =Comps_Data!D5 -> 414.35 | E9: =Comps_Data!E5 -> 103.27 | F9: =E9*D9 -> 42789.925 | G9: =Comps_Data!I5 -> 4303.89 | H9: =F9+G9 -> 47093.815 | K9: =Comps_Data!K5 -> 31649.46 | L9: =Comps_Data!L5 -> 2215.4622 | M9: =Comps_Data!M5 -> 1128.5 | O9: =$H9/K9 -> 1.4879816 | P9: =$H9/L9 -> 21.25688 | Q9: =F9/M9 -> 37.917523
B10: =Comps_Data!C6 -> Thangamayil Jew. | D10: =Comps_Data!D6 -> 3862.6 | E10: =Comps_Data!E6 -> 3.11 | F10: =E10*D10 -> 12012.686 | G10: =Comps_Data!I6 -> 882.56 | H10: =F10+G10 -> 12895.246 | K10: =Comps_Data!K6 -> 7055.32 | L10: =Comps_Data!L6 -> 423.3192 | M10: =Comps_Data!M6 -> 240.4 | O10: =$H10/K10 -> 1.8277337 | P10: =$H10/L10 -> 30.462228 | Q10: =F10/M10 -> 49.969576
B11: =Comps_Data!C7 -> P N Gadgil Jewe. | D11: =Comps_Data!D7 -> 599.1 | E11: =Comps_Data!E7 -> 13.57 | F11: =E11*D11 -> 8129.787 | G11: =Comps_Data!I7 -> 762.44 | H11: =F11+G11 -> 8892.227 | K11: =Comps_Data!K7 -> 8783.01 | L11: =Comps_Data!L7 -> 614.8107 | M11: =Comps_Data!M7 -> 381.55 | O11: =$H11/K11 -> 1.012435 | P11: =$H11/L11 -> 14.463358 | Q11: =F11/M11 -> 21.307265
B12: =Comps_Data!C8 -> PC Jeweller | D12: =Comps_Data!D8 -> 8.43 | E12: =Comps_Data!E8 -> 836.86 | F12: =E12*D12 -> 7054.7298 | G12: =Comps_Data!I8 -> 1530.71 | H12: =F12+G12 -> 8585.4398 | K12: =Comps_Data!K8 -> 3124.56 | L12: =Comps_Data!L8 -> 843.6312 | M12: =Comps_Data!M8 -> 656.35 | O12: =$H12/K12 -> 2.7477276 | P12: =$H12/L12 -> 10.176769 | Q12: =F12/M12 -> 10.748427
B13: =Comps_Data!C9 -> Bluestone Jewel | D13: =Comps_Data!D9 -> 422.9 | E13: =Comps_Data!E9 -> 15.22 | F13: =E13*D13 -> 6436.538 | G13: =Comps_Data!I9 -> 1712.1 | H13: =F13+G13 -> 8148.638 | K13: =Comps_Data!K9 -> 2214.87 | L13: =Comps_Data!L9 -> 354.3792 | M13: =Comps_Data!M9 -> -59.08 | O13: =$H13/K13 -> 3.6790593 | P13: =$H13/L13 -> 22.99412 | Q13: =F13/M13 -> -108.94614
B14: =Comps_Data!C10 -> Ethos | D14: =Comps_Data!D10 -> 2301.2 | E14: =Comps_Data!E10 -> 2.68 | F14: =E14*D14 -> 6167.216 | G14: =Comps_Data!I10 -> 93.82 | H14: =F14+G14 -> 6261.036 | K14: =Comps_Data!K10 -> 1509.55 | L14: =Comps_Data!L10 -> 241.528 | M14: =Comps_Data!M10 -> 96.13 | O14: =$H14/K14 -> 4.1476175 | P14: =$H14/L14 -> 25.922609 | Q14: =F14/M14 -> 64.154957
B15: =Comps_Data!C11 -> Sky Gold & Diam. | D15: =Comps_Data!D11 -> 369.3 | E15: =Comps_Data!E11 -> 15.49 | F15: =E15*D15 -> 5720.457 | G15: =Comps_Data!I11 -> 638.59 | H15: =F15+G15 -> 6359.047 | K15: =Comps_Data!K11 -> 5441.55 | L15: =Comps_Data!L11 -> 380.9085 | M15: =Comps_Data!M11 -> 229.29 | O15: =$H15/K15 -> 1.1686095 | P15: =$H15/L15 -> 16.694421 | Q15: =F15/M15 -> 24.948567
B16: =Comps_Data!C12 -> Senco Gold | D16: =Comps_Data!D12 -> 315.95 | E16: =Comps_Data!E12 -> 16.38 | F16: =E16*D16 -> 5175.261 | G16: =Comps_Data!I12 -> 1823.8 | H16: =F16+G16 -> 6999.061 | K16: =Comps_Data!K12 -> 7773.13 | L16: =Comps_Data!L12 -> 932.7756 | M16: =Comps_Data!M12 -> 485.09 | O16: =$H16/K16 -> 0.90041734 | P16: =$H16/L16 -> 7.5034778 | Q16: =F16/M16 -> 10.668661
B17: =Comps_Data!C13 -> Goldiam Intl. | D17: =Comps_Data!D13 -> 304.1 | E17: =Comps_Data!E13 -> 11.29 | F17: =E17*D17 -> 3433.289 | G17: =Comps_Data!I13 -> -157.84 | H17: =F17+G17 -> 3275.449 | K17: =Comps_Data!K13 -> 940.82 | L17: =Comps_Data!L13 -> 225.7968 | M17: =Comps_Data!M13 -> 156.54 | O17: =$H17/K17 -> 3.4814832 | P17: =$H17/L17 -> 14.50618 | Q17: =F17/M17 -> 21.932343
B19: High | O19: =MAX(O8:O17) -> 5.1134383 | P19: =MAX(P8:P17) -> 46.485803 | Q19: =MAX(Q8:Q17) -> 78.806687
B20: 75th Percentile | O20: =QUARTILE(O8:O17,3) -> 3.6296652 | P20: =QUARTILE(P8:P17,3) -> 25.190487 | Q20: =QUARTILE(Q8:Q17,3) -> 46.956562
B21: Average | O21: =AVERAGE(O8:O17) -> 2.5566503 | P21: =AVERAGE(P8:P17) -> 21.046585 | Q21: =AVERAGE(Q8:Q17) -> 21.150786
B22: Median | O22: =MEDIAN(O8:O17) -> 2.2877306 | P22: =MEDIAN(P8:P17) -> 18.975651 | Q22: =MEDIAN(Q8:Q17) -> 23.440455
B23: 25th Percentile | O23: =QUARTILE(O8:O17,1) -> 1.2484525 | P23: =QUARTILE(P8:P17,1) -> 14.474063 | Q23: =QUARTILE(Q8:Q17,1) -> 13.388136
B24: Low | O24: =MIN(O8:O17) -> 0.90041734 | P24: =MIN(P8:P17) -> 7.5034778 | Q24: =MIN(Q8:Q17) -> -108.94614
B26: Titan Comparable Valuation | O26: EV/Revenue | P26: EV/EBITDA | Q26: P/E
B27: Implied Enterprise Value | O27: =O$22*K8 -> 172906.68 | P27: =P$22*L8 -> 157759.77 | Q27: =Q29+Q28 -> 122598.21
B28: Net Debt | O28: =$G$8 -> 10881 | P28: =$G$8 -> 10881 | Q28: =$G$8 -> 10881
B29: Implied Market Value | O29: =O27-O28 -> 162025.68 | P29: =P27-P28 -> 146878.77 | Q29: =Q22*M8 -> 111717.21
B30: Shares Outstanding | O30: =$E$8 -> 88.78 | P30: =$E$8 -> 88.78 | Q30: =$E$8 -> 88.78
B31: Implied Value per share | O31: =O29/O30 -> 1825.0246 | P31: =P29/P30 -> 1654.4128 | Q31: =Q29/Q30 -> 1258.3601
B33: Source: Screener | O33: =IF(O31>$D$8,"Undervalued","Overvalued") -> Overvalued | P33: =IF(P31>$D$8,"Undervalued","Overvalued") -> Overvalued | Q33: =IF(Q31>$D$8,"Undervalued","Overvalued") -> Overvalued
O34: =$D$8/O$31-1 -> 1.3181058 | P34: =$D$8/P$31-1 -> 1.5571611 | Q34: =$D$8/Q$31-1 -> 2.3619947
O35: =$D$8/O$31-1 -> 1.3181058 | P35: =$D$8/P$31-1 -> 1.5571611 | Q35: =$D$8/Q$31-1 -> 2.3619947

Sheet Comps_Data
B3: S.No. | C3: Name | D3: CMP Rs. | E3: No. Eq. Shares Cr. | F3: Market cap | G3: Debt Rs.Cr. | H3: Cash End Rs.Cr. | J3: EV | K3: Sales Rs.Cr. | L3: EBITDA | M3: NP 12M Rs.Cr.
B4: 1 | C4: Titan Company | D4: 4230.6 | E4: 88.78 | F4: =E4*D4 -> 375592.67 | G4: 12465 | H4: 1584 | I4: =G4-H4 -> 10881 | J4: =F4+G4-H4 -> 386473.67 | K4: 75580 | L4: 8313.8 | M4: 4766
B5: 2 | C5: Kalyan Jewellers | D5: 414.35 | E5: 103.27 | F5: =E5*D5 -> 42789.925 | G5: 5334.96 | H5: 1031.07 | I5: =G5-H5 -> 4303.89 | J5: =F5+G5-H5 -> 47093.815 | K5: 31649.46 | L5: 2215.4622 | M5: 1128.5
B6: 3 | C6: Thangamayil Jew. | D6: 3862.6 | E6: 3.11 | F6: =E6*D6 -> 12012.686 | G6: 1124.35 | H6: 241.79 | I6: =G6-H6 -> 882.56 | J6: =F6+G6-H6 -> 12895.246 | K6: 7055.32 | L6: 423.3192 | M6: 240.4
B7: 4 | C7: P N Gadgil Jewe. | D7: 599.1 | E7: 13.57 | F7: =E7*D7 -> 8129.787 | G7: 1291.13 | H7: 528.69 | I7: =G7-H7 -> 762.44 | J7: =F7+G7-H7 -> 8892.227 | K7: 8783.01 | L7: 614.8107 | M7: 381.55
B8: 5 | C8: PC Jeweller | D8: 8.43 | E8: 836.86 | F8: =E8*D8 -> 7054.7298 | G8: 1594.49 | H8: 63.78 | I8: =G8-H8 -> 1530.71 | J8: =F8+G8-H8 -> 8585.4398 | K8: 3124.56 | L8: 843.6312 | M8: 656.35
B9: 6 | C9: Bluestone Jewel | D9: 422.9 | E9: 15.22 | F9: =E9*D9 -> 6436.538 | G9: 1889.28 | H9: 177.18 | I9: =G9-H9 -> 1712.1 | J9: =F9+G9-H9 -> 8148.638 | K9: 2214.87 | L9: 354.3792 | M9: -59.08
B10: 7 | C10: Ethos | D10: 2301.2 | E10: 2.68 | F10: =E10*D10 -> 6167.216 | G10: 313.84 | H10: 220.02 | I10: =G10-H10 -> 93.82 | J10: =F10+G10-H10 -> 6261.036 | K10: 1509.55 | L10: 241.528 | M10: 96.13
B11: 8 | C11: Sky Gold & Diam. | D11: 369.3 | E11: 15.49 | F11: =E11*D11 -> 5720.457 | G11: 813.72 | H11: 175.13 | I11: =G11-H11 -> 638.59 | J11: =F11+G11-H11 -> 6359.047 | K11: 5441.55 | L11: 380.9085 | M11: 229.29
B12: 9 | C12: Senco Gold | D12: 315.95 | E12: 16.38 | F12: =E12*D12 -> 5175.261 | G12: 2407.77 | H12: 583.97 | I12: =G12-H12 -> 1823.8 | J12: =F12+G12-H12 -> 6999.061 | K12: 7773.13 | L12: 932.7756 | M12: 485.09
B13: 10 | C13: Goldiam Intl. | D13: 304.1 | E13: 11.29 | F13: =E13*D13 -> 3433.289 | G13: 24.19 | H13: 182.03 | I13: =G13-H13 -> -157.84 | J13: =F13+G13-H13 -> 3275.449 | K13: 940.82 | L13: 225.7968 | M13: 156.54
B21: 11 | C21: Vaibhav Global | D21: 192.71 | E21: 16.71 | F21: =E21*D21 -> 3220.1841 | G21: 227.47 | H21: 129.26 | J21: =F21+G21-H21 -> 3318.3941 | K21: 3606.89 | L21: 360.689 | M21: 209.06
B22: 12 | C22: Rajesh Exports | D22: 96.18 | E22: 29.53 | F22: =E22*D22 -> 2840.1954 | G22: 879.02 | H22: 1891.23 | J22: =F22+G22-H22 -> 1827.9854 | K22: 741041.52 | L22: 0 | M22: 167.95
B23: 13 | C23: KDDL Ltd | D23: 2222.9 | E23: 1.23 | F23: =E23*D23 -> 2734.167 | G23: 466.82 | H23: 516.9 | J23: =F23+G23-H23 -> 2684.087 | K23: 1998.02 | L23: 339.6634 | M23: 132.21
B24: 14 | C24: Timex Group | D24: 261.8 | E24: 10.1 | F24: =E24*D24 -> 2644.18 | G24: 12.58 | H24: 0.02 | J24: =F24+G24-H24 -> 2656.74 | K24: 698.8 | L24: 90.844 | M24: 57.34
B25: 15 | C25: D.P. Abhushan | D25: 1015.3 | E25: 2.28 | F25: =E25*D25 -> 2314.884 | G25: 211.65 | H25: 22.9 | J25: =F25+G25-H25 -> 2503.634 | K25: 3447.64 | L25: 275.8112 | M25: 186.38
B26: 16 | C26: Shringar House | D26: 181.04 | E26: 9.64 | F26: =E26*D26 -> 1745.2256 | G26: 185.23 | H26: 3.1 | J26: =F26+G26-H26 -> 1927.3556 | K26: 1871.63 | L26: 131.0141 | M26: 96.71
B27: 17 | C27: Khazanchi Jewell | D27: 645.95 | E27: 2.47 | F27: =E27*D27 -> 1595.4965 | G27: 59.56 | H27: 2.7 | J27: =F27+G27-H27 -> 1652.3565 | K27: 2163.34 | L27: 108.167 | M27: 76.37
B28: 18 | C28: Motisons Jewel | D28: 12.5 | E28: 100.18 | F28: =E28*D28 -> 1252.25 | G28: 54.89 | H28: 7.13 | J28: =F28+G28-H28 -> 1300.01 | K28: 470.83 | L28: 94.166 | M28: 66.54
B29: 19 | C29: Shanti Gold | D29: 173.06 | E29: 7.21 | F29: =E29*D29 -> 1247.7626 | G29: 184.4 | H29: 14.19 | J29: =F29+G29-H29 -> 1417.9726 | K29: 1657.08 | L29: 198.8496 | M29: 127.73
B30: 20 | C30: Laxmi Goldorna | D30: 237.09 | E30: 5.01 | F30: =E30*D30 -> 1187.8209 | G30: 96.72 | H30: 0.25 | J30: =F30+G30-H30 -> 1284.2909 | K30: 105.39 | L30: 24.2397 | M30: 9.74
B31: 21 | C31: PNGS Reva Diamo. | D31: 374.1 | E31: 3.17 | F31: =E31*D31 -> 1185.897 | G31: 90.92 | H31: 39.02 | J31: =F31+G31-H31 -> 1237.797 | K31: 258.18 | L31: 80.0358 | M31: 59.47
B32: 22 | C32: Renaiss. Global | D32: 103.1 | E32: 10.73 | F32: =E32*D32 -> 1106.263 | G32: 713.39 | H32: 145.82 | J32: =F32+G32-H32 -> 1673.833 | K32: 2554.02 | L32: 178.7814 | M32: 82.77
... B40: 30 | C40: Manbro Indust. | D40: 89.7 | E40: 5.8 | F40: =E40*D40 -> 520.26 | G40: 0 | H40: 0.09 | J40: =F40+G40-H40 -> 520.17 | K40: 0 | L40: 0 | M40: 1.39

Sheet Common Size Statement
B2: ="Common Size Income Statement"&" - "&'Data Sheet'!$B$1 -> Common Size Income Statement - TITAN COMPANY LTD
B4: Particulars | C4: ='Data Sheet'!B$16 -> 42460 | D4: ='Data Sheet'!C$16 -> 42825 | E4: ='Data Sheet'!D$16 -> 43190 | F4: ='Data Sheet'!E$16 -> 43555 | G4: ='Data Sheet'!F$16 -> 43921 | H4: ='Data Sheet'!G$16 -> 44286 | I4: ='Data Sheet'!H$16 -> 44651 | J4: ='Data Sheet'!I$16 -> 45016 | ... L4: ='Data Sheet'!K$16 -> 45747
B6: ='Data Sheet'!A17 -> Sales | C6: ='Data Sheet'!B17/'Data Sheet'!B$17 -> 1 | D6: ='Data Sheet'!C17/'Data Sheet'!C$17 -> 1 | E6: ='Data Sheet'!D17/'Data Sheet'!D$17 -> 1 | F6: ='Data Sheet'!E17/'Data Sheet'!E$17 -> 1 | G6: ='Data Sheet'!F17/'Data Sheet'!F$17 -> 1 | H6: ='Data Sheet'!G17/'Data Sheet'!G$17 -> 1 | I6: ='Data Sheet'!H17/'Data Sheet'!H$17 -> 1 | J6: ='Data Sheet'!I17/'Data Sheet'!I$17 -> 1 | ... L6: ='Data Sheet'!K17/'Data Sheet'!K$17 -> 1
B7: ='Data Sheet'!A18 -> Raw Material Cost | C7: ='Data Sheet'!B18/'Data Sheet'!B$17 -> 0.74248419 | D7: ='Data Sheet'!C18/'Data Sheet'!C$17 -> 0.74061277 | E7: ='Data Sheet'!D18/'Data Sheet'!D$17 -> 0.78567064 | F7: ='Data Sheet'!E18/'Data Sheet'!E$17 -> 0.76702706 | G7: ='Data Sheet'!F18/'Data Sheet'!F$17 -> 0.76159035 | H7: ='Data Sheet'!G18/'Data Sheet'!G$17 -> 0.75272593 | I7: ='Data Sheet'!H18/'Data Sheet'!H$17 -> 0.91794854 | J7: ='Data Sheet'!I18/'Data Sheet'!I$17 -> 0.8031793 | ... L7: ='Data Sheet'!K18/'Data Sheet'!K$17 -> 0.91423515
B8: ='Data Sheet'!A19 -> Change in Inventory | C8: ='Data Sheet'!B19/'Data Sheet'!B$17 -> 0.01697693 | D8: ='Data Sheet'!C19/'Data Sheet'!C$17 -> 0.02365689 | E8: ='Data Sheet'!D19/'Data Sheet'!D$17 -> 0.060708683 | F8: ='Data Sheet'!E19/'Data Sheet'!E$17 -> 0.039255212 | G8: ='Data Sheet'!F19/'Data Sheet'!F$17 -> 0.041706251 | H8: ='Data Sheet'!G19/'Data Sheet'!G$17 -> -0.0056366661 | I8: ='Data Sheet'!H19/'Data Sheet'!H$17 -> 0.16649884 | J8: ='Data Sheet'!I19/'Data Sheet'!I$17 -> 0.055058534 | ... L8: ='Data Sheet'!K19/'Data Sheet'!K$17 -> 0.12926757
B9: ='Data Sheet'!A20 -> Power and Fuel | C9: ='Data Sheet'!B20/'Data Sheet'!B$17 -> 0.0036538136 | D9: ='Data Sheet'!C20/'Data Sheet'!C$17 -> 0.0033059771 | E9: ='Data Sheet'!D20/'Data Sheet'!D$17 -> 0.0028114545 | F9: ='Data Sheet'!E20/'Data Sheet'!E$17 -> 0.0024526608 | G9: ='Data Sheet'!F20/'Data Sheet'!F$17 -> 0.0024700741 | H9: ='Data Sheet'!G20/'Data Sheet'!G$17 -> 0.0017094807 | I9: ='Data Sheet'!H20/'Data Sheet'!H$17 -> 0.0015625543 | J9: ='Data Sheet'!I20/'Data Sheet'!I$17 -> 0.0014540974 | ... L9: ='Data Sheet'!K20/'Data Sheet'!K$17 -> 0.0012901945
B10: ='Data Sheet'!A21 -> Other Mfr. Exp | C10: ='Data Sheet'!B21/'Data Sheet'!B$17 -> 0.023208811 | D10: ='Data Sheet'!C21/'Data Sheet'!C$17 -> 0.012097282 | E10: ='Data Sheet'!D21/'Data Sheet'!D$17 -> 0.007743907 | F10: ='Data Sheet'!E21/'Data Sheet'!E$17 -> 0.0097722175 | G10: ='Data Sheet'!F21/'Data Sheet'!F$17 -> 0.010212806 | H10: ='Data Sheet'!G21/'Data Sheet'!G$17 -> 0.0065145075 | I10: ='Data Sheet'!H21/'Data Sheet'!H$17 -> 0.0063543873 | J10: ='Data Sheet'!I21/'Data Sheet'!I$17 -> 0.0055452865 | ... L10: ='Data Sheet'!K21/'Data Sheet'!K$17 -> 0.0053923515
B11: ='Data Sheet'!A22 -> Employee Cost | C11: ='Data Sheet'!B22/'Data Sheet'!B$17 -> 0.062051865 | D11: ='Data Sheet'!C22/'Data Sheet'!C$17 -> 0.067440726 | E11: ='Data Sheet'!D22/'Data Sheet'!D$17 -> 0.056220405 | F11: ='Data Sheet'!E22/'Data Sheet'!E$17 -> 0.051795584 | G11: ='Data Sheet'!F22/'Data Sheet'!F$17 -> 0.057191716 | H11: ='Data Sheet'!G22/'Data Sheet'!G$17 -> 0.049390131 | I11: ='Data Sheet'!H22/'Data Sheet'!H$17 -> 0.047084968 | J11: ='Data Sheet'!I22/'Data Sheet'!I$17 -> 0.040813309 | ... L11: ='Data Sheet'!K22/'Data Sheet'!K$17 -> 0.035794627
B12: ='Data Sheet'!A23 -> Selling and admin | C12: ='Data Sheet'!B23/'Data Sheet'!B$17 -> 0.075065472 | D12: ='Data Sheet'!C23/'Data Sheet'!C$17 -> 0.09133365 | E12: ='Data Sheet'!D23/'Data Sheet'!D$17 -> 0.079269741 | F12: ='Data Sheet'!E23/'Data Sheet'!E$17 -> 0.073530274 | G12: ='Data Sheet'!F23/'Data Sheet'!F$17 -> 0.069827095 | H12: ='Data Sheet'!G23/'Data Sheet'!G$17 -> 0.047542044 | I12: ='Data Sheet'!H23/'Data Sheet'!H$17 -> 0.058925657 | J12: ='Data Sheet'!I23/'Data Sheet'!I$17 -> 0.066913124 | ... L12: ='Data Sheet'!K23/'Data Sheet'!K$17 -> 0.057694852
B13: ='Data Sheet'!A24 -> Other Expenses | C13: ='Data Sheet'!B24/'Data Sheet'!B$17 -> 0.027208495 | D13: ='Data Sheet'!C24/'Data Sheet'!C$17 -> 0.021096719 | E13: ='Data Sheet'!D24/'Data Sheet'!D$17 -> 0.026993561 | F13: ='Data Sheet'!E24/'Data Sheet'!E$17 -> 0.033871594 | G13: ='Data Sheet'!F24/'Data Sheet'!F$17 -> 0.023418203 | H13: ='Data Sheet'!G24/'Data Sheet'!G$17 -> 0.05678248 | I13: ='Data Sheet'!H24/'Data Sheet'!H$17 -> 0.018507587 | J13: ='Data Sheet'!I24/'Data Sheet'!I$17 -> 0.016833025 | ... L13: ='Data Sheet'!K24/'Data Sheet'!K$17 -> 0.020676194
B14: ='Data Sheet'!A25 -> Other Income | C14: ='Data Sheet'!B25/'Data Sheet'!B$17 -> 0.0061485169 | D14: ='Data Sheet'!C25/'Data Sheet'!C$17 -> -0.0031958784 | E14: ='Data Sheet'!D25/'Data Sheet'!D$17 -> 0.0043381512 | F14: ='Data Sheet'!E25/'Data Sheet'!E$17 -> 0.009023931 | G14: ='Data Sheet'!F25/'Data Sheet'!F$17 -> 0.007267718 | H14: ='Data Sheet'!G25/'Data Sheet'!G$17 -> 0.0083163925 | I14: ='Data Sheet'!H25/'Data Sheet'!H$17 -> 0.0061460467 | J14: ='Data Sheet'!I25/'Data Sheet'!I$17 -> 0.0075415896 | ... L14: ='Data Sheet'!K25/'Data Sheet'!K$17 -> 0.0080554453
B15: ='Data Sheet'!A26 -> Depreciation | C15: ='Data Sheet'!B26/'Data Sheet'!B$17 -> 0.0087079601 | D15: ='Data Sheet'!C26/'Data Sheet'!C$17 -> 0.008335074 | E15: ='Data Sheet'!D26/'Data Sheet'!D$17 -> 0.0081533421 | F15: ='Data Sheet'!E26/'Data Sheet'!E$17 -> 0.0082331742 | G15: ='Data Sheet'!F26/'Data Sheet'!F$17 -> 0.016530496 | H15: ='Data Sheet'!G26/'Data Sheet'!G$17 -> 0.017325818 | I15: ='Data Sheet'!H26/'Data Sheet'!H$17 -> 0.013854648 | J15: ='Data Sheet'!I26/'Data Sheet'!I$17 -> 0.010868762 | ... L15: ='Data Sheet'!K26/'Data Sheet'!K$17 -> 0.011462882
B16: ='Data Sheet'!A27 -> Interest | C16: ='Data Sheet'!B27/'Data Sheet'!B$17 -> 0.0037566879 | D16: ='Data Sheet'!C27/'Data Sheet'!C$17 -> 0.0028459757 | E16: ='Data Sheet'!D27/'Data Sheet'!D$17 -> 0.0032829253 | F16: ='Data Sheet'!E27/'Data Sheet'!E$17 -> 0.0026564172 | G16: ='Data Sheet'!F27/'Data Sheet'!F$17 -> 0.0078852366 | H16: ='Data Sheet'!G27/'Data Sheet'!G$17 -> 0.0093790427 | I16: ='Data Sheet'!H27/'Data Sheet'!H$17 -> 0.0075697073 | J16: ='Data Sheet'!I27/'Data Sheet'!I$17 -> 0.0073937153 | ... L16: ='Data Sheet'!K27/'Data Sheet'!K$17 -> 0.015763531
B17: ='Data Sheet'!A28 -> Profit before tax | C17: ='Data Sheet'!B28/'Data Sheet'!B$17 -> 0.076988158 | D17: ='Data Sheet'!C28/'Data Sheet'!C$17 -> 0.073392842 | E17: ='Data Sheet'!D28/'Data Sheet'!D$17 -> 0.094900858 | F17: ='Data Sheet'!E28/'Data Sheet'!E$17 -> 0.098940163 | G17: ='Data Sheet'!F28/'Data Sheet'!F$17 -> 0.099847995 | H17: ='Data Sheet'!G28/'Data Sheet'!G$17 -> 0.061310294 | I17: ='Data Sheet'!H28/'Data Sheet'!H$17 -> 0.10083683 | J17: ='Data Sheet'!I28/'Data Sheet'!I$17 -> 0.10959951 | ... L17: ='Data Sheet'!K28/'Data Sheet'!K$17 -> 0.075013233
... B20: ='Data Sheet'!A31 -> Dividend Amount | C20: ='Data Sheet'!B31/'Data Sheet'!B$17 -> 0.017321914 | D20: ='Data Sheet'!C31/'Data Sheet'!C$17 -> 0.017406904 | E20: ='Data Sheet'!D31/'Data Sheet'!D$17 -> 0.0206529 | F20: ='Data Sheet'!E31/'Data Sheet'!E$17 -> 0.02244354 | G20: ='Data Sheet'!F31/'Data Sheet'!F$17 -> 0.016910507 | H20: ='Data Sheet'!G31/'Data Sheet'!G$17 -> 0.016447976 | I20: ='Data Sheet'!H31/'Data Sheet'!H$17 -> 0.023177888 | J20: ='Data Sheet'!I31/'Data Sheet'!I$17 -> 0.021934689 | ... L20: ='Data Sheet'!K31/'Data Sheet'!K$17 -> 0.016193595
B21: ='Data Sheet'!A33 -> EBITDA | C21: ='Data Sheet'!B33/'Data Sheet'!B$17 -> 0.089275436 | D21: ='Data Sheet'!C33/'Data Sheet'!C$17 -> 0.08564396 | E21: ='Data Sheet'!D33/'Data Sheet'!D$17 -> 0.10808529 | F21: ='Data Sheet'!E33/'Data Sheet'!E$17 -> 0.11061343 | G21: ='Data Sheet'!F33/'Data Sheet'!F$17 -> 0.12464374 | H21: ='Data Sheet'!G33/'Data Sheet'!G$17 -> 0.087968952 | I21: ='Data Sheet'!H33/'Data Sheet'!H$17 -> 0.1213931 | J21: ='Data Sheet'!I33/'Data Sheet'!I$17 -> 0.12727049 | ... L21: ='Data Sheet'!K33/'Data Sheet'!K$17 -> 0.10223965
B23: ="Common Size Balance Sheet"&" - "&'Data Sheet'!$B$1 -> Common Size Balance Sheet - TITAN COMPANY LTD
B25: Particulars | C25: ='Data Sheet'!B$16 -> 42460 | D25: ='Data Sheet'!C$16 -> 42825 | E25: ='Data Sheet'!D$16 -> 43190 | F25: ='Data Sheet'!E$16 -> 43555 | G25: ='Data Sheet'!F$16 -> 43921 | H25: ='Data Sheet'!G$16 -> 44286 | I25: ='Data Sheet'!H$16 -> 44651 | J25: ='Data Sheet'!I$16 -> 45016 | ... L25: ='Data Sheet'!K$16 -> 45747
B27: Total Liabilities | C27: ='Data Sheet'!B61/'Data Sheet'!B$61 -> 1 | D27: ='Data Sheet'!C61/'Data Sheet'!C$61 -> 1 | E27: ='Data Sheet'!D61/'Data Sheet'!D$61 -> 1 | F27: ='Data Sheet'!E61/'Data Sheet'!E$61 -> 1 | G27: ='Data Sheet'!F61/'Data Sheet'!F$61 -> 1 | H27: ='Data Sheet'!G61/'Data Sheet'!G$61 -> 1 | I27: ='Data Sheet'!H61/'Data Sheet'!H$61 -> 1 | J27: ='Data Sheet'!I61/'Data Sheet'!I$61 -> 1 | ... L27: ='Data Sheet'!K61/'Data Sheet'!K$61 -> 1
B28: ='Data Sheet'!A57 -> Equity Share Capital | C28: ='Data Sheet'!B57/'Data Sheet'!B$61 -> 0.013998937 | D28: ='Data Sheet'!C57/'Data Sheet'!C$61 -> 0.010559531 | E28: ='Data Sheet'!D57/'Data Sheet'!D$61 -> 0.0093246116 | F28: ='Data Sheet'!E57/'Data Sheet'!E$61 -> 0.0075816578 | G28: ='Data Sheet'!F57/'Data Sheet'!F$61 -> 0.0065711754 | H28: ='Data Sheet'!G57/'Data Sheet'!G$61 -> 0.0054123084 | I28: ='Data Sheet'!H57/'Data Sheet'!H$61 -> 0.0042004908 | J28: ='Data Sheet'!I57/'Data Sheet'!I$61 -> 0.0032938564 | ... L28: ='Data Sheet'!K57/'Data Sheet'!K$61 -> 0.0021896912
B29: ='Data Sheet'!A58 -> Reserves | C29: ='Data Sheet'!B58/'Data Sheet'!B$61 -> 0.53887551 | D29: ='Data Sheet'!C58/'Data Sheet'!C$61 -> 0.49284157 | E29: ='Data Sheet'!D58/'Data Sheet'!D$61 -> 0.52526825 | F29: ='Data Sheet'!E58/'Data Sheet'!E$61 -> 0.51079861 | G29: ='Data Sheet'!F58/'Data Sheet'!F$61 -> 0.48582398 | H29: ='Data Sheet'!G58/'Data Sheet'!G$61 -> 0.45049866 | I29: ='Data Sheet'!H58/'Data Sheet'!H$61 -> 0.43486879 | J29: ='Data Sheet'!I58/'Data Sheet'!I$61 -> 0.43530718 | ... L29: ='Data Sheet'!K58/'Data Sheet'!K$61 -> 0.28379875
B30: ='Data Sheet'!A59 -> Borrowings | C30: ='Data Sheet'!B59/'Data Sheet'!B$61 -> 0.01782586 | D30: ='Data Sheet'!C59/'Data Sheet'!C$61 -> 0.22389704 | E30: ='Data Sheet'!D59/'Data Sheet'!D$61 -> 0.1776077 | F30: ='Data Sheet'!E59/'Data Sheet'!E$61 -> 0.20435634 | G30: ='Data Sheet'!F59/'Data Sheet'!F$61 -> 0.26299468 | H30: ='Data Sheet'!G59/'Data Sheet'!G$61 -> 0.34286062 | I30: ='Data Sheet'!H59/'Data Sheet'!H$61 -> 0.34335473 | J30: ='Data Sheet'!I59/'Data Sheet'!I$61 -> 0.34666913 | ... L30: ='Data Sheet'!K59/'Data Sheet'!K$61 -> 0.51118219
B31: ='Data Sheet'!A60 -> Other Liabilities | C31: ='Data Sheet'!B60/'Data Sheet'!B$61 -> 0.42929969 | D31: ='Data Sheet'!C60/'Data Sheet'!C$61 -> 0.27270186 | E31: ='Data Sheet'!D60/'Data Sheet'!D$61 -> 0.28779944 | F31: ='Data Sheet'!E60/'Data Sheet'!E$61 -> 0.2772634 | G31: ='Data Sheet'!F60/'Data Sheet'!F$61 -> 0.24461016 | H31: ='Data Sheet'!G60/'Data Sheet'!G$61 -> 0.20122841 | I31: ='Data Sheet'!H60/'Data Sheet'!H$61 -> 0.21757599 | J31: ='Data Sheet'!I60/'Data Sheet'!I$61 -> 0.21472983 | ... L31: ='Data Sheet'!K60/'Data Sheet'!K$61 -> 0.20282938
B33: Total Assets | C33: ='Data Sheet'!B76/'Data Sheet'!B$76 -> 1 | D33: ='Data Sheet'!C76/'Data Sheet'!C$76 -> 1 | E33: ='Data Sheet'!D76/'Data Sheet'!D$76 -> 1 | F33: ='Data Sheet'!E76/'Data Sheet'!E$76 -> 1 | G33: ='Data Sheet'!F76/'Data Sheet'!F$76 -> 1 | H33: ='Data Sheet'!G76/'Data Sheet'!G$76 -> 1 | I33: ='Data Sheet'!H76/'Data Sheet'!H$76 -> 1 | J33: ='Data Sheet'!I76/'Data Sheet'!I$76 -> 1 | ... L33: ='Data Sheet'!K76/'Data Sheet'!K$76 -> 1
B34: ='Data Sheet'!A62 -> Net Block | C34: ='Data Sheet'!B62/'Data Sheet'!B$76 -> 0.12149967 | D34: ='Data Sheet'!C62/'Data Sheet'!C$76 -> 0.14138687 | E34: ='Data Sheet'!D62/'Data Sheet'!D$76 -> 0.15479506 | F34: ='Data Sheet'!E62/'Data Sheet'!E$76 -> 0.13378748 | G34: ='Data Sheet'!F62/'Data Sheet'!F$76 -> 0.19440343 | H34: ='Data Sheet'!G62/'Data Sheet'!G$76 -> 0.15342982 | I34: ='Data Sheet'!H62/'Data Sheet'!H$76 -> 0.12006796 | J34: ='Data Sheet'!I62/'Data Sheet'!I$76 -> 0.11095485 | ... L34: ='Data Sheet'!K62/'Data Sheet'!K$76 -> 0.099938492
B35: ='Data Sheet'!A63 -> Capital Work in Progress | C35: ='Data Sheet'!B63/'Data Sheet'!B$76 -> 0.016826161 | D35: ='Data Sheet'!C63/'Data Sheet'!C$76 -> 0.018087271 | E35: ='Data Sheet'!D63/'Data Sheet'!D$76 -> 0.0045551746 | F35: ='Data Sheet'!E63/'Data Sheet'!E$76 -> 0.0027131028 | G35: ='Data Sheet'!F63/'Data Sheet'!F$76 -> 0.0013290018 | H35: ='Data Sheet'!G63/'Data Sheet'!G$76 -> 0.0019459985 | I35: ='Data Sheet'!H63/'Data Sheet'!H$76 -> 0.0040117047 | J35: ='Data Sheet'!I63/'Data Sheet'!I$76 -> 0.0053293856 | ... L35: ='Data Sheet'!K63/'Data Sheet'!K$76 -> 0.0025833436
B36: ='Data Sheet'!A64 -> Investments | C36: ='Data Sheet'!B64/'Data Sheet'!B$76 -> 0.0047950854 | D36: ='Data Sheet'!C64/'Data Sheet'!C$76 -> 0.051231212 | E36: ='Data Sheet'!D64/'Data Sheet'!D$76 -> 0.0037800492 | F36: ='Data Sheet'!E64/'Data Sheet'!E$76 -> 0.0092588797 | G36: ='Data Sheet'!F64/'Data Sheet'!F$76 -> 0.011665682 | H36: ='Data Sheet'!G64/'Data Sheet'!G$76 -> 0.17173437 | I36: ='Data Sheet'!H64/'Data Sheet'!H$76 -> 0.013875779 | J36: ='Data Sheet'!I64/'Data Sheet'!I$76 -> 0.093079201 | ... L36: ='Data Sheet'!K64/'Data Sheet'!K$76 -> 0.048911305
B37: ='Data Sheet'!A65 -> Other Assets | C37: ='Data Sheet'!B74/'Data Sheet'!B$76 -> 0.10694728 | D37: ='Data Sheet'!C74/'Data Sheet'!C$76 -> 0.086086705 | E37: ='Data Sheet'!D74/'Data Sheet'!D$76 -> 0.11862465 | F37: ='Data Sheet'!E74/'Data Sheet'!E$76 -> 0.12615629 | G37: ='Data Sheet'!F74/'Data Sheet'!F$76 -> 0.14316302 | H37: ='Data Sheet'!G74/'Data Sheet'!G$76 -> 0.10526636 | I37: ='Data Sheet'!H74/'Data Sheet'!H$76 -> 0.11884085 | J37: ='Data Sheet'!I74/'Data Sheet'!I$76 -> 0.10222058 | ... L37: ='Data Sheet'!K74/'Data Sheet'!K$76 -> 0.089900357
B38: ='Data Sheet'!A67 -> Receivables | C38: ='Data Sheet'!B67/'Data Sheet'!B$76 -> 0.030353632 | D38: ='Data Sheet'!C67/'Data Sheet'!C$76 -> 0.024692033 | E38: ='Data Sheet'!D67/'Data Sheet'!D$76 -> 0.031056481 | F38: ='Data Sheet'!E67/'Data Sheet'!E$76 -> 0.0359057 | G38: ='Data Sheet'!F67/'Data Sheet'!F$76 -> 0.023036031 | H38: ='Data Sheet'!G67/'Data Sheet'!G$76 -> 0.022257358 | I38: ='Data Sheet'!H67/'Data Sheet'!H$76 -> 0.026666037 | J38: ='Data Sheet'!I67/'Data Sheet'!I$76 -> 0.024944486 | ... L38: ='Data Sheet'!K67/'Data Sheet'!K$76 -> 0.026276295
B39: ='Data Sheet'!A68 -> Inventory | C39: ='Data Sheet'!B68/'Data Sheet'!B$76 -> 0.70123196 | D39: ='Data Sheet'!C68/'Data Sheet'!C$76 -> 0.58586964 | E39: ='Data Sheet'!D68/'Data Sheet'!D$76 -> 0.62228916 | F39: ='Data Sheet'!E68/'Data Sheet'!E$76 -> 0.601103 | G39: ='Data Sheet'!F68/'Data Sheet'!F$76 -> 0.5982723 | H39: ='Data Sheet'!G68/'Data Sheet'!G$76 -> 0.51131112 | I39: ='Data Sheet'!H68/'Data Sheet'!H$76 -> 0.64229753 | J39: ='Data Sheet'!I68/'Data Sheet'!I$76 -> 0.61376758 | ... L39: ='Data Sheet'!K68/'Data Sheet'!K$76 -> 0.69341862
B40: ='Data Sheet'!A69 -> Cash & Bank | C40: ='Data Sheet'!B69/'Data Sheet'!B$76 -> 0.018346208 | D40: ='Data Sheet'!C69/'Data Sheet'!C$76 -> 0.09264627 | E40: ='Data Sheet'!D69/'Data Sheet'!D$76 -> 0.064899423 | F40: ='Data Sheet'!E69/'Data Sheet'!E$76 -> 0.09107554 | G40: ='Data Sheet'!F69/'Data Sheet'!F$76 -> 0.028130538 | H40: ='Data Sheet'!G69/'Data Sheet'!G$76 -> 0.034054974 | I40: ='Data Sheet'!H69/'Data Sheet'!H$76 -> 0.074240136 | J40: ='Data Sheet'!I69/'Data Sheet'!I$76 -> 0.049703923 | ... L40: ='Data Sheet'!K69/'Data Sheet'!K$76 -> 0.038971583

Sheet DCF>

Sheet DCF
B2: Calculation of PV and FCFF | D2: ='Intrinsic Growth'!K2 -> 45747 | E2: =D2+365 -> 46112 | F2: =E2+365 -> 46477 | G2: =F2+365 -> 46842 | H2: =G2+365 -> 47207 | I2: =H2+365 -> 47572
B4: EBIT | D4: ='Data Sheet'!K33-'Data Sheet'!K26 -> 5488 | E4: =D4*(1+$D$14) -> 6274.462 | F4: =E4*(1+$D$14) -> 7173.6285 | G4: =F4*(1+$D$14) -> 8201.6508 | H4: =G4*(1+$D$14) -> 9376.9945 | I4: =H4*(1+$D$14) -> 10720.772
B5: Tax Rate | D5: 0.25 | E5: =D5 -> 0.25 | F5: =E5 -> 0.25 | G5: =F5 -> 0.25 | H5: =G5 -> 0.25 | I5: =H5 -> 0.25
B6: EBIT(1-T) | D6: =D4*(1-D5) -> 4116 | E6: =E4*(1-E5) -> 4705.8465 | F6: =F4*(1-F5) -> 5380.2214 | G6: =G4*(1-G5) -> 6151.2381 | H6: =H4*(1-H5) -> 7032.7459 | I6: =I4*(1-I5) -> 8040.5789
B7: Less: Reinvestment Rate | D7: ='Intrinsic Growth'!K54 -> 0.10231337 | E7: =D7 -> 0.10231337 | F7: =E7 -> 0.10231337 | G7: =F7 -> 0.10231337 | H7: =G7 -> 0.10231337 | I7: =H7 -> 0.10231337
B8: Free Cash Flow to Firm (FCFF) | D8: =D6*(1-D7) -> 3694.8782 | E8: =E6*(1-E7) -> 4224.3755 | F8: =F6*(1-F7) -> 4829.7528 | G8: =G6*(1-G7) -> 5521.8842 | H8: =H6*(1-H7) -> 6313.202 | I8: =I6*(1-I7) -> 7217.9202
B9: Mid Year Convention | E9: 0.5 | F9: =E9+1 -> 1.5 | G9: =F9+1 -> 2.5 | H9: =G9+1 -> 3.5 | I9: =H9+1 -> 4.5
B10: Discounting Factor | E10: =1/(1+$D$16)^E9 -> 0.94678912 | F10: =1/(1+$D$16)^F9 -> 0.8487109 | G10: =1/(1+$D$16)^G9 -> 0.76079264 | H10: =1/(1+$D$16)^H9 -> 0.68198186 | I10: =1/(1+$D$16)^I9 -> 0.61133512
B12: PV of FCFF | E12: =E8*E10 -> 3999.5928 | F12: =F8*F10 -> 4099.0639 | G12: =G8*G10 -> 4201.0089 | H12: =H8*H10 -> 4305.4892 | I12: =I8*I10 -> 4412.5681
B14: Expected Growth | D14: ='Intrinsic Growth'!K63 -> 0.14330576
B15: Terminal Growth | D15: 0.065
B16: WACC | D16: =WACC!J47 -> 0.1155614
B18: Calculation of Terminal Value
B20: FCFF (n+1) | D20: =I8*(1+D14) -> 8252.2897
B21: WACC | D21: =D16 -> 0.1155614
B22: Terminal Growth Rate | D22: =D15 -> 0.065
B24: Terminal Value | D24: =D20/(D21-D22) -> 163213.23
B26: Calculation of Equity Value per Share
B28: PV of FCFF | D28: =SUM(E12:I12) -> 21017.723
B29: PV of Terminal value | D29: =D24*I10 -> 99777.982
B30: Value of Operating Assets | D30: =SUM(D28:D29) -> 120795.71
B32: Add: Cash | D32: ='Data Sheet'!K69 -> 1584
B33: Less: Debt | D33: =SUM('Raw FS'!N7:N8) -> 18096
B34: Value of Equity | D34: =D30+D32-D33 -> 104283.71
B35: No. of Shares | D35: ='Data Sheet'!B6 -> 88.766701
B37: Equity Value Per Share | D37: =D34/D35 -> 1174.8066
B39: Share Price | D39: ='Data Sheet'!B8 -> 4246.1
B40: Discount/premium | D40: =D39/D37-1 -> 2.6142971
D41: =D40 -> 2.6142971

Sheet Intrinsic Growth
A2: # | B2: Calculation of ROIC | G2: ='Data Sheet'!G$16 -> 44286 | H2: ='Data Sheet'!H$16 -> 44651 | I2: ='Data Sheet'!I$16 -> 45016 | J2: ='Data Sheet'!J$16 -> 45382 | K2: ='Data Sheet'!K$16 -> 45747
B4: Current Assets
B5: ='Raw FS'!B36 -> Inventories | G5: ='Raw FS'!J36 -> 8408 | H5: ='Raw FS'!K36 -> 13609 | I5: ='Raw FS'!L36 -> 16584 | J5: ='Raw FS'!M36 -> 19051 | K5: ='Raw FS'!N36 -> 28184
B6: ='Raw FS'!B37 -> Trade receivables | G6: ='Raw FS'!J37 -> 366 | H6: ='Raw FS'!K37 -> 565 | I6: ='Raw FS'!L37 -> 674 | J6: ='Raw FS'!M37 -> 1018 | K6: ='Raw FS'!N37 -> 1068
B7: ='Raw FS'!B39 -> Loans n Advances | G7: ='Raw FS'!J39 -> 109 | H7: ='Raw FS'!K39 -> 29 | I7: ='Raw FS'!L39 -> 167 | J7: ='Raw FS'!M39 -> 151 | K7: ='Raw FS'!N39 -> 324
B8: ='Raw FS'!B40 -> Other asset items | G8: ='Raw FS'!J40 -> 1622 | H8: ='Raw FS'!K40 -> 2489 | I8: ='Raw FS'!L40 -> 2595 | J8: ='Raw FS'!M40 -> 3650 | K8: ='Raw FS'!N40 -> 3330
B9: Total Current Assets | G9: =SUM(G5:G8) -> 10505 | H9: =SUM(H5:H8) -> 16692 | I9: =SUM(I5:I8) -> 20020 | J9: =SUM(J5:J8) -> 23870 | K9: =SUM(K5:K8) -> 32906
B11: Current Liabilitites
B12: ='Raw FS'!B8 -> Short term Borrowings | G12: ='Raw FS'!J8 -> 4367 | H12: ='Raw FS'!K8 -> 5914 | I12: ='Raw FS'!L8 -> 7494 | J12: ='Raw FS'!M8 -> 9877 | K12: ='Raw FS'!N8 -> 17501
B13: ='Raw FS'!B13 -> Trade Payables | G13: ='Raw FS'!J13 -> 789 | H13: ='Raw FS'!K13 -> 1294 | I13: ='Raw FS'!L13 -> 1214 | J13: ='Raw FS'!M13 -> 1410 | K13: ='Raw FS'!N13 -> 1963
B14: ='Raw FS'!B15 -> Other liability items | G14: ='Raw FS'!J15 -> 2036 | H14: ='Raw FS'!K15 -> 2754 | I14: ='Raw FS'!L15 -> 3817 | J14: ='Raw FS'!M15 -> 4131 | K14: ='Raw FS'!N15 -> 4141
B15: Total Current Liabilities | G15: =SUM(G12:G14) -> 7192 | H15: =SUM(H12:H14) -> 9962 | I15: =SUM(I12:I14) -> 12525 | J15: =SUM(J12:J14) -> 15418 | K15: =SUM(K12:K14) -> 23605
A17: # | B17: Net Working Capital | G17: =G9-G15 -> 3313 | H17: =H9-H15 -> 6730 | I17: =I9-I15 -> 7495 | J17: =J9-J15 -> 8452 | K17: =K9-K15 -> 9301
B19: Non Current Assets
B20: ='Raw FS'!B19 -> Land | G20: ='Raw FS'!J19 -> 108 | H20: ='Raw FS'!K19 -> 136 | I20: ='Raw FS'!L19 -> 144 | J20: ='Raw FS'!M19 -> 163 | K20: ='Raw FS'!N19 -> 163
B21: ='Raw FS'!B20 -> Building | G21: ='Raw FS'!J20 -> 1617 | H21: ='Raw FS'!K20 -> 1853 | I21: ='Raw FS'!L20 -> 2403 | J21: ='Raw FS'!M20 -> 3546 | K21: ='Raw FS'!N20 -> 4177
B22: ='Raw FS'!B21 -> Plant Machinery | G22: ='Raw FS'!J21 -> 739 | H22: ='Raw FS'!K21 -> 768 | I22: ='Raw FS'!L21 -> 838 | J22: ='Raw FS'!M21 -> 899 | K22: ='Raw FS'!N21 -> 1012
B23: ='Raw FS'!B22 -> Equipments | G23: ='Raw FS'!J22 -> 76 | H23: ='Raw FS'!K22 -> 96 | I23: ='Raw FS'!L22 -> 130 | J23: ='Raw FS'!M22 -> 110 | K23: ='Raw FS'!N22 -> 127
B24: ='Raw FS'!B23 -> Computers | G24: ='Raw FS'!J23 -> 142 | H24: ='Raw FS'!K23 -> 159 | I24: ='Raw FS'!L23 -> 204 | J24: ='Raw FS'!M23 -> 212 | K24: ='Raw FS'!N23 -> 228
B25: ='Raw FS'!B24 -> Furniture n fittings | G25: ='Raw FS'!J24 -> 309 | H25: ='Raw FS'!K24 -> 321 | I25: ='Raw FS'!L24 -> 376 | J25: ='Raw FS'!M24 -> 173 | K25: ='Raw FS'!N24 -> 193
B26: ='Raw FS'!B25 -> Vehicles | G26: ='Raw FS'!J25 -> 30 | H26: ='Raw FS'!K25 -> 38 | I26: ='Raw FS'!L25 -> 40 | J26: ='Raw FS'!M25 -> 50 | K26: ='Raw FS'!N25 -> 57
B27: ='Raw FS'!B26 -> Intangible Assets | G27: ='Raw FS'!J26 -> 320 | H27: ='Raw FS'!K26 -> 320 | I27: ='Raw FS'!L26 -> 320 | J27: ='Raw FS'!M26 -> 320 | K27: ='Raw FS'!N26 -> 320
B28: ='Raw FS'!B27 -> Other fixed assets | G28: ='Raw FS'!J27 -> 158 | H28: ='Raw FS'!K27 -> 157 | I28: ='Raw FS'!L27 -> 205 | J28: ='Raw FS'!M27 -> 305 | K28: ='Raw FS'!N27 -> 369
B30: Gross Block | G30: =SUM(G20:G28) -> 3499 | H30: =SUM(H20:H28) -> 3848 | I30: =SUM(I20:I28) -> 4660 | J30: =SUM(J20:J28) -> 5778 | K30: =SUM(K20:K28) -> 6646
B31: ='Raw FS'!B29 -> Accumulated Depreciation | G31: =-'Raw FS'!J29 -> -976 | H31: =-'Raw FS'!K29 -> -1304 | I31: =-'Raw FS'!L29 -> -1662 | J31: =-'Raw FS'!M29 -> -2069 | K31: =-'Raw FS'!N29 -> -2584
A32: # | B32: Net Non Current Assets | G32: =SUM(G30:G31) -> 2523 | H32: =SUM(H30:H31) -> 2544 | I32: =SUM(I30:I31) -> 2998 | J32: =SUM(J30:J31) -> 3709 | K32: =SUM(K30:K31) -> 4062
A34: # | B34: Invested Capital | G34: =G32+G17 -> 5836 | H34: =H32+H17 -> 9274 | I34: =I32+I17 -> 10493 | J34: =J32+J17 -> 12161 | K34: =K32+K17 -> 13363
B35: EBIT | G35: =HistoricalFS!H18-HistoricalFS!H24 -> 1350 | H35: =HistoricalFS!I18-HistoricalFS!I24 -> 2945 | I35: =HistoricalFS!J18-HistoricalFS!J24 -> 4441 | J35: =HistoricalFS!K18-HistoricalFS!K24 -> 4708 | K35: =HistoricalFS!L18-HistoricalFS!L24 -> 5001
A37: # | B37: ROIC | G37: =G35/G34 -> 0.23132282 | H37: =H35/H34 -> 0.31755445 | I37: =I35/I34 -> 0.42323454 | J37: =J35/J34 -> 0.38713922 | K37: =K35/K34 -> 0.37424231
A40: # | B40: Calculation of Reinvestment Rate | G40: ='Data Sheet'!G$16 -> 44286 | H40: ='Data Sheet'!H$16 -> 44651 | I40: ='Data Sheet'!I$16 -> 45016 | J40: ='Data Sheet'!J$16 -> 45382 | K40: ='Data Sheet'!K$16 -> 45747
B42: Net Capex | G42: =SUM('Raw FS'!J59:J60) -> -139 | H42: =SUM('Raw FS'!K59:K60) -> -216 | I42: =SUM('Raw FS'!L59:L60) -> -420 | J42: =SUM('Raw FS'!M59:M60) -> -671 | K42: =SUM('Raw FS'!N59:N60) -> -470
B43: Change in Working Capital | H43: =H17-G17 -> 3417 | I43: =I17-H17 -> 765 | J43: =J17-I17 -> 957 | K43: =K17-J17 -> 849
B45: EBIT | G45: =G35 -> 1350 | H45: =H35 -> 2945 | I45: =I35 -> 4441 | J45: =J35 -> 4708 | K45: =K35 -> 5001
B46: Marginal Tax Rate | G46: 0.25 | H46: 0.25 | I46: 0.25 | J46: 0.25 | K46: 0.25
B47: EBIT(1-T) | G47: =G45*(1-G46) -> 1012.5 | H47: =H45*(1-H46) -> 2208.75 | I47: =I45*(1-I46) -> 3330.75 | J47: =J45*(1-J46) -> 3531 | K47: =K45*(1-K46) -> 3750.75
B49: Reinvestment | H49: =SUM(H42:H43) -> 3201 | I49: =SUM(I42:I43) -> 345 | J49: =SUM(J42:J43) -> 286 | K49: =SUM(K42:K43) -> 379
A51: # | B51: Reinvestment Rate | H51: =H49/H47 -> 1.449236 | I51: =I49/I47 -> 0.10358027 | J51: =J49/J47 -> 0.080996885 | K51: =K49/K47 -> 0.10104646
J53: 4 Year Average | K53: =AVERAGE(H51:K51) -> 0.4337149
J54: 4 Year Median | K54: =MEDIAN(H51:K51) -> 0.10231337
A56: # | B56: Calculation of Growth Rate | G56: ='Data Sheet'!G$16 -> 44286 | H56: ='Data Sheet'!H$16 -> 44651 | I56: ='Data Sheet'!I$16 -> 45016 | J56: ='Data Sheet'!J$16 -> 45382 | K56: ='Data Sheet'!K$16 -> 45747
B58: Reinvestment Rate | H58: =H51 -> 1.449236 | I58: =I51 -> 0.10358027 | J58: =J51 -> 0.080996885 | K58: =K51 -> 0.10104646
B59: ROIC | G59: =G37 -> 0.23132282 | H59: =H37 -> 0.31755445 | I59: =I37 -> 0.42323454 | J59: =J37 -> 0.38713922 | K59: =K37 -> 0.37424231
A61: # | B61: Intrinsic Growth | H61: =H58*H59 -> 0.46021134 | I61: =I58*I59 -> 0.04383875 | J61: =J58*J59 -> 0.03135707 | K61: =K58*K59 -> 0.03781586
J63: 4 Year Average | K63: =AVERAGE(H61:K61) -> 0.14330576
J64: 4 Year Median | K64: =MEDIAN(H61:K61) -> 0.040827305

Sheet WACC
B2: Weighted Average Cost of Capital
B4: All figures are in INR unless stated otherwise.
B6: Peer Comps
G7: Debt/ | H7: Debt/ | I7: Levered | J7: Unlevered
B8: Name | C8: Country | D8: Total Debt | E8: Total Equity | F8: Tax Rate 1 | G8: Equity | H8: Capital | I8: Beta 2 | J8: Beta 3
B10: ='Beta - Comps'!C3 -> Titan Company | C10: India | D10: ='Beta - Comps'!F3 -> 12465 | E10: ='Beta - Comps'!E3 -> 376912.29 | F10: 0.3 | G10: =D10/E10 -> 0.033071355 | H10: =D10/(D10+E10) -> 0.032012653 | I10: ='Titan Beta Regression'!J6 -> 1.1953036 | J10: =I10/(1+(1-F10)*G10) -> 1.1682584
B11: ='Beta - Comps'!C4 -> Kalyan Jewellers | C11: India | D11: ='Beta - Comps'!F4 -> 5334.96 | E11: ='Beta - Comps'!E4 -> 43400.23 | F11: 0.3 | G11: =D11/E11 -> 0.12292469 | H11: =D11/(D11+E11) -> 0.10946833 | I11: ='Kalyan J Regression'!J6 -> 0.057413536 | J11: =I11/(1+(1-F11)*G11) -> 0.052864675
B12: ='Beta - Comps'!C5 -> Thangamayil Jew. | C12: India | D12: ='Beta - Comps'!F5 -> 1124.35 | E12: ='Beta - Comps'!E5 -> 11659.68 | F12: 0.3 | G12: =D12/E12 -> 0.096430605 | H12: =D12/(D12+E12) -> 0.087949575 | I12: ='Thangamayil J Regression'!J6 -> 1.0684007 | J12: =I12/(1+(1-F12)*G12) -> 1.0008424
B13: ='Beta - Comps'!C6 -> P N Gadgil Jewe. | C13: India | D13: ='Beta - Comps'!F6 -> 1291.13 | E13: ='Beta - Comps'!E6 -> 7904.82 | F13: 0.3 | G13: =D13/E13 -> 0.16333452 | H13: =D13/(D13+E13) -> 0.14040202 | I13: ='P N Gadgil J Regression'!J6 -> -0.42304575 | J13: =I13/(1+(1-F13)*G13) -> -0.37963994
B14: ='Beta - Comps'!C7 -> PC Jeweller | C14: India | D14: ='Beta - Comps'!F7 -> 1594.49 | E14: ='Beta - Comps'!E7 -> 7054.05 | F14: 0.3 | G14: =D14/E14 -> 0.22603894 | H14: =D14/(D14+E14) -> 0.18436522 | I14: ='PC Jeweller Regression'!J6 -> 2.5407188 | J14: =I14/(1+(1-F14)*G14) -> 2.1936271
B15: ='Beta - Comps'!C8 -> Bluestone Jewel | C15: India | D15: ='Beta - Comps'!F8 -> 1889.28 | E15: ='Beta - Comps'!E8 -> 6494.97 | F15: 0.3 | G15: =D15/E15 -> 0.29088356 | H15: =D15/(D15+E15) -> 0.22533679 | I15: ='Bluestone Jewel Regression'!J6 -> -1.7078554 | J15: =I15/(1+(1-F15)*G15) -> -1.4189342
E16: Average | F16: =AVERAGE(F10:F15) -> 0.3 | G16: =AVERAGE(G10:G15) -> 0.15544728 | H16: =AVERAGE(H10:H15) -> 0.12992243 | I16: =AVERAGE(I10:I15) -> 0.4551559 | J16: =AVERAGE(J10:J15) -> 0.43616976
E17: Median | F17: =MEDIAN(F10:F15) -> 0.3 | G17: =MEDIAN(G10:G15) -> 0.14312961 | H17: =MEDIAN(H10:H15) -> 0.12493518 | I17: =MEDIAN(I10:I15) -> 0.56290713 | J17: =MEDIAN(J10:J15) -> 0.52685356
B20: Cost of Debt | G20: Cost of Equity
B22: Pre-tax Cost of Debt | E22: =16/712 -> 0.02247191 | F22: =HistoricalFS!L21/('Raw FS'!N7+'Raw FS'!N8) -> 0.052663572 | G22: Risk Free Rate | J22: 0.07043
B23: Tax Rate | E23: =F17 -> 0.3 | F23: =E23 -> 0.3 | G23: Equity Risk Premium | J23: =Rm!G7-WACC!J22 -> 0.081062308
B24: After Tax Cost of Debt | E24: 0.0588 | F24: {=F22(1-F23)} -> #REF! | G24: Levered Beta 4 | J24: =J33 -> 0.66130824
G25: Cost of Equity | J25: =J22+(J23*J24) -> 0.12403717
B28: Capital Structure | G28: Levered Beta
D30: Current | E30: Target | G30: Comps Median Unlevered Beta | J30: =J17 -> 0.52685356
B31: Total Debt | C31: =D10 -> 12465 | D31: =C31/$C$33 -> 0.032012653 | E31: =H16 -> 0.12992243 | G31: Target Debt/ Equity | J31: =E35 -> 0.14932282
B32: Market Capitalization | C32: =E10 -> 376912.29 | D32: =D33-D31 -> 0.96798735 | E32: =E33-E31 -> 0.87007757 | G32: Tax Rate | J32: =F17 -> 0.3
B33: Total Capitalization | C33: =SUM(C31:C32) -> 389377.29 | D33: 1 | E33: 1 | G33: Levered Beta | J33: =J30*(1+(1-J31)*J32) -> 0.66130824
B35: Debt / Equity | D35: =D31/D32 -> 0.033071355 | E35: =E31/E32 -> 0.14932282 | G35: Weighted Average Cost of Capital
B37: 1. Tax Rate considered as Marginal Tax Rate for the country | G37: Debt Capital | J37: 0.084
B38: 2. Levered Beta is based on 5 year monthly data | G38: Equity Capital | J38: 0.3
B39: 3. Unlevered Beta = Levered Beta/(1+(1-Tax Rate) x Debt/Equity) | G39: After Tax Cost of Debt | J39: 0.0588
B40: 3. Levered Beta = Unlevered Beta/(1+(1-Tax Rate) x Debt/Equity)
B41: 4. levered Beta = Unlevered Beta*(1+(1-Tax Rate)*Debt/Equity) | G41: Cost of Equity | J41: =J25 -> 0.12403717
G42: Equity Weight | J42: =E32 -> 0.87007757
G44: Cost of Debt | J44: =E24 -> 0.0588
G45: Debt Weight | J45: =E31 -> 0.12992243
G47: WACC | J47: =(J41*J42)+(J44*J45) -> 0.1155614

Sheet Raw FS
B2: Particular | C2: 41699 | D2: 42064 | E2: 42430 | F2: 42795 | G2: 43160 | H2: 43525 | I2: 43891 | J2: 44256 | K2: 44621 | L2: 44986 | M2: 45352 | N2: 45717
B3: Balance Sheet
B4: Equity Capital | C4: 89 | D4: 89 | E4: 89 | F4: 89 | G4: 89 | H4: 89 | I4: 89 | J4: 89 | K4: 89 | L4: 89 | M4: 89 | N4: 89
B5: Reserves | C5: 2434 | D5: 2995 | E5: 3418 | F5: 4144 | G5: 5001 | H5: 5981 | I5: 6580 | J5: 7408 | K5: 9214 | L5: 11762 | M5: 9304 | N5: 11535
B6: Borrowings -
B7: Long term Borrowings | C7: 0 | D7: 0 | E7: 0 | F7: 0 | G7: 0 | H7: 32 | I7: 17 | J7: 9 | K7: 2 | L7: 0 | M7: 3302 | N7: 595
B8: Short term Borrowings | C8: 807 | D8: 100 | E8: 113 | F8: 1882 | G8: 1691 | H8: 2353 | I8: 2291 | J8: 4367 | K8: 5914 | L8: 7494 | M8: 9877 | N8: 17501
B9: Lease Liabilities | C9: 0 | D9: 0 | E9: 0 | F9: 0 | G9: 0 | H9: 0 | I9: 1243 | J9: 1256 | K9: 1359 | L9: 1873 | M9: 2349 | N9: 2681
B10: Other Borrowings | C10: 0 | D10: 0 | E10: 0 | F10: 0 | G10: 0 | H10: 8 | I10: 11 | J10: 6 | K10: 0 | L10: 0 | M10: 0 | N10: 0
B11: Other Liabilities -
B12: Non controlling int | C12: 0 | D12: 0 | E12: 0 | F12: 26 | G12: -2 | H12: 14 | I12: 4 | J12: 5 | K12: 30 | L12: 53 | M12: 0 | N12: 0
B13: Trade Payables | C13: 859 | D13: 1940 | E13: 1655 | F13: 783 | G13: 878 | H13: 906 | I13: 596 | J13: 789 | K13: 1294 | L13: 1214 | M13: 1410 | N13: 1963
B14: Advance from Customers | C14: 1418 | D14: 160 | E14: 710 | F14: 943 | G14: 233 | H14: 290 | I14: 386 | J14: 479 | K14: 532 | L14: 718 | M14: 1085 | N14: 2140
B15: Other liability items | C15: 504 | D15: 585 | E15: 358 | F15: 541 | G15: 1631 | H15: 2037 | I15: 2327 | J15: 2036 | K15: 2754 | L15: 3817 | M15: 4131 | N15: 4141
B16: Total Liabilities | C16: 6111 | D16: 5868 | E16: 6342 | F16: 8408 | G16: 9521 | H16: 11710 | I16: 13544 | J16: 16444 | K16: 21188 | L16: 27020 | M16: 31547 | N16: 40645
B18: Fixed Assets -
B19: Land | C19: 95 | D19: 104 | E19: 85 | F19: 85 | G19: 85 | H19: 85 | I19: 108 | J19: 108 | K19: 136 | L19: 144 | M19: 163 | N19: 163
B20: Building | C20: 121 | D20: 156 | E20: 137 | F20: 198 | G20: 341 | H20: 386 | I20: 1473 | J20: 1617 | K20: 1853 | L20: 2403 | M20: 3546 | N20: 4177
B21: Plant Machinery | C21: 632 | D21: 719 | E21: 445 | F21: 473 | G21: 563 | H21: 630 | I21: 724 | J21: 739 | K21: 768 | L21: 838 | M21: 899 | N21: 1012
B22: Equipments | C22: 23 | D22: 24 | E22: 18 | F22: 24 | G22: 34 | H22: 50 | I22: 70 | J22: 76 | K22: 96 | L22: 130 | M22: 110 | N22: 127
B23: Computers | C23: 0 | D23: 0 | E23: 0 | F23: 46 | G23: 72 | H23: 92 | I23: 119 | J23: 142 | K23: 159 | L23: 204 | M23: 212 | N23: 228
B24: Furniture n fittings | C24: 174 | D24: 189 | E24: 107 | F24: 138 | G24: 203 | H24: 251 | I24: 313 | J24: 309 | K24: 321 | L24: 376 | M24: 173 | N24: 193
B25: Vehicles | C25: 14 | D25: 17 | E25: 11 | F25: 10 | G25: 16 | H25: 22 | I25: 28 | J25: 30 | K25: 38 | L25: 40 | M25: 50 | N25: 57
B26: Intangible Assets | C26: 0 | D26: 0 | E26: 13 | F26: 318 | G26: 319 | H26: 319 | I26: 333 | J26: 320 | K26: 320 | L26: 320 | M26: 320 | N26: 320
B27: Other fixed assets | C27: 73 | D27: 73 | E27: 20 | F27: 26 | G27: 69 | H27: 96 | I27: 135 | J27: 158 | K27: 157 | L27: 205 | M27: 305 | N27: 369
B28: Gross Block | C28: 1132 | D28: 1282 | E28: 836 | F28: 1318 | G28: 1704 | H28: 1931 | I28: 3303 | J28: 3499 | K28: 3848 | L28: 4660 | M28: 5778 | N28: 6646
B29: Accumulated Depreciation | C29: 518 | D29: 583 | E29: 66 | F29: 130 | G29: 230 | H29: 365 | I29: 670 | J29: 976 | K29: 1304 | L29: 1662 | M29: 2069 | N29: 2584
B30: Net Block | C30: =C28-C29 -> 614 | D30: =D28-D29 -> 699 | E30: =E28-E29 -> 770 | F30: =F28-F29 -> 1188 | G30: =G28-G29 -> 1474 | H30: =H28-H29 -> 1566 | I30: =I28-I29 -> 2633 | J30: =J28-J29 -> 2523 | ... N30: =N28-N29 -> 4062
B32: CWIP | C32: 33 | D32: 55 | E32: 107 | F32: 152 | G32: 43 | H32: 32 | I32: 18 | J32: 32 | K32: 85 | L32: 144 | M32: 97 | N32: 105
B33: Investments | C33: 3 | D33: 3 | E33: 30 | F33: 431 | G33: 36 | H33: 108 | I33: 158 | J33: 2824 | K33: 294 | L33: 2515 | M33: 2345 | N33: 1988
B35: Other Assets -
B36: Inventories | C36: 3869 | D36: 4049 | E36: 4447 | F36: 4926 | G36: 5925 | H36: 7039 | I36: 8103 | J36: 8408 | K36: 13609 | L36: 16584 | M36: 19051 | N36: 28184
B37: Trade receivables | C37: 154 | D37: 190 | E37: 192 | F37: 208 | G37: 296 | H37: 420 | I37: 312 | J37: 366 | K37: 565 | L37: 674 | M37: 1018 | N37: 1068
B38: Cash Equivalents | C38: 893 | D38: 214 | E38: 116 | F38: 779 | G38: 618 | H38: 1066 | I38: 381 | J38: 560 | K38: 1573 | L38: 1343 | M38: 1526 | N38: 1584
B39: Loans n Advances | C39: 24 | D39: 47 | E39: 87 | F39: 122 | G39: 141 | H39: 25 | I39: 142 | J39: 109 | K39: 29 | L39: 167 | M39: 151 | N39: 324
B40: Other asset items | C40: 520 | D40: 611 | E40: 591 | F40: 602 | G40: 988 | H40: 1452 | I40: 1797 | J40: 1622 | K40: 2489 | L40: 2595 | M40: 3650 | N40: 3330
B41: Total Assets | C41: 6111 | D41: 5868 | E41: 6342 | F41: 8408 | G41: 9521 | H41: 11710 | I41: 13544 | J41: 16444 | K41: 21188 | L41: 27020 | M41: 31547 | N41: 40645
B45: Cash Flows
B46: Particular | C46: 41699 | D46: 42064 | E46: 42430 | F46: 42795 | G46: 43160 | H46: 43525 | I46: 43891 | J46: 44256 | K46: 44621 | L46: 44986 | M46: 45352 | N46: 45717
B47: Cash from Operating Activity -
B48: Profit from operations | C48: 1049 | D48: 1163 | E48: 942 | F48: 1073 | G48: 1642 | H48: 2183 | I48: 2481 | J48: 1789 | K48: 3298 | L48: 4937 | M48: 5404 | N48: 5774
B49: Receivables | C49: 12 | D49: -39 | E49: 0 | F49: -12 | G49: -90 | H49: -139 | I49: 109 | J49: -59 | K49: -207 | L49: -112 | M49: -348 | N49: -95
B50: Inventory | C50: -189 | D50: -180 | E50: -398 | F50: -448 | G50: -996 | H50: -1120 | I50: -1057 | J50: -316 | K50: -5199 | L50: -2977 | M50: -2462 | N50: -9072
B51: Payables | C51: -1239 | D51: 1079 | E51: -245 | F51: 238 | G51: 95 | H51: 32 | I51: -310 | J51: 195 | K51: 504 | L51: -89 | M51: 196 | N51: 564
B52: Loans Advances | C52: -6 | D52: -71 | E52: -66 | F52: 0 | G52: 3 | H52: -24 | I52: -20 | J52: -8 | K52: -3 | L52: -18 | M52: -21 | N52: 4
B53: Operating borrowings | C53: 0 | D53: 0 | E53: 0 | F53: 763 | G53: -270 | H53: 741 | I53: -768 | J53: 2625 | K53: 1188 | L53: -99 | M53: 42 | N53: 2468
B54: Other WC items | C54: 104 | D54: -1204 | E54: 545 | F54: 375 | G54: 22 | H54: 206 | I54: -226 | J54: 184 | K54: 497 | L54: 882 | M54: 57 | N54: 905
B55: Working capital changes | C55: -1318 | D55: -415 | E55: -163 | F55: 916 | G55: -1237 | H55: -304 | I55: -2272 | J55: 2621 | K55: -3220 | L55: -2413 | M55: -2536 | N55: -5226
B56: Direct taxes | C56: -285 | D56: -245 | E56: -202 | F56: -277 | G56: -456 | H56: -636 | I56: -557 | J56: -271 | K56: -802 | L56: -1154 | M56: -1173 | N56: -1089
B58: Cash from Investing Activity -
B59: Fixed assets purchased | C59: -213 | D59: -209 | E59: -254 | F59: -256 | G59: -305 | H59: -265 | I59: -355 | J59: -146 | K59: -224 | L59: -432 | M59: -691 | N59: -494
B60: Fixed assets sold | C60: 2 | D60: 2 | E60: 2 | F60: 5 | G60: 6 | H60: 1 | I60: 10 | J60: 7 | K60: 8 | L60: 12 | M60: 20 | N60: 24
B61: Investments purchased | C61: 0 | D61: -135 | E61: -1078 | F61: -325 | G61: 0 | H61: -36 | I61: -13 | J61: -2656 | K61: -253 | L61: -2104 | M61: -21893 | N61: -15342
B62: Investments sold | C62: 0 | D62: 135 | E62: 1083 | F62: 0 | G62: 412 | H62: 18 | I62: 0 | J62: 43 | K62: 2870 | L62: 0 | M62: 22213 | N62: 15747
B63: Interest received | C63: 112 | D63: 77 | E63: 58 | F63: 41 | G63: 64 | H63: 85 | I63: 73 | J63: 49 | K63: 56 | L63: 143 | M63: 249 | N63: 288
B64: Investment in group cos | C64: 0 | D64: 0 | E64: -18 | F64: 0 | G64: 0 | H64: 0 | I64: 0 | J64: 0 | K64: 0 | L64: 0 | M64: 0 | N64: 0
B65: Acquisition of companies | C65: 0 | D65: 0 | E65: 0 | F65: -385 | G65: 0 | H65: 0 | I65: 0 | J65: 0 | K65: 0 | L65: 0 | M65: 0 | N65: 0
B66: Inter corporate deposits | C66: -90 | D66: -48 | E66: 38 | F66: 5 | G66: -35 | H66: -115 | I66: 200 | J66: -50 | K66: -344 | L66: 294 | M66: -143 | N66: 243
B67: Other investing items | C67: -82 | D67: 60 | E67: 10 | F67: -38 | G67: -43 | H67: -485 | I67: 359 | J67: -46 | K67: -948 | L67: 273 | M67: 56 | N67: 80
B69: Cash from Financing Activity -
B70: Proceeds from borrowings | C70: 0 | D70: 0 | E70: 0 | F70: 0 | G70: 0 | H70: 0 | I70: 693 | J70: 0 | K70: 349 | L70: 1684 | M70: 5629 | N70: 2599
B71: Repayment of borrowings | C71: 0 | D71: 0 | E71: 0 | F71: 0 | G71: 0 | H71: -39 | I71: 0 | J71: -562 | K71: -7 | L71: -7 | M71: 0 | N71: -378
B72: Interest paid fin | C72: -87 | D72: -81 | E72: -42 | F72: -38 | G72: -54 | H72: -53 | I72: -399 | J72: -317 | K72: -218 | L72: -300 | M72: -619 | N72: -538
B73: Dividends paid | C73: -185 | D73: -185 | E73: -394 | F73: -4 | G73: -277 | H73: -397 | I73: -536 | J73: -355 | K73: -355 | L73: -666 | M73: -888 | N73: -976
B74: Financial liabilities | C74: 0 | D74: 0 | E74: 0 | F74: 0 | G74: 0 | H74: 0 | I74: 0 | J74: 0 | K74: -172 | L74: -254 | M74: -318 | N74: -700
B75: Share application money | C75: 25 | D75: 17 | E75: 17 | F75: 8 | G75: 4 | H75: 15 | I75: 2 | J75: 1 | K75: 0 | L75: 0 | M75: 0 | N75: 0
B76: Other financing items | C76: 770 | D76: -739 | E76: -68 | F76: -124 | G76: 79 | H76: 0 | I76: 0 | J76: 0 | K76: 0 | L76: 0 | M76: -5133 | N76: -14
B78: Net Cash Flow | C78: -329 | D78: -620 | E78: -88 | F78: 594 | G78: -206 | H78: -43 | I78: -355 | J78: 106 | K78: 38 | L78: 13 | M78: 177 | N78: -2

Sheet Balance Sheet
A1: ='Profit & Loss'!A1 -> TITAN COMPANY LTD | E1: =UPDATE | J1: SCREENER.IN
A3: Narration | B3: ='Data Sheet'!B56 -> 42460 | C3: ='Data Sheet'!C56 -> 42825 | D3: ='Data Sheet'!D56 -> 43190 | E3: ='Data Sheet'!E56 -> 43555 | F3: ='Data Sheet'!F56 -> 43921 | G3: ='Data Sheet'!G56 -> 44286 | H3: ='Data Sheet'!H56 -> 44651 | I3: ='Data Sheet'!I56 -> 45016 | ... K3: ='Data Sheet'!K56 -> 45747
A4: Equity Share Capital | B4: ='Data Sheet'!B57 -> 88.78 | C4: ='Data Sheet'!C57 -> 88.78 | D4: ='Data Sheet'!D57 -> 88.78 | E4: ='Data Sheet'!E57 -> 88.78 | F4: ='Data Sheet'!F57 -> 89 | G4: ='Data Sheet'!G57 -> 89 | H4: ='Data Sheet'!H57 -> 89 | I4: ='Data Sheet'!I57 -> 89 | ... K4: ='Data Sheet'!K57 -> 89
A5: Reserves | B5: ='Data Sheet'!B58 -> 3417.5 | C5: ='Data Sheet'!C58 -> 4143.6 | D5: ='Data Sheet'!D58 -> 5001.1 | E5: ='Data Sheet'!E58 -> 5981.37 | F5: ='Data Sheet'!F58 -> 6580 | G5: ='Data Sheet'!G58 -> 7408 | H5: ='Data Sheet'!H58 -> 9214 | I5: ='Data Sheet'!I58 -> 11762 | ... K5: ='Data Sheet'!K58 -> 11535
A6: Borrowings | B6: ='Data Sheet'!B59 -> 113.05 | C6: ='Data Sheet'!C59 -> 1882.43 | D6: ='Data Sheet'!D59 -> 1691.01 | E6: ='Data Sheet'!E59 -> 2392.98 | F6: ='Data Sheet'!F59 -> 3562 | G6: ='Data Sheet'!G59 -> 5638 | H6: ='Data Sheet'!H59 -> 7275 | I6: ='Data Sheet'!I59 -> 9367 | ... K6: ='Data Sheet'!K59 -> 20777
A7: Other Liabilities | B7: ='Data Sheet'!B60 -> 2722.58 | C7: ='Data Sheet'!C60 -> 2292.76 | D7: ='Data Sheet'!D60 -> 2740.15 | E7: ='Data Sheet'!E60 -> 3246.71 | F7: ='Data Sheet'!F60 -> 3313 | G7: ='Data Sheet'!G60 -> 3309 | H7: ='Data Sheet'!H60 -> 4610 | I7: ='Data Sheet'!I60 -> 5802 | ... K7: ='Data Sheet'!K60 -> 8244
A8: Total | B8: ='Data Sheet'!B61 -> 6341.91 | C8: ='Data Sheet'!C61 -> 8407.57 | D8: ='Data Sheet'!D61 -> 9521.04 | E8: ='Data Sheet'!E61 -> 11709.84 | F8: ='Data Sheet'!F61 -> 13544 | G8: ='Data Sheet'!G61 -> 16444 | H8: ='Data Sheet'!H61 -> 21188 | I8: ='Data Sheet'!I61 -> 27020 | ... K8: ='Data Sheet'!K61 -> 40645
A10: Net Block | B10: ='Data Sheet'!B62 -> 770.54 | C10: ='Data Sheet'!C62 -> 1188.72 | D10: ='Data Sheet'!D62 -> 1473.81 | E10: ='Data Sheet'!E62 -> 1566.63 | F10: ='Data Sheet'!F62 -> 2633 | G10: ='Data Sheet'!G62 -> 2523 | H10: ='Data Sheet'!H62 -> 2544 | I10: ='Data Sheet'!I62 -> 2998 | ... K10: ='Data Sheet'!K62 -> 4062
A11: Capital Work in Progress | B11: ='Data Sheet'!B63 -> 106.71 | C11: ='Data Sheet'!C63 -> 152.07 | D11: ='Data Sheet'!D63 -> 43.37 | E11: ='Data Sheet'!E63 -> 31.77 | F11: ='Data Sheet'!F63 -> 18 | G11: ='Data Sheet'!G63 -> 32 | H11: ='Data Sheet'!H63 -> 85 | I11: ='Data Sheet'!I63 -> 144 | ... K11: ='Data Sheet'!K63 -> 105
A12: Investments | B12: ='Data Sheet'!B64 -> 30.41 | C12: ='Data Sheet'!C64 -> 430.73 | D12: ='Data Sheet'!D64 -> 35.99 | E12: ='Data Sheet'!E64 -> 108.42 | F12: ='Data Sheet'!F64 -> 158 | G12: ='Data Sheet'!G64 -> 2824 | H12: ='Data Sheet'!H64 -> 294 | I12: ='Data Sheet'!I64 -> 2515 | ... K12: ='Data Sheet'!K64 -> 1988
A13: Other Assets | B13: ='Data Sheet'!B65 -> 5434.25 | C13: ='Data Sheet'!C65 -> 6636.05 | D13: ='Data Sheet'!D65 -> 7967.87 | E13: ='Data Sheet'!E65 -> 10003.02 | F13: ='Data Sheet'!F65 -> 10735 | G13: ='Data Sheet'!G65 -> 11065 | H13: ='Data Sheet'!H65 -> 18265 | I13: ='Data Sheet'!I65 -> 21363 | ... K13: ='Data Sheet'!K65 -> 34490
A14: Total | B14: ='Data Sheet'!B66 -> 6341.91 | C14: ='Data Sheet'!C66 -> 8407.57 | D14: ='Data Sheet'!D66 -> 9521.04 | E14: ='Data Sheet'!E66 -> 11709.84 | F14: ='Data Sheet'!F66 -> 13544 | G14: ='Data Sheet'!G66 -> 16444 | H14: ='Data Sheet'!H66 -> 21188 | I14: ='Data Sheet'!I66 -> 27020 | ... K14: ='Data Sheet'!K66 -> 40645
A16: Working Capital | B16: =B13-B7 -> 2711.67 | C16: =C13-C7 -> 4343.29 | D16: =D13-D7 -> 5227.72 | E16: =E13-E7 -> 6756.31 | F16: =F13-F7 -> 7422 | G16: =G13-G7 -> 7756 | H16: =H13-H7 -> 13655 | I16: =I13-I7 -> 15561 | ... K16: =K13-K7 -> 26246
A17: Debtors | B17: ='Data Sheet'!B67 -> 192.5 | C17: ='Data Sheet'!C67 -> 207.6 | D17: ='Data Sheet'!D67 -> 295.69 | E17: ='Data Sheet'!E67 -> 420.45 | F17: ='Data Sheet'!F67 -> 312 | G17: ='Data Sheet'!G67 -> 366 | H17: ='Data Sheet'!H67 -> 565 | I17: ='Data Sheet'!I67 -> 674 | ... K17: ='Data Sheet'!K67 -> 1068
A18: Inventory | B18: ='Data Sheet'!B68 -> 4447.15 | C18: ='Data Sheet'!C68 -> 4925.74 | D18: ='Data Sheet'!D68 -> 5924.84 | E18: ='Data Sheet'!E68 -> 7038.82 | F18: ='Data Sheet'!F68 -> 8103 | G18: ='Data Sheet'!G68 -> 8408 | H18: ='Data Sheet'!H68 -> 13609 | I18: ='Data Sheet'!I68 -> 16584 | ... K18: ='Data Sheet'!K68 -> 28184
A20: Debtor Days | B20: =IF('Profit & Loss'!B4>0,'Balance Sheet'!B17/('Profit & Loss'!B4/365),0) -> 6.2312155 | C20: =IF('Profit & Loss'!C4>0,'Balance Sheet'!C17/('Profit & Loss'!C4/365),0) -> 5.714122 | D20: =IF('Profit & Loss'!D4>0,'Balance Sheet'!D17/('Profit & Loss'!D4/365),0) -> 6.6953095 | E20: =IF('Profit & Loss'!E4>0,'Balance Sheet'!E17/('Profit & Loss'!E4/365),0) -> 7.7591372 | F20: =IF('Profit & Loss'!F4>0,'Balance Sheet'!F17/('Profit & Loss'!F4/365),0) -> 5.4094623 | G20: =IF('Profit & Loss'!G4>0,'Balance Sheet'!G17/('Profit & Loss'!G4/365),0) -> 6.1721493 | H20: =IF('Profit & Loss'!H4>0,'Balance Sheet'!H17/('Profit & Loss'!H4/365),0) -> 7.1608389 | I20: =IF('Profit & Loss'!I4>0,'Balance Sheet'!I17/('Profit & Loss'!I4/365),0) -> 6.063093 | ... K20: =IF('Profit & Loss'!K4>0,'Balance Sheet'!K17/('Profit & Loss'!K4/365),0) -> 6.4479952
A21: Inventory Turnover | B21: =IF('Balance Sheet'!B18>0,'Profit & Loss'!B4/'Balance Sheet'!B18,0) -> 2.5355317 | C21: =IF('Balance Sheet'!C18>0,'Profit & Loss'!C4/'Balance Sheet'!C18,0) -> 2.6921498 | D21: =IF('Balance Sheet'!D18>0,'Profit & Loss'!D4/'Balance Sheet'!D18,0) -> 2.7207098 | E21: =IF('Balance Sheet'!E18>0,'Profit & Loss'!E4/'Balance Sheet'!E18,0) -> 2.8099198 | F21: =IF('Balance Sheet'!F18>0,'Profit & Loss'!F4/'Balance Sheet'!F18,0) -> 2.5980501 | G21: =IF('Balance Sheet'!G18>0,'Profit & Loss'!G4/'Balance Sheet'!G18,0) -> 2.574215 | H21: =IF('Balance Sheet'!H18>0,'Profit & Loss'!H4/'Balance Sheet'!H18,0) -> 2.1161731 | I21: =IF('Balance Sheet'!I18>0,'Profit & Loss'!I4/'Balance Sheet'!I18,0) -> 2.4466353 | ... K21: =IF('Balance Sheet'!K18>0,'Profit & Loss'!K4/'Balance Sheet'!K18,0) -> 2.1450468
A23: Return on Equity | B23: =IF(SUM('Balance Sheet'!B4:B5)>0,'Profit & Loss'!B12/SUM('Balance Sheet'!B4:B5),"") -> 0.19237482 | C23: =IF(SUM('Balance Sheet'!C4:C5)>0,'Profit & Loss'!C12/SUM('Balance Sheet'!C4:C5),"") -> 0.16810164 | D23: =IF(SUM('Balance Sheet'!D4:D5)>0,'Profit & Loss'!D12/SUM('Balance Sheet'!D4:D5),"") -> 0.22202685 | E23: =IF(SUM('Balance Sheet'!E4:E5)>0,'Profit & Loss'!E12/SUM('Balance Sheet'!E4:E5),"") -> 0.23132048 | F23: =IF(SUM('Balance Sheet'!F4:F5)>0,'Profit & Loss'!F12/SUM('Balance Sheet'!F4:F5),"") -> 0.22507123 | G23: =IF(SUM('Balance Sheet'!G4:G5)>0,'Profit & Loss'!G12/SUM('Balance Sheet'!G4:G5),"") -> 0.12978525 | H23: =IF(SUM('Balance Sheet'!H4:H5)>0,'Profit & Loss'!H12/SUM('Balance Sheet'!H4:H5),"") -> 0.23358057 | I23: =IF(SUM('Balance Sheet'!I4:I5)>0,'Profit & Loss'!I12/SUM('Balance Sheet'!I4:I5),"") -> 0.27423846 | ... K23: =IF(SUM('Balance Sheet'!K4:K5)>0,'Profit & Loss'!K12/SUM('Balance Sheet'!K4:K5),"") -> 0.28707846
A24: Return on Capital Emp | C24: =IF((B4+B5+B6+C4+C5+C6)>0,('Profit & Loss'!C10+'Profit & Loss'!C9)*2/(B4+B5+B6+C4+C5+C6),"") -> 0.20772046 | D24: =IF((C4+C5+C6+D4+D5+D6)>0,('Profit & Loss'!D10+'Profit & Loss'!D9)*2/(C4+C5+C6+D4+D5+D6),"") -> 0.24546167 | E24: =IF((D4+D5+D6+E4+E5+E6)>0,('Profit & Loss'!E10+'Profit & Loss'!E9)*2/(D4+D5+D6+E4+E5+E6),"") -> 0.26363518 | F24: =IF((E4+E5+E6+F4+F5+F6)>0,('Profit & Loss'!F10+'Profit & Loss'!F9)*2/(E4+E5+E6+F4+F5+F6),"") -> 0.24264301 | G24: =IF((F4+F5+F6+G4+G5+G6)>0,('Profit & Loss'!G10+'Profit & Loss'!G9)*2/(F4+F5+F6+G4+G5+G6),"") -> 0.13095951 | H24: =IF((G4+G5+G6+H4+H5+H6)>0,('Profit & Loss'!H10+'Profit & Loss'!H9)*2/(G4+G5+G6+H4+H5+H6),"") -> 0.21014371 | I24: =IF((H4+H5+H6+I4+I5+I6)>0,('Profit & Loss'!I10+'Profit & Loss'!I9)*2/(H4+H5+H6+I4+I5+I6),"") -> 0.2511906 | J24: =IF((I4+I5+I6+J4+J5+J6)>0,('Profit & Loss'!J10+'Profit & Loss'!J9)*2/(I4+I5+I6+J4+J5+J6),"") -> 0.22722642 | K24: =IF((J4+J5+J6+K4+K5+K6)>0,('Profit & Loss'!K10+'Profit & Loss'!K9)*2/(J4+J5+J6+K4+K5+K6),"") -> 0.19147971

Sheet Cash Flow
A1: ='Balance Sheet'!A1 -> TITAN COMPANY LTD | E1: =UPDATE | J1: SCREENER.IN
A3: Narration | B3: ='Data Sheet'!B81 -> 42460 | C3: ='Data Sheet'!C81 -> 42825 | D3: ='Data Sheet'!D81 -> 43190 | E3: ='Data Sheet'!E81 -> 43555 | F3: ='Data Sheet'!F81 -> 43921 | G3: ='Data Sheet'!G81 -> 44286 | H3: ='Data Sheet'!H81 -> 44651 | I3: ='Data Sheet'!I81 -> 45016 | ... K3: ='Data Sheet'!K81 -> 45747
A4: Cash from Operating Activity | B4: ='Data Sheet'!B82 -> 576.09 | C4: ='Data Sheet'!C82 -> 1712.3 | D4: ='Data Sheet'!D82 -> -51.12 | E4: ='Data Sheet'!E82 -> 1242.92 | F4: ='Data Sheet'!F82 -> -348 | G4: ='Data Sheet'!G82 -> 4139 | H4: ='Data Sheet'!H82 -> -724 | I4: ='Data Sheet'!I82 -> 1370 | ... K4: ='Data Sheet'!K82 -> -541
A5: Cash from Investing Activity | B5: ='Data Sheet'!B83 -> -158.79 | C5: ='Data Sheet'!C83 -> -953.15 | D5: ='Data Sheet'!D83 -> 97.62 | E5: ='Data Sheet'!E83 -> -796.61 | F5: ='Data Sheet'!F83 -> 235 | G5: ='Data Sheet'!G83 -> -2799 | H5: ='Data Sheet'!H83 -> 1165 | I5: ='Data Sheet'!I83 -> -1814 | ... K5: ='Data Sheet'!K83 -> 546
A6: Cash from Financing Activity | B6: ='Data Sheet'!B84 -> -504.84 | C6: ='Data Sheet'!C84 -> -165.6 | D6: ='Data Sheet'!D84 -> -252.45 | E6: ='Data Sheet'!E84 -> -488.83 | F6: ='Data Sheet'!F84 -> -242 | G6: ='Data Sheet'!G84 -> -1234 | H6: ='Data Sheet'!H84 -> -403 | I6: ='Data Sheet'!I84 -> 457 | ... K6: ='Data Sheet'!K84 -> -7
A7: Net Cash Flow | B7: ='Data Sheet'!B85 -> -87.54 | C7: ='Data Sheet'!C85 -> 593.55 | D7: ='Data Sheet'!D85 -> -205.95 | E7: ='Data Sheet'!E85 -> -42.52 | F7: ='Data Sheet'!F85 -> -355 | G7: ='Data Sheet'!G85 -> 106 | H7: ='Data Sheet'!H85 -> 38 | I7: ='Data Sheet'!I85 -> 13 | ... K7: ='Data Sheet'!K85 -> -2

Sheet Data>

Sheet Data Sheet
A1: COMPANY NAME | B1: TITAN COMPANY LTD | E1: =IF(B2<>B3, "A NEW VERSION OF THE WORKSHEET IS AVAILABLE", "")
A2: LATEST VERSION | B2: 2.1 | E2: PLEASE DO NOT MAKE ANY CHANGES TO THIS SHEET
A3: CURRENT VERSION | B3: 2.1
A5: META
A6: Number of shares | B6: =IF(B9>0, B9/B8, 0) -> 88.766701
A7: Face Value | B7: 1
A8: Current Price | B8: 4246.1
A9: Market Capitalization | B9: 376912.29
A15: PROFIT & LOSS
A16: Report Date | B16: 42460 | C16: 42825 | D16: 43190 | E16: 43555 | F16: 43921 | G16: 44286 | H16: 44651 | I16: 45016 | J16: 45382 | K16: 45747
A17: Sales | B17: 11275.89 | C17: 13260.83 | D17: 16119.77 | E17: 19778.52 | F17: 21052 | G17: 21644 | H17: 28799 | I17: 40575 | J17: 51084 | K17: 60456
A18: Raw Material Cost | B18: 8372.17 | C18: 9821.14 | D18: 12664.83 | E18: 15170.66 | F18: 16033 | G18: 16292 | H18: 26436 | I18: 32589 | J18: 42103 | K18: 55271
A19: Change in Inventory | B19: 191.43 | C19: 313.71 | D19: 978.61 | E19: 776.41 | F19: 878 | G19: -122 | H19: 4795 | I19: 2234 | J19: 2671 | K19: 7815
A20: Power and Fuel | B20: 41.2 | C20: 43.84 | D20: 45.32 | E20: 48.51 | F20: 52 | G20: 37 | H20: 45 | I20: 59 | J20: 71 | K20: 78
A21: Other Mfr. Exp | B21: 261.7 | C21: 160.42 | D21: 124.83 | E21: 193.28 | F21: 215 | G21: 141 | H21: 183 | I21: 225 | J21: 286 | K21: 326
A22: Employee Cost | B22: 699.69 | C22: 894.32 | D22: 906.26 | E22: 1024.44 | F22: 1204 | G22: 1069 | H22: 1356 | I22: 1656 | J22: 1875 | K22: 2164
A23: Selling and admin | B23: 846.43 | C23: 1211.16 | D23: 1277.81 | E23: 1454.32 | F23: 1470 | G23: 1029 | H23: 1697 | I23: 2715 | J23: 3249 | K23: 3488
A24: Other Expenses | B24: 306.8 | C24: 279.76 | D24: 435.13 | E24: 669.93 | F24: 493 | G24: 1229 | H24: 533 | I24: 683 | J24: 879 | K24: 1250
A25: Other Income | B25: 69.33 | C25: -42.38 | D25: 69.93 | E25: 178.48 | F25: 153 | G25: 180 | H25: 177 | I25: 306 | J25: 534 | K25: 487
A26: Depreciation | B26: 98.19 | C26: 110.53 | D26: 131.43 | E26: 162.84 | F26: 348 | G26: 375 | H26: 399 | I26: 441 | J26: 584 | K26: 693
A27: Interest | B27: 42.36 | C27: 37.74 | D27: 52.92 | E27: 52.54 | F27: 166 | G27: 203 | H27: 218 | I27: 300 | J27: 619 | K27: 953
... A31: Dividend Amount | B31: 195.32 | C31: 230.83 | D31: 332.92 | E31: 443.9 | F31: 356 | G31: 356 | H31: 667.5 | I31: 890 | J31: 979 | K31: 979
A33: EBITDA | B33: =B30+B29+B27+B26 -> 1006.66 | C33: =C30+C29+C27+C26 -> 1135.71 | D33: =D30+D29+D27+D26 -> 1742.31 | E33: =E30+E29+E27+E26 -> 2187.77 | F33: =F30+F29+F27+F26 -> 2624 | G33: =G30+G29+G27+G26 -> 1904 | H33: =H30+H29+H27+H26 -> 3496 | I33: =I30+I29+I27+I26 -> 5164 | ... K33: =K30+K29+K27+K26 -> 6181
A40: Quarters
A41: Report Date | B41: 45199 | C41: 45291 | D41: 45382 | E41: 45473 | F41: 45565 | G41: 45657 | H41: 45747 | I41: 45838 | J41: 45930 | K41: 46022
A42: Sales | B42: 12529 | C42: 14164 | D42: 12494 | E42: 13266 | F42: 14534 | G42: 17740 | H42: 14916 | I42: 16523 | J42: 18725 | K42: 25416
A43: Expenses | B43: 11118 | C43: 12599 | D43: 11303 | E43: 12019 | F43: 13298 | G43: 16066 | H43: 13379 | I43: 14693 | J43: 16850 | K43: 22703
A44: Other Income | B44: 125 | C44: 136 | D44: 159 | E44: 120 | F44: 123 | G44: 128 | H44: 116 | I44: 105 | J44: 113 | K44: -1
A45: Depreciation | B45: 144 | C45: 154 | D45: 158 | E45: 164 | F45: 171 | G45: 175 | H45: 183 | I45: 184 | J45: 189 | K45: 207
A46: Interest | B46: 140 | C46: 169 | D46: 201 | E46: 230 | F46: 240 | G46: 231 | H46: 252 | I46: 271 | J46: 277 | K46: 282
A47: Profit before tax | B47: 1252 | C47: 1378 | D47: 991 | E47: 973 | F47: 948 | G47: 1396 | H47: 1218 | I47: 1480 | J47: 1522 | K47: 2223
A48: Tax | B48: 336 | C48: 325 | D48: 220 | E48: 258 | F48: 244 | G48: 349 | H48: 347 | I48: 389 | J48: 402 | K48: 539
A49: Net profit | B49: 915 | C49: 1053 | D49: 771 | E49: 715 | F49: 704 | G49: 1047 | H49: 871 | I49: 1091 | J49: 1120 | K49: 1684
A50: Operating Profit | B50: 1411 | C50: 1565 | D50: 1191 | E50: 1247 | F50: 1236 | G50: 1674 | H50: 1537 | I50: 1830 | J50: 1875 | K50: 2713
A55: BALANCE SHEET
A56: Report Date | B56: 42460 | C56: 42825 | D56: 43190 | E56: 43555 | F56: 43921 | G56: 44286 | H56: 44651 | I56: 45016 | J56: 45382 | K56: 45747
A57: Equity Share Capital | B57: 88.78 | C57: 88.78 | D57: 88.78 | E57: 88.78 | F57: 89 | G57: 89 | H57: 89 | I57: 89 | J57: 89 | K57: 89
A58: Reserves | B58: 3417.5 | C58: 4143.6 | D58: 5001.1 | E58: 5981.37 | F58: 6580 | G58: 7408 | H58: 9214 | I58: 11762 | J58: 9304 | K58: 11535
A59: Borrowings | B59: 113.05 | C59: 1882.43 | D59: 1691.01 | E59: 2392.98 | F59: 3562 | G59: 5638 | H59: 7275 | I59: 9367 | J59: 15528 | K59: 20777
A60: Other Liabilities | B60: 2722.58 | C60: 2292.76 | D60: 2740.15 | E60: 3246.71 | F60: 3313 | G60: 3309 | H60: 4610 | I60: 5802 | J60: 6626 | K60: 8244
A61: Total | B61: 6341.91 | C61: 8407.57 | D61: 9521.04 | E61: 11709.84 | F61: 13544 | G61: 16444 | H61: 21188 | I61: 27020 | J61: 31547 | K61: 40645
A62: Net Block | B62: 770.54 | C62: 1188.72 | D62: 1473.81 | E62: 1566.63 | F62: 2633 | G62: 2523 | H62: 2544 | I62: 2998 | J62: 3709 | K62: 4062
A63: Capital Work in Progress | B63: 106.71 | C63: 152.07 | D63: 43.37 | E63: 31.77 | F63: 18 | G63: 32 | H63: 85 | I63: 144 | J63: 97 | K63: 105
A64: Investments | B64: 30.41 | C64: 430.73 | D64: 35.99 | E64: 108.42 | F64: 158 | G64: 2824 | H64: 294 | I64: 2515 | J64: 2345 | K64: 1988
A65: Other Assets | B65: 5434.25 | C65: 6636.05 | D65: 7967.87 | E65: 10003.02 | F65: 10735 | G65: 11065 | H65: 18265 | I65: 21363 | J65: 25396 | K65: 34490
A66: Total | B66: 6341.91 | C66: 8407.57 | D66: 9521.04 | E66: 11709.84 | F66: 13544 | G66: 16444 | H66: 21188 | I66: 27020 | J66: 31547 | K66: 40645
A67: Receivables | B67: 192.5 | C67: 207.6 | D67: 295.69 | E67: 420.45 | F67: 312 | G67: 366 | H67: 565 | I67: 674 | J67: 1018 | K67: 1068
... A70: No. of Equity Shares | B70: 887786160 | C70: 887786160 | D70: 887786160 | E70: 887786160 | F70: 887786160 | G70: 887786160 | H70: 887786160 | I70: 890000000 | J70: 890000000 | K70: 890000000
A71: New Bonus Shares
A72: Face value | B72: 1 | C72: 1 | D72: 1 | E72: 1 | F72: 1 | G72: 1 | H72: 1 | I72: 1 | J72: 1 | K72: 1
A74: Other Assets ( w/o cash n equi.) | B74: =B65-SUM(B67:B69) -> 678.25 | C74: =C65-SUM(C67:C69) -> 723.78 | D74: =D65-SUM(D67:D69) -> 1129.43 | E74: =E65-SUM(E67:E69) -> 1477.27 | F74: =F65-SUM(F67:F69) -> 1939 | G74: =G65-SUM(G67:G69) -> 1731 | H74: =H65-SUM(H67:H69) -> 2518 | I74: =I65-SUM(I67:I69) -> 2762 | ... K74: =K65-SUM(K67:K69) -> 3654
A76: Total Assets | B76: =B61 -> 6341.91 | C76: =C61 -> 8407.57 | D76: =D61 -> 9521.04 | E76: =E61 -> 11709.84 | F76: =F61 -> 13544 | G76: =G61 -> 16444 | H76: =H61 -> 21188 | I76: =I61 -> 27020 | ... K76: =K61 -> 40645
A80: CASH FLOW:
A81: Report Date | B81: 42460 | C81: 42825 | D81: 43190 | E81: 43555 | F81: 43921 | G81: 44286 | H81: 44651 | I81: 45016 | J81: 45382 | K81: 45747
A82: Cash from Operating Activity | B82: 576.09 | C82: 1712.3 | D82: -51.12 | E82: 1242.92 | F82: -348 | G82: 4139 | H82: -724 | I82: 1370 | J82: 1695 | K82: -541
A83: Cash from Investing Activity | B83: -158.79 | C83: -953.15 | D83: 97.62 | E83: -796.61 | F83: 235 | G83: -2799 | H83: 1165 | I83: -1814 | J83: -189 | K83: 546
A84: Cash from Financing Activity | B84: -504.84 | C84: -165.6 | D84: -252.45 | E84: -488.83 | F84: -242 | G84: -1234 | H84: -403 | I84: 457 | J84: -1329 | K84: -7
A85: Net Cash Flow | B85: -87.54 | C85: 593.55 | D85: -205.95 | E85: -42.52 | F85: -355 | G85: 106 | H85: 38 | I85: 13 | J85: 177 | K85: -2
A90: PRICE: | B90: 338.8 | C90: 462.75 | D90: 942.3 | E90: 1141.85 | F90: 933.7 | G90: 1558.05 | H90: 2536.15 | I90: 2514.9 | J90: 3801.8 | K90: 3063.35
A92: DERIVED:
A93: Adjusted Equity Shares in Cr | B93: 88.78 | C93: 88.78 | D93: 88.78 | E93: 88.78 | F93: 88.78 | G93: 88.78 | H93: 88.78 | I93: 88.78 | J93: 88.78 | K93: 88.78
